Workbook

Sheet AMK SETTLEMENT CALC NEW
A3: MONTH/YEAR: | B3: 46023 | E3: MONTH/YEAR: | F3: =B3 | I3: MONTH/YEAR: | J3: =B3 | M3: MONTH/YEAR: | N3: =B3 | Q3: MONTH/YEAR: | R3: =B3 | U3: MONTH/YEAR: | V3: =B3 | Y3: MONTH/YEAR: | Z3: =B3 | AD3: MONTH/YEAR: | AE3: =B3 | AI3: MONTH/YEAR: | AJ3: =AE3
A4: BRANCH: | B4: CASA DENTAL AMK PTE LTD | E4: BRANCH: | F4: CASA DENTAL AMK PTE LTD | I4: BRANCH: | J4: CASA DENTAL AMK PTE LTD | M4: BRANCH: | N4: CASA DENTAL AMK PTE LTD | Q4: BRANCH: | R4: CASA DENTAL AMK PTE LTD | U4: BRANCH: | V4: CASA DENTAL AMK PTE LTD | Y4: BRANCH: | Z4: CASA DENTAL AMK PTE LTD | AD4: BRANCH: | AE4: CASA DENTAL AMK PTE LTD | AI4: BRANCH: | AJ4: CASA DENTAL AMK PTE LTD
A5: ALL PROVIDERS SETTLEMENT | E5: DR CHAN | I5: DR JASMINE | M5: DR JIAWEN | Q5: DR KALIE | U5: DR JOLEEN | Y5: DR BRANDON | AD5: DR JEAN CHONG | AI5: DR ANDREW YIN
C6: ADMIN CHARGES | G6: ADMIN CHARGES | J6: TOTALS | K6: ADMIN CHARGES | O6: ADMIN CHARGES | S6: ADMIN CHARGES | W6: ADMIN CHARGES | AA6: ADMIN CHARGES | AF6: ADMIN CHARGES | AK6: ADMIN CHARGES
A7: AIA | B7: None_test | C7: =B7*0.05*1.09 | E7: AIA | G7: =F7*0.05*1.09 | I7: AIA | K7: =J7*0.05*1.09 | M7: AIA | O7: =N7*0.05*1.09 | Q7: AIA | S7: =R7*0.05*1.09 | U7: AIA | W7: =V7*0.05*1.09 | Y7: AIA | AA7: =Z7*0.05*1.09 | AD7: AIA | AF7: =AE7*0.05*1.09 | AI7: AIA | AK7: =AJ7*0.05*1.09
A8: ALLIANCE | C8: =B8*0.05*1.09 | E8: ALLIANCE | G8: =F8*0.05*1.09 | I8: ALLIANCE | K8: =J8*0.05*1.09 | M8: ALLIANCE | O8: =N8*0.05*1.09 | U8: ALLIANCE | W8: =V8*0.05*1.09 | Y8: ALLIANCE | AA8: =Z8*0.05*1.09 | AD8: ALLIANCE | AF8: =AE8*0.05*1.09
A9: AMEX | C9: =B9*0.0195 | E9: AMEX | G9: =F9*0.0195 | I9: AMEX | K9: =J9*0.0195 | M9: AMEX | O9: =N9*0.0195 | Q9: AMEX | S9: =R9*0.0195 | U9: AMEX | W9: =V9*0.0195 | Y9: AMEX | AA9: =Z9*0.0195 | AD9: AMEX | AF9: =AE9*0.0195 | AI9: AMEX | AK9: =AJ9*0.0195
A10: BABYBONUS | C10: =B10*0.008 | E10: BABYBONUS | G10: =F10*0.008 | I10: BABYBONUS | K10: =J10*0.008 | M10: BABYBONUS | O10: =N10*0.008 | U10: BABYBONUS | W10: =V10*0.008 | Y10: BABYBONUS | AA10: =Z10*0.008 | AD10: BABYBONUS | AF10: =AE10*0.008
A11: CASH | E11: CASH | I11: CASH | M11: CASH | Q11: ALLIANCE | S11: =R11*0.05*1.09 | U11: CASH | Y11: CASH | AD11: CASH | AI11: ALLIANCE | AK11: =AJ11*0.05*1.09
A12: CASA VOUCHER | E12: CASA VOUCHER | I12: CASA VOUCHER | M12: CASA VOUCHER | Q12: CASH | U12: CASA VOUCHER | Y12: CASA VOUCHER | AD12: CASA VOUCHER | AI12: CASH
A13: CDC VOUCHER | E13: CDC VOUCHER | I13: CDC VOUCHER | M13: CDC VOUCHER | Q13: CASA VOUCHER | U13: CDC VOUCHER | Y13: CDC VOUCHER | AD13: CDC VOUCHER | AI13: CASA VOUCHER
A14: CHAS | E14: CHAS | I14: CHAS | M14: CHAS | U14: CHAS | Y14: CHAS | AD14: CHAS
A15: CYNERGY | E15: CYNERGY | I15: CYNERGY | M15: CYNERGY | U15: CYNERGY | Y15: CYNERGY | AD15: CYNERGY
A16: DA ADEPT HEALTH | C16: =B16*8% | E16: DA ADEPT HEALTH | G16: =F16*8% | I16: DA ADEPT HEALTH | K16: =J16*8% | M16: DA ADEPT HEALTH | O16: =N16*8% | U16: DA ADEPT HEALTH | W16: =V16*8% | Y16: DA ADEPT HEALTH | AA16: =Z16*8% | AD16: DA ADEPT HEALTH | AF16: =AE16*8%
A17: DEPOSIT | C17: =G17+K17+O17+O17+S17+W17+AA17+AF17 | E17: DEPOSIT | I17: DEPOSIT | M17: DEPOSIT | Q17: DEPOSIT | S17: 0 | U17: DEPOSIT | Y17: DEPOSIT | AD17: DEPOSIT | AI17: DEPOSIT
A18: IHP | C18: =B18*0.051*1.09 | E18: IHP | G18: =F18*0.051*1.09 | I18: IHP | K18: =J18*0.051*1.09 | M18: IHP | O18: =N18*0.051*1.09 | U18: IHP | W18: =V18*0.051*1.09 | Y18: IHP | AA18: =Z18*0.051*1.09 | AD18: IHP | AF18: =AE18*0.051*1.09
A19: JCB | C19: =B19*0.15*1.09 | E19: JCB | G19: =F19*0.15*1.09 | I19: JCB | K19: =J19*0.15*1.09 | M19: JCB | O19: =N19*0.15*1.09 | U19: JCB | W19: =V19*0.15*1.09 | Y19: JCB | AA19: =Z19*0.15*1.09 | AD19: JCB | AF19: =AE19*0.15*1.09
A20: MASTER | C20: =B20*0.021 | E20: MASTER | G20: =F20*0.021 | I20: MASTER | K20: =J20*0.021 | M20: MASTER | O20: =N20*0.021 | U20: MASTER | W20: =V20*0.021 | Y20: MASTER | AA20: =Z20*0.021 | AD20: MASTER | AF20: =AE20*0.021
A21: MEDISAVE | E21: MEDISAVE | I21: MEDISAVE | M21: MEDISAVE | U21: MEDISAVE | Y21: MEDISAVE | AD21: MEDISAVE
A22: mednefits | C22: =B22*20% | E22: mednefits | G22: =F22*20% | I22: mednefits | K22: =J22*20% | M22: mednefits | O22: =N22*20% | U22: mednefits | W22: =V22*20% | Y22: mednefits | AA22: =Z22*20% | AD22: mednefits | AF22: =AE22*20%
A23: MHC | C23: =B23*0.15*1.09 | E23: MHC | G23: =F23*0.15*1.09 | I23: MHC | K23: =J23*0.15*1.09 | M23: MHC | O23: =N23*0.15*1.09 | U23: MHC | W23: =V23*0.15*1.09 | Y23: MHC | AA23: =Z23*0.15*1.09 | AD23: MHC | AF23: =AE23*0.15*1.09
A24: NETS | C24: =B24*0.008 | E24: NETS | G24: =F24*0.008 | I24: NETS | K24: =J24*0.008 | M24: NETS | O24: =N24*0.008 | U24: NETS | W24: =V24*0.008 | Y24: NETS | AA24: =Z24*0.008 | AD24: NETS | AF24: =AE24*0.008
A25: PARKWAY | E25: PARKWAY | G25: =F25*10% | I25: PARKWAY | K25: =J25*10% | M25: PARKWAY | O25: =N25*10% | U25: PARKWAY | W25: =V25*10% | Y25: PARKWAY | AA25: =Z25*10% | AD25: PARKWAY | AF25: =AE25*10%
A26: PAYNOW | E26: PAYNOW | I26: PAYNOW | M26: PAYNOW | U26: PAYNOW | Y26: PAYNOW | AD26: PAYNOW
A27: RHI | E27: RHI | I27: RHI | M27: RHI | U27: RHI | Y27: RHI | AD27: RHI
A28: SAH | C28: =B28*8% | E28: SAH | G28: =F28*8% | I28: SAH | K28: =J28*8% | M28: SAH | O28: =N28*8% | U28: SAH | W28: =V28*8% | Y28: SAH | AA28: =Z28*8% | AD28: SAH | AF28: =AE28*8%
A29: UNION PAY | C29: =B29*2.5% | E29: UNION PAY | G29: =F29*2.5% | I29: UNION PAY | K29: =J29*2.5% | M29: UNION PAY | O29: =N29*2.5% | U29: UNION PAY | W29: =V29*2.5% | Y29: UNION PAY | AA29: =Z29*2.5% | AD29: UNION PAY | AF29: =AE29*2.5%
A30: VISA | C30: =B30*0.021 | E30: VISA | G30: =F30*0.021 | I30: VISA | K30: =J30*0.021 | M30: VISA | O30: =N30*0.021 | U30: VISA | W30: =V30*0.021 | Y30: VISA | AA30: =Z30*0.021 | AD30: VISA | AF30: =AE30*0.021
A31: TOTAL INCOME | B31: =SUM(B7:B30) | C31: =SUM(C7:C30) | E31: DR TOTAL INCOME | F31: =SUM(F7:F30) | G31: =SUM(G7:G30) | I31: DR TOTAL INCOME | J31: =SUM(J7:J30) | K31: =SUM(K7:K30) | M31: DR TOTAL INCOME | N31: =SUM(N7:N30) | O31: =SUM(O7:O30) | U31: DR TOTAL INCOME | V31: =SUM(V7:V30) | W31: =SUM(W7:W30) | Y31: DR TOTAL INCOME | Z31: =SUM(Z7:Z30) | AA31: =SUM(AA7:AA30) | AD31: DR TOTAL INCOME | AE31: =SUM(AE7:AE30) | AF31: =SUM(AF7:AF30)
B33: EXPENSES | F33: DEDUCTIONS | H33: REMARKS | J33: DEDUCTIONS | L33: REMARKS | N33: DEDUCTIONS | P33: REMARKS | R33: DEDUCTIONS | T33: REMARKS | V33: DEDUCTIONS | X33: REMARKS | Z33: DEDUCTIONS | AB33: REMARKS | AE33: DEDUCTIONS | AG33: REMARKS | AJ33: DEDUCTIONS | AL33: REMARKS
B34: ADMIN FEE | C34: =SUM(C7:C30) | F34: ADMIN CHARGES | G34: =G31 | J34: ADMIN CHARGES | K34: =K31 | N34: ADMIN CHARGES | O34: =O31 | R34: ADMIN CHARGES | S34: =#REF! | V34: ADMIN CHARGES | W34: =W31 | Z34: ADMIN CHARGES | AA34: =AA31 | AE34: ADMIN CHARGES | AF34: =AF31 | AJ34: ADMIN CHARGES | AK34: =#REF!
B35: GST | C35: =G35+K35+O35+S35+W35+AA35+AF35+AK35 | F35: GST | J35: GST | N35: GST | R35: GST | V35: GST | Z35: GST | AE35: GST | AJ35: GST
B36: RENTAL | F36: ICC-5 | J36: ICC-5 | N36: ICC-5 | V36: ICC-5 | Z36: ICC-5 | AE36: ICC-5
B37: LOAN INTEREST | F37: PRODUCTS | J37: PRODUCTS | N37: PRODUCTS | V37: PRODUCTS | Z37: PRODUCTS | AE37: PRODUCTS
B38: NEW CATEGORY | C38: Amount
B39: IRAS TAX | F39: ORTHO (B+B) | J39: ORTHO (B+B) | N39: ORTHO (B+B) | V39: ORTHO (B+B) | Z39: ORTHO (B+B) | AE39: ORTHO (B+B)
B40: CK SECRETARIAL / ACCOUNTS SERVICES | F40: ABUTMENTS | J40: ABUTMENTS | N40: ABUTMENTS | V40: ABUTMENTS | Z40: ABUTMENTS | AE40: ABUTMENTS
B41: TOWN COUNCIL | C41: =160.5+103.75 | F41: IMPLANT | J41: IMPLANT | N41: IMPLANT | V41: IMPLANT | Z41: IMPLANT | AE41: IMPLANT
B42: SERVICE & CONSERVANCY CHARGES | C42: 400 | F42: SKY LAB | J42: SKY LAB | N42: SKY LAB | V42: SKY LAB | Z42: SKY LAB | AE42: SKY LAB
B43: SP | F43: DIGICADCAM | J43: DIGICADCAM | N43: DIGICADCAM | V43: DIGICADCAM | Z43: DIGICADCAM | AE43: DIGICADCAM
B44: SINGTEL | F44: OTHER LAB | J44: OTHER LAB | N44: OTHER LAB | V44: OTHER LAB | Z44: OTHER LAB | AE44: OTHER LAB
B45: PRODUCTS | C45: =G37+K37+O37+S60+W37+AA37+AF37+AK60 | F45: INVISALIGN | J45: INVISALIGN | N45: INVISALIGN | V45: INVISALIGN | Z45: INVISALIGN | AE45: INVISALIGN
B46: ADMIN STAFF & OFFICE RENTAL | F46: TRANSFER (+) | J46: TRANSFER (+) | N46: TRANSFER (+) | V46: TRANSFER (+) | Z46: TRANSFER (+) | AE46: TRANSFER (+)
B47: SUPPLIERS | F47: TRANSFER (-) | J47: TRANSFER (-) | N47: TRANSFER (-) | V47: TRANSFER (-) | Z47: TRANSFER (-) | AE47: TRANSFER (-)
B48: VOUCHER | C48: =B12 | F48: REFUND/REFERRAL | J48: REFUND/REFERRAL | N48: REFUND/REFERRAL | V48: REFUND | Z48: REFUND | AE48: REFUND
B49: PETTY CASH | F49: VOUCHER | J49: VOUCHER | N49: VOUCHER | V49: VOUCHER | Z49: VOUCHER | AE49: SEDATION
B50: STOCKS / CONSUMABLES FEES | F50: RETAINERS/BT/SPLINT | J50: RETAINERS/BT/SPLINT | N50: RETAINERS/BT/SPLINT | V50: RETAINERS/BT/SPLINT | Z50: RETAINERS/BT/SPLINT | AE50: RETAINERS/BT/SPLINT
B51: MARKETING FEE | F51: INSTALLMENT | J51: INSTALLMENT | N51: INSTALLMENT | V51: INSTALLMENT | Z51: INSTALLMENT | AE51: INSTALLMENT
B52: INVISALIGN | C52: =G45+K45+O45+S67+W45+AA45+AF45+AK67 | F52: DEDUCTIONS | J52: DEDUCTIONS | N52: DEDUCTIONS | V52: DEDUCTIONS | Z52: DEDUCTIONS | AE52: DEDUCTIONS
B53: IMPLANT | C53: =G41+O41+S63+W41+AA41+AF41+K41+AK63
B54: SKYLAB | C54: =G42+O42+W42+S64+K42+AA42+AF42+AK64 | F54: TOTAL | G54: =F31-G34-G35-G37-G36-G39-G40-G41-G42-G43-G44-G45+G46-G47-G48-G49-G50-G51-G52 | J54: TOTAL | K54: =J31-K34-K35-K36-K37-K39-K40-K41-K42-K43-K44-K45+K46-K47-K48-K49-K50-K51-K52 | N54: TOTAL | O54: =N31-O34-O35-O36-O37-O39-O40-O41-O42-O43-O44-O45+O46-O47-O48-O49-O50-O51-O52 | V54: TOTAL | W54: =V31-W34-W35-W36-W37-W39-W40-W41-W42-W43-W44-W45+W46-W47-W48-W49-W50-W51-W52 | Z54: TOTAL | AA54: =Z31-AA34-AA35-AA36-AA37-AA39-AA40-AA41-AA42-AA43-AA44-AA45+AA46-AA47-AA48-AA49-AA50-AA51-AA52 | AE54: TOTAL | AF54: =AE31-AF34-AF35-AF36-AF37-AF39-AF40-AF41-AF42-AF43-AF44-AF45+AF46-AF47-AF48-AF49-AF50-AF51-AF52
B55: DIGICADCAM | C55: =G43+O43+W43+AA43+AF43+S65+K43+AK65 | F55: DOCTORS FEE BEFORE DEDUCTION | G55: =G54/2+G56 | J55: DOCTORS FEE BEFORE DEDUCTION | K55: =K54/2+K56 | N55: DOCTORS PAY | O55: =(O54*40%)+O56 | V55: DOCTORS PAY | W55: =(W54*50%)+W56 | Z55: DOCTORS PAY | AA55: =(AA54*45%)+AA56 | AE55: DOCTORS PAY | AF55: =(AF54*45%)+AF56
B56: OTHER LAB | C56: =G44+O44+K44+S66+W44+AA44+AF44+AK66 | F56: ADJUSTMENTS (+) | J56: ADJUSTMENTS (+) | N56: ADJUSTMENTS (+) | V56: ADJUSTMENTS (+) | Z56: ADJUSTMENTS (+) | AE56: ADJUSTMENTS (+)
B57: ORTHO (B+B) | C57: =G39+K39+O39+S61+W39+AA39+AF39+AK61 | F57: ADJUSTMENTS (-) | G57: =G62+G66 | H57: ADDN MARKETING& MEDISAVE ADMIN | J57: ADJUSTMENTS (-) | K57: =K62+K66 | L57: ADDN MARKETING | N57: ADJUSTMENTS (-) | O57: =O62+O66 | P57: ADDN MARKETING & MEDISAVE ADMIN | V57: ADJUSTMENTS (-) | W57: =W62+W66 | X57: ADDN MKTRG & MEDISAVE ADMIN | Z57: ADJUSTMENTS (-) | AA57: =AA62+AA66 | AB57: MEDISAVE ADMIN | AE57: ADJUSTMENTS (-) | AF57: =AF62+AF66 | AG57: MARKETING FEE & MEDISAVE ADMIN
B58: ABUTMENT | C58: =O40+G40+K40+S62+AA40+W40+AF40+AK62 | F58: NET PAY | G58: =G55-G57 | J58: NET PAY | K58: =K55-K57 | N58: NET PAY | O58: =O55-O57 | V58: NET PAY | W58: =W55-W57 | Z58: NET PAY | AA58: =AA55-AA57 | AE58: NET PAY | AF58: =AF55-AF57
B59: REFUND / REFERRAL | C59: =G48+K48+O48+S70+W48+AA48+AF48+AK70 | R59: ICC-5 | AJ59: ICC-5
B60: DOCTORS PAY | C60: =G55+K55+O55+W55+AA55+AF55 | F60: MEDISAVE ADMIN FEE CALCULATION: | J60: MEDISAVE ADMIN FEE CALCULATION: | N60: MEDISAVE ADMIN FEE CALCULATION: | R60: PRODUCTS | V60: MEDISAVE ADMIN FEE CALCULATION: | Z60: MEDISAVE ADMIN FEE CALCULATION: | AE60: MEDISAVE ADMIN FEE CALCULATION: | AJ60: PRODUCTS
B61: NURSE PAY (BASIC PAY) | F61: Medisave Claim | G61: Admin Fee | H61: REMARKS | J61: Medisave Claim | K61: Admin Fee | L61: REMARKS | N61: Medisave Claim | O61: Admin Fee | P61: REMARKS | R61: ORTHO (B+B) | V61: Medisave Claim | W61: Admin Fee | X61: REMARKS | Z61: Medisave Claim | AA61: Admin Fee | AB61: REMARKS | AE61: Medisave Claim | AF61: Admin Fee | AG61: REMARKS | AJ61: ORTHO (B+B)
B62: NURSE PAY (INCENTIVE) | G62: =F62*20 | K62: =J62*20 | O62: =N62*20 | R62: ABUTMENTS | W62: =V62*20 | AA62: =Z62*20 | AF62: =AE62*20 | AJ62: ABUTMENTS
B63: NURSE TRANSFER FEE | R63: IMPLANT | AJ63: IMPLANT
B64: TANK CULTURE | C64: 163.5 | F64: ADDITIONAL MARKETING: | J64: ADDITIONAL MARKETING: | N64: ADDITIONAL MARKETING: | R64: SKY LAB | V64: ADDITIONAL MARKETING: | Z64: ADDITIONAL MARKETING: | AE64: ADDITIONAL MARKETING: | AJ64: SKY LAB
B65: SHARP BIN | F65: MONTH | G65: AMOUNT | H65: REMARKS | J65: MONTH | K65: AMOUNT | L65: REMARKS | N65: MONTH | O65: AMOUNT | P65: REMARKS | R65: DIGICADCAM | V65: MONTH | W65: AMOUNT | X65: REMARKS | Z65: MONTH | AA65: AMOUNT | AB65: REMARKS | AE65: MONTH | AF65: AMOUNT | AG65: REMARKS | AJ65: DIGICADCAM
B66: COURIER | C66: 129.44 | F66: =B3 | G66: 300 | J66: =F66 | K66: 120 | N66: =F66 | O66: 150 | R66: OTHER LAB | V66: =V3 | W66: 180 | Z66: =V66 | AA66: 120 | AE66: =AE3 | AF66: 180 | AJ66: OTHER LAB
B67: REPAIR & MAINTENANCE | R67: INVISALIGN | AJ67: INVISALIGN
B68: MOM LEVY | C68: =400+400 | F68: OTHERS: (CPF,PERSONAL REFUND, COURSEFEE) | J68: OTHERS: (CPF,PERSONAL REFUND, COURSEFEE) | N68: OTHERS: (CPF,PERSONAL REFUND, COURSEFEE) | R68: TRANSFER (+) | V68: OTHERS: (CPF,PERSONAL REFUND, COURSEFEE) | Z68: OTHERS: (CPF,PERSONAL REFUND, COURSEFEE) | AE68: OTHERS: (CPF,PERSONAL REFUND, COURSEFEE) | AJ68: TRANSFER (+)
B69: NEW CATEGORY | C69: AMOUNT | R69: TRANSFER (-) | AJ69: TRANSFER (-)
F70: DETAILS | G70: AMOUNT | J70: DETAILS | K70: AMOUNT | N70: DETAILS | O70: AMOUNT | R70: REFUND | V70: DETAILS | W70: AMOUNT | Z70: DETAILS | AA70: AMOUNT | AE70: DETAILS | AF70: AMOUNT | AJ70: REFUND
R71: VOUCHER | AE71: CPF | AF71: =1800+306 | AH71: feb 2191 | AJ71: SEDATION
R72: RETAINERS/BT/SPLINT | AJ72: RETAINERS/BT/SPLINT
B73: TOTAL | C73: =B31-C34-C35-C59-C36-C37-C43-C44-C39-C47-C40-C46-C49-C50-C52-C51-C56-C55-C54-C60-C61-C62-C63-C48-C64-C41-C65-C42-C68-C67-C66-C91-C92-C93-C94-C95-C96-C69-C70-C71 | R73: INSTALLMENT | AJ73: INSTALLMENT
B74: FOR INCENTIVE % | C74: =B31-C34-C35-C59-C43-C44-C47-C46-C49-C45-C50-C51-C48-C64-C41-C65-C42-C66-C94-C96-C95-C67-C93-C91-C69-C70-C71 | R74: DEDUCTIONS | AJ74: DEDUCTIONS
B75: PERCENT | C75: =VLOOKUP(C74,'% RATES INCENTIVES AMK'!C:D,2,TRUE)
A76: INCOME LESS GST | B76: =B31-C35 | C76: =C73/B76*100 | D76: % | R76: TOTAL | S76: =#REF!-S34-S35-S60-S59-S61-S62-S63-S64-S65-S66-S67+S68-S69-S70-S71-S72-S73-S74 | AJ76: TOTAL | AK76: =#REF!-AK34-AK35-AK59-AK60-AK61-AK62-AK63-AK64-AK65-AK66-AK67+AK68-AK69-AK70-AK71-AK72-AK73-AK74
R77: DOCTORS PAY | S77: =(S76*50%)+S78 | AJ77: DOCTORS PAY | AK77: =(AK76*50%)+AK78
B78: MEDISAVE ADMIN | C78: =G62+K62+O62+S84+W62+AA62+AF62+AK84 | D78: =C78/20 | F78: TOTAL PAYMENT | G78: =G58-G71-G75-G76-G72-G73-G74 | J78: TOTAL PAYMENT | K78: =K58-K71-K75-K76-K72-K73-K74 | N78: TOTAL PAYMENT | O78: =O58-O71-O75-O76-O72-O73-O74 | R78: ADJUSTMENTS (+) | V78: TOTAL PAYMENT | W78: =W58-W71-W75-W76-W72-W73-W74 | Z78: TOTAL PAYMENT | AA78: =AA58-AA71-AA75-AA76-AA72-AA73-AA74 | AE78: TOTAL PAYMENT | AF78: =AF58-AF71-AF75-AF76-AF72-AF73-AF74 | AJ78: ADJUSTMENTS (+)
B79: ADDITIONAL MARKETING | C79: =G66+K66+O66+S88+W66+AA66+AF66 | R79: ADJUSTMENTS (-) | S79: =S84+S88 | AJ79: ADJUSTMENTS (-) | AK79: =AK84+AK88 | AL79: MARKETING FEE & MEDISAVE ADMIN
B80: DOCTORS PERSONAL DEDUCTION | C80: =G71+G75+G76+K71+K75+K76+O71+O75+O76+S93+S97+S98+W71+W75+W76+AA71+AA75+AA76+AF71+AF75+AF76+G72+G73+G74+K72+K73+K74+O72+O73+O74+S94+S95+S96+W72+W73+W74+AA72+AA73+AA74+AF72+AF73+AF74 | R80: NET PAY | S80: =S77-S79 | AJ80: NET PAY | AK80: =AK77-AK79
B81: TOTAL | C81: =SUM(C78:C80)
B82: TOTAL ICC-5 | C82: =G36+K36+O36+S59+AA36+W36+AF36 | R82: MEDISAVE ADMIN FEE CALCULATION: | AJ82: MEDISAVE ADMIN FEE CALCULATION:
R83: Medisave Claim | S83: Admin Fee | T83: REMARKS | AJ83: Medisave Claim | AK83: Admin Fee | AL83: REMARKS
B84: NURSES FEE-REVENUE | C84: =(C61+C62+C63)/B31 | S84: =R84*20 | AK84: =AJ84*20
B85: CONSUMABLE EXCL OFFICE RENT - REVENUE | C85: =(C50+C47+C49)/B31
B86: OFFICE RENT & ADMIN STAFF - REVENUE | C86: =(C46/B31) | R86: ADDITIONAL MARKETING: | AJ86: ADDITIONAL MARKETING:
B87: MARKETING - REVENUE | C87: =C51/B31 | R87: MONTH | S87: AMOUNT | T87: REMARKS | AJ87: MONTH | AK87: AMOUNT | AL87: REMARKS
R88: =R3 | AJ88: =AJ3
R90: OTHERS: (CPF,PERSONAL REFUND, COURSEFEE) | AJ90: OTHERS: (CPF,PERSONAL REFUND, COURSEFEE)
R92: DETAILS | S92: AMOUNT | AJ92: DETAILS | AK92: AMOUNT
AH93: feb 2191
R100: TOTAL CHEQUE AMOUNT | S100: =S80-S93-S97-S98-S94-S95-S96 | AJ100: TOTAL CHEQUE AMOUNT | AK100: =AK80-AK93-AK97-AK98-AK94-AK95-AK96

Sheet CLEMENTI SETTLEMENT CALC NEW
A3: MONTH/YEAR: | B3: 46023 | E3: MONTH/YEAR: | F3: =B3 | I3: MONTH/YEAR: | J3: =B3 | M3: MONTH/YEAR: | N3: =B3 | Q3: MONTH/YEAR: | R3: =B3 | U3: MONTH/YEAR: | V3: =B3 | Y3: MONTH/YEAR: | Z3: =B3 | AD3: MONTH/YEAR: | AE3: =B3 | AI3: MONTH/YEAR: | AJ3: =AE3 | AN3: MONTH/YEAR: | AO3: =AE3 | AS3: MONTH/YEAR: | AT3: =AO3 | AX3: MONTH/YEAR: | AY3: =V3
A4: BRANCH: | B4: CASA DENTAL CLEMENTI PTE LTD | E4: BRANCH: | F4: =B4 | I4: BRANCH: | J4: =B4 | M4: BRANCH: | N4: =B4 | Q4: BRANCH: | R4: CASA DENTAL AMK PTE LTD | U4: BRANCH: | V4: =B4 | Y4: BRANCH: | Z4: =B4 | AD4: BRANCH: | AE4: =B4 | AI4: BRANCH: | AJ4: CASA DENTAL AMK PTE LTD | AN4: BRANCH: | AO4: =AE4 | AS4: BRANCH: | AT4: =AO4 | AX4: BRANCH: | AY4: =V4
A5: ALL PROVIDERS SETTLEMENT | E5: DR CHAN KC | I5: DR JASMINE LEE | M5: DR ROCKY LEUNG | Q5: DR KALIE | U5: DR PETER KEITH | Y5: DR HUANG JIAWEN | AD5: DR ANG LI EN | AI5: DR ANDREW YIN | AN5: DR KAREN LEONG | AS5: DR JOLEEN NGOI | AX5: DR CHARLENE YAP
C6: ADMIN CHARGES | G6: ADMIN CHARGES | J6: TOTALS | K6: ADMIN CHARGES | O6: ADMIN CHARGES | S6: ADMIN CHARGES | W6: ADMIN CHARGES | AA6: ADMIN CHARGES | AF6: ADMIN CHARGES | AK6: ADMIN CHARGES | AP6: ADMIN CHARGES | AU6: ADMIN CHARGES | AZ6: ADMIN CHARGES
A7: AIA | C7: =B7*0.05*1.09 | E7: AIA | G7: =F7*0.05*1.09 | I7: AIA | K7: =J7*0.05*1.09 | M7: AIA | O7: =N7*0.05*1.09 | Q7: AIA | S7: =R7*0.05*1.09 | U7: AIA | W7: =V7*0.05*1.09 | Y7: AIA | AA7: =Z7*0.05*1.09 | AD7: AIA | AF7: =AE7*0.05*1.09 | AI7: AIA | AK7: =AJ7*0.05*1.09 | AN7: AIA | AP7: =AO7*0.05*1.09 | AS7: AIA | AU7: =AT7*0.05*1.09 | AX7: AIA | AZ7: =AY7*0.05*1.09
A8: ALLIANCE | C8: =B8*0.05*1.09 | E8: ALLIANCE | G8: =F8*0.05*1.09 | I8: ALLIANCE | K8: =J8*0.05*1.09 | M8: ALLIANCE | O8: =N8*0.05*1.09 | U8: ALLIANCE | W8: =V8*0.05*1.09 | Y8: ALLIANCE | AA8: =Z8*0.05*1.09 | AD8: ALLIANCE | AF8: =AE8*0.05*1.09 | AN8: ALLIANCE | AP8: =AO8*0.05*1.09 | AS8: ALLIANCE | AU8: =AT8*0.05*1.09 | AX8: ALLIANCE | AZ8: =AY8*0.05*1.09
A9: AMEX | C9: =B9*0.0195 | E9: AMEX | G9: =F9*0.0195 | I9: AMEX | K9: =J9*0.0195 | M9: AMEX | O9: =N9*0.0195 | Q9: AMEX | S9: =R9*0.0195 | U9: AMEX | W9: =V9*0.0195 | Y9: AMEX | AA9: =Z9*0.0195 | AD9: AMEX | AF9: =AE9*0.0195 | AI9: AMEX | AK9: =AJ9*0.0195 | AN9: AMEX | AP9: =AO9*0.0195 | AS9: AMEX | AU9: =AT9*0.0195 | AX9: AMEX | AZ9: =AY9*0.0195
A10: BABYBONUS | C10: =B10*0.008 | E10: BABYBONUS | G10: =F10*0.008 | I10: BABYBONUS | K10: =J10*0.008 | M10: BABYBONUS | O10: =N10*0.008 | U10: BABYBONUS | W10: =V10*0.008 | Y10: BABYBONUS | AA10: =Z10*0.008 | AD10: BABYBONUS | AF10: =AE10*0.008 | AN10: BABYBONUS | AP10: =AO10*0.008 | AS10: BABYBONUS | AU10: =AT10*0.008 | AX10: BABYBONUS | AZ10: =AY10*0.008
A11: CASH | E11: CASH | I11: CASH | M11: CASH | Q11: ALLIANCE | S11: =R11*0.05*1.09 | U11: CASH | Y11: CASH | AD11: CASH | AI11: ALLIANCE | AK11: =AJ11*0.05*1.09 | AN11: CASH | AS11: CASH | AX11: CASH
A12: CASA VOUCHER | E12: CASA VOUCHER | I12: CASA VOUCHER | M12: CASA VOUCHER | Q12: CASH | U12: CASA VOUCHER | Y12: CASA VOUCHER | AD12: CASA VOUCHER | AI12: CASH | AN12: CASA VOUCHER | AS12: CASA VOUCHER | AX12: CASA VOUCHER
A13: CDC VOUCHER | E13: CDC VOUCHER | I13: CDC VOUCHER | M13: CDC VOUCHER | Q13: CASA VOUCHER | U13: CDC VOUCHER | Y13: CDC VOUCHER | AD13: CDC VOUCHER | AI13: CASA VOUCHER | AN13: CDC VOUCHER | AS13: CDC VOUCHER | AX13: CDC VOUCHER
A14: CHAS | E14: CHAS | I14: CHAS | M14: CHAS | U14: CHAS | Y14: CHAS | AD14: CHAS | AN14: CHAS | AS14: CHAS | AX14: CHAS
A15: CYNERGY | E15: CYNERGY | I15: CYNERGY | M15: CYNERGY | U15: CYNERGY | Y15: CYNERGY | AD15: CYNERGY | AN15: CYNERGY | AS15: CYNERGY | AX15: CYNERGY
A16: DA ADEPT HEALTH | C16: =B16*8% | E16: DA ADEPT HEALTH | G16: =F16*8% | I16: DA ADEPT HEALTH | K16: =J16*8% | M16: DA ADEPT HEALTH | O16: =N16*8% | U16: DA ADEPT HEALTH | W16: =V16*8% | Y16: DA ADEPT HEALTH | AA16: =Z16*8% | AD16: DA ADEPT HEALTH | AF16: =AE16*8% | AN16: DA ADEPT HEALTH | AP16: =AO16*8% | AS16: DA ADEPT HEALTH | AU16: =AT16*8% | AX16: DA ADEPT HEALTH | AZ16: =AY16*8%
A17: DEPOSIT | C17: =G17+K17+O17+O17+S17+W17+AA17+AF17+AP17+AU17+AZ17 | E17: DEPOSIT | I17: DEPOSIT | M17: DEPOSIT | Q17: DEPOSIT | S17: 0 | U17: DEPOSIT | Y17: DEPOSIT | AD17: DEPOSIT | AI17: DEPOSIT | AN17: DEPOSIT | AS17: DEPOSIT | AX17: DEPOSIT
A18: IHP | C18: =B18*0.051*1.09 | E18: IHP | G18: =F18*0.051*1.09 | I18: IHP | K18: =J18*0.051*1.09 | M18: IHP | O18: =N18*0.051*1.09 | U18: IHP | W18: =V18*0.051*1.09 | Y18: IHP | AA18: =Z18*0.051*1.09 | AD18: IHP | AF18: =AE18*0.051*1.09 | AN18: IHP | AP18: =AO18*0.051*1.09 | AS18: IHP | AU18: =AT18*0.051*1.09 | AX18: IHP | AZ18: =AY18*0.051*1.09
A19: JCB | C19: =B19*0.15*1.09 | E19: JCB | G19: =F19*0.15*1.09 | I19: JCB | K19: =J19*0.15*1.09 | M19: JCB | O19: =N19*0.15*1.09 | U19: JCB | W19: =V19*0.15*1.09 | Y19: JCB | AA19: =Z19*0.15*1.09 | AD19: JCB | AF19: =AE19*0.15*1.09 | AN19: JCB | AP19: =AO19*0.15*1.09 | AS19: JCB | AU19: =AT19*0.15*1.09 | AX19: JCB | AZ19: =AY19*0.15*1.09
A20: MASTER | C20: =B20*0.021 | E20: MASTER | G20: =F20*0.021 | I20: MASTER | K20: =J20*0.021 | M20: MASTER | O20: =N20*0.021 | U20: MASTER | W20: =V20*0.021 | Y20: MASTER | AA20: =Z20*0.021 | AD20: MASTER | AF20: =AE20*0.021 | AN20: MASTER | AP20: =AO20*0.021 | AS20: MASTER | AU20: =AT20*0.021 | AX20: MASTER | AZ20: =AY20*0.021
A21: MEDISAVE | E21: MEDISAVE | I21: MEDISAVE | M21: MEDISAVE | U21: MEDISAVE | Y21: MEDISAVE | AD21: MEDISAVE | AN21: MEDISAVE | AS21: MEDISAVE | AX21: MEDISAVE
A22: mednefits | C22: =B22*20% | E22: mednefits | G22: =F22*20% | I22: mednefits | K22: =J22*20% | M22: mednefits | O22: =N22*20% | U22: mednefits | W22: =V22*20% | Y22: mednefits | AA22: =Z22*20% | AD22: mednefits | AF22: =AE22*20% | AN22: mednefits | AP22: =AO22*20% | AS22: mednefits | AU22: =AT22*20% | AX22: mednefits | AZ22: =AY22*20%
A23: MHC | C23: =B23*0.15*1.09 | E23: MHC | G23: =F23*0.15*1.09 | I23: MHC | K23: =J23*0.15*1.09 | M23: MHC | O23: =N23*0.15*1.09 | U23: MHC | W23: =V23*0.15*1.09 | Y23: MHC | AA23: =Z23*0.15*1.09 | AD23: MHC | AF23: =AE23*0.15*1.09 | AN23: MHC | AP23: =AO23*0.15*1.09 | AS23: MHC | AU23: =AT23*0.15*1.09 | AX23: MHC | AZ23: =AY23*0.15*1.09
A24: NETS | C24: =B24*0.008 | E24: NETS | G24: =F24*0.008 | I24: NETS | K24: =J24*0.008 | M24: NETS | O24: =N24*0.008 | U24: NETS | W24: =V24*0.008 | Y24: NETS | AA24: =Z24*0.008 | AD24: NETS | AF24: =AE24*0.008 | AN24: NETS | AP24: =AO24*0.008 | AS24: NETS | AU24: =AT24*0.008 | AX24: NETS | AZ24: =AY24*0.008
A25: PARKWAY | C25: =B25*10% | E25: PARKWAY | G25: =F25*10% | I25: PARKWAY | K25: =J25*10% | M25: PARKWAY | O25: =N25*10% | U25: PARKWAY | W25: =V25*10% | Y25: PARKWAY | AA25: =Z25*10% | AD25: PARKWAY | AF25: =AE25*10% | AN25: PARKWAY | AP25: =AO25*10% | AS25: PARKWAY | AU25: =AT25*10% | AX25: PARKWAY | AZ25: =AY25*10%
A26: PAYNOW | E26: PAYNOW | I26: PAYNOW | M26: PAYNOW | U26: PAYNOW | Y26: PAYNOW | AD26: PAYNOW | AN26: PAYNOW | AS26: PAYNOW | AX26: PAYNOW
A27: RHI | E27: RHI | I27: RHI | M27: RHI | U27: RHI | Y27: RHI | AD27: RHI | AN27: RHI | AS27: RHI | AX27: RHI
A28: SAH | C28: =B28*8% | E28: SAH | G28: =F28*8% | I28: SAH | K28: =J28*8% | M28: SAH | O28: =N28*8% | U28: SAH | W28: =V28*8% | Y28: SAH | AA28: =Z28*8% | AD28: SAH | AF28: =AE28*8% | AN28: SAH | AP28: =AO28*8% | AS28: SAH | AU28: =AT28*8% | AX28: SAH | AZ28: =AY28*8%
A29: UNION PAY | C29: =B29*2.5% | E29: UNION PAY | G29: =F29*2.5% | I29: UNION PAY | K29: =J29*2.5% | M29: UNION PAY | O29: =N29*2.5% | U29: UNION PAY | W29: =V29*2.5% | Y29: UNION PAY | AA29: =Z29*2.5% | AD29: UNION PAY | AF29: =AE29*2.5% | AN29: UNION PAY | AP29: =AO29*2.5% | AS29: UNION PAY | AU29: =AT29*2.5% | AX29: UNION PAY | AZ29: =AY29*2.5%
A30: VISA | C30: =B30*0.021 | E30: VISA | G30: =F30*0.021 | I30: VISA | K30: =J30*0.021 | M30: VISA | O30: =N30*0.021 | U30: VISA | W30: =V30*0.021 | Y30: VISA | AA30: =Z30*0.021 | AD30: VISA | AF30: =AE30*0.021 | AN30: VISA | AP30: =AO30*0.021 | AS30: VISA | AU30: =AT30*0.021 | AX30: VISA | AZ30: =AY30*0.021
A31: TOTAL INCOME | B31: =SUM(B7:B30) | C31: =SUM(C7:C30) | E31: DR TOTAL INCOME | F31: =SUM(F7:F30) | G31: =SUM(G7:G30) | I31: DR TOTAL INCOME | J31: =SUM(J7:J30) | K31: =SUM(K7:K30) | M31: DR TOTAL INCOME | N31: =SUM(N7:N30) | O31: =SUM(O7:O30) | U31: DR TOTAL INCOME | V31: =SUM(V7:V30) | W31: =SUM(W7:W30) | Y31: DR TOTAL INCOME | Z31: =SUM(Z7:Z30) | AA31: =SUM(AA7:AA30) | AD31: DR TOTAL INCOME | AE31: =SUM(AE7:AE30) | AF31: =SUM(AF7:AF30) | AN31: DR TOTAL INCOME | AO31: =SUM(AO7:AO30) | AP31: =SUM(AP7:AP30) | AS31: DR TOTAL INCOME | AT31: =SUM(AT7:AT30) | AU31: =SUM(AU7:AU30) | AX31: DR TOTAL INCOME | AY31: =SUM(AY7:AY30) | AZ31: =SUM(AZ7:AZ30)
B33: EXPENSES | F33: DEDUCTIONS | H33: REMARKS | J33: DEDUCTIONS | L33: REMARKS | N33: DEDUCTIONS | P33: REMARKS | R33: DEDUCTIONS | T33: REMARKS | V33: DEDUCTIONS | X33: REMARKS | Z33: DEDUCTIONS | AB33: REMARKS | AE33: DEDUCTIONS | AG33: REMARKS | AJ33: DEDUCTIONS | AL33: REMARKS | AO33: DEDUCTIONS | AQ33: REMARKS | AT33: DEDUCTIONS | AV33: REMARKS | AY33: DEDUCTIONS | BA33: REMARKS
B34: ADMIN FEE | C34: =SUM(C7:C30) | F34: ADMIN CHARGES | G34: =G31 | J34: ADMIN CHARGES | K34: =K31 | N34: ADMIN CHARGES | O34: =O31 | R34: ADMIN CHARGES | S34: =#REF! | V34: ADMIN CHARGES | W34: =W31 | Z34: ADMIN CHARGES | AA34: =AA31 | AE34: ADMIN CHARGES | AF34: =AF31 | AJ34: ADMIN CHARGES | AK34: =#REF! | AO34: ADMIN CHARGES | AP34: =AP31 | AT34: ADMIN CHARGES | AU34: =AU31 | AY34: ADMIN CHARGES | AZ34: =AZ31
B35: GST | C35: =K35+O35+AA35+AF35+AM35+AP35+T35+W35+AU35+AZ35 | F35: GST | J35: GST | N35: GST | R35: GST | V35: GST | Z35: GST | AE35: GST | AJ35: GST | AO35: GST | AT35: GST | AY35: GST
B36: RENTAL | F36: ICC-5 | J36: ICC-5 | N36: ICC-5 | V36: ICC-5 | Z36: ICC-5 | AE36: ICC-5 | AO36: ICC-5 | AT36: ICC-5 | AY36: ICC-5
B37: LOAN INTEREST | F37: PRODUCTS | J37: PRODUCTS | N37: PRODUCTS | V37: PRODUCTS | Z37: PRODUCTS | AE37: PRODUCTS | AO37: PRODUCTS | AT37: PRODUCTS | AY37: PRODUCTS
B38: IRAS TAX | F38: ORTHO (B+B) | J38: ORTHO (B+B) | N38: ORTHO (B+B) | V38: ORTHO (B+B) | Z38: ORTHO (B+B) | AE38: ORTHO (B+B) | AO38: ORTHO (B+B) | AT38: ORTHO (B+B) | AY38: ORTHO (B+B)
B39: CK SECRETARIAL / ACCOUNTS SERVICES | F39: ABUTMENTS | J39: ABUTMENTS | N39: ABUTMENTS | V39: ABUTMENTS | Z39: ABUTMENTS | AE39: ABUTMENTS | AO39: ABUTMENTS | AT39: ABUTMENTS | AY39: ABUTMENTS
B40: TOWN COUNCIL | C40: 98.1 | F40: IMPLANT | J40: IMPLANT | N40: IMPLANT | V40: IMPLANT | Z40: IMPLANT | AE40: IMPLANT | AO40: IMPLANT | AT40: IMPLANT | AY40: IMPLANT
B41: SERVICE & CONSERVANCY CHARGES | C41: 400 | F41: SKY LAB | J41: SKY LAB | N41: SKY LAB | V41: SKY LAB | Z41: SKY LAB | AE41: SKY LAB | AO41: SKY LAB | AT41: SKY LAB | AY41: SKY LAB
B42: SP | F42: DIGICADCAM | J42: DIGICADCAM | N42: DIGICADCAM | V42: DIGICADCAM | Z42: DIGICADCAM | AE42: DIGICADCAM | AO42: DIGICADCAM | AT42: DIGICADCAM | AY42: DIGICADCAM
B43: SINGTEL | F43: OTHER LAB | J43: OTHER LAB | N43: OTHER LAB | V43: OTHER LAB | Z43: OTHER LAB | AE43: OTHER LAB | AO43: OTHER LAB | AT43: OTHER LAB | AY43: OTHER LAB
B44: PRODUCTS | C44: =G37+K37+O37+S59+W37+AA37+AF37+AK59+AP37+AU37+AZ37 | F44: INVISALIGN | J44: INVISALIGN | N44: INVISALIGN | V44: INVISALIGN | Z44: INVISALIGN | AE44: INVISALIGN | AO44: INVISALIGN | AT44: INVISALIGN | AY44: INVISALIGN
B45: ADMIN STAFF & OFFICE RENTAL | F45: TRANSFER (+) | J45: TRANSFER (+) | N45: TRANSFER (+) | V45: TRANSFER (+) | Z45: TRANSFER (+) | AE45: TRANSFER (+) | AO45: TRANSFER (+) | AT45: TRANSFER (+) | AY45: TRANSFER (+)
B46: SUPPLIERS | F46: TRANSFER (-) | J46: TRANSFER (-) | N46: TRANSFER (-) | V46: TRANSFER (-) | Z46: TRANSFER (-) | AE46: TRANSFER (-) | AO46: TRANSFER (-) | AT46: TRANSFER (-) | AY46: TRANSFER (-)
B47: VOUCHER | C47: =B12 | F47: REFUND/REFERRAL | J47: REFUND/REFERRAL | N47: REFUND/REFERRAL | V47: REFUND | Z47: REFUND | AE47: REFUND | AO47: REFUND | AT47: REFUND | AY47: REFUND
B48: PETTY CASH | F48: VOUCHER | G48: =F12 | J48: VOUCHER | N48: VOUCHER | V48: VOUCHER | Z48: VOUCHER | AE48: SEDATION | AO48: SEDATION | AT48: SEDATION | AY48: SEDATION
B49: STOCKS / CONSUMABLES FEES | F49: RETAINERS/BT/SPLINT | J49: RETAINERS/BT/SPLINT | N49: RETAINERS/BT/SPLINT | V49: RETAINERS/BT/SPLINT | Z49: RETAINERS/BT/SPLINT | AE49: RETAINERS/BT/SPLINT | AO49: RETAINERS/BT/SPLINT | AT49: RETAINERS/BT/SPLINT | AY49: RETAINERS/BT/SPLINT
B50: MARKETING FEE | F50: INSTALLMENT | J50: INSTALLMENT | N50: INSTALLMENT | V50: INSTALLMENT | Z50: INSTALLMENT | AE50: INSTALLMENT | AO50: INSTALLMENT | AT50: INSTALLMENT | AY50: INSTALLMENT
B51: INVISALIGN | C51: =G44+K44+O44+S66+W44+AA44+AF44+AK66+AP44+AU44 | F51: DEDUCTIONS | J51: DEDUCTIONS | N51: DEDUCTIONS | V51: DEDUCTIONS | Z51: DEDUCTIONS | AE51: DEDUCTIONS | AO51: DEDUCTIONS | AT51: DEDUCTIONS | AY51: DEDUCTIONS
B52: IMPLANT | C52: =G40+O40+S62+W40+AA40+AF40+K40+AK62+AP40+AU40+AZ40
B53: SKYLAB | C53: =G41+O41+W41+S63+K41+AA41+AF41+AK63+AP41+AU41+AZ41 | F53: TOTAL | G53: =F31-G34-G35-G37-G36-G38-G39-G40-G41-G42-G43-G44+G45-G46-G47-G48-G49-G50-G51 | J53: TOTAL | K53: =J31-K34-K35-K36-K37-K38-K39-K40-K41-K42-K43-K44+K45-K46-K47-K48-K49-K50-K51 | N53: TOTAL | O53: =N31-O34-O35-O36-O37-O38-O39-O40-O41-O42-O43-O44+O45-O46-O47-O48-O49-O50-O51 | V53: TOTAL | W53: =V31-W34-W35-W36-W37-W38-W39-W40-W41-W42-W43-W44+W45-W46-W47-W48-W49-W50-W51 | Z53: TOTAL | AA53: =Z31-AA34-AA35-AA36-AA37-AA38-AA39-AA40-AA41-AA42-AA43-AA44+AA45-AA46-AA47-AA48-AA49-AA50-AA51 | AE53: TOTAL | AF53: =AE31-AF34-AF35-AF36-AF37-AF38-AF39-AF40-AF41-AF42-AF43-AF44+AF45-AF46-AF47-AF48-AF49-AF50-AF51 | AO53: TOTAL | AP53: =AO31-AP34-AP35-AP36-AP37-AP38-AP39-AP40-AP41-AP42-AP43-AP44+AP45-AP46-AP47-AP48-AP49-AP50-AP51 | AT53: TOTAL | AU53: =AT31-AU34-AU35-AU36-AU37-AU38-AU39-AU40-AU41-AU42-AU43-AU44+AU45-AU46-AU47-AU48-AU49-AU50-AU51 | AY53: TOTAL | AZ53: =AY31-AZ34-AZ35-AZ36-AZ37-AZ38-AZ39-AZ40-AZ41-AZ42-AZ43-AZ44+AZ45-AZ46-AZ47-AZ48-AZ49-AZ50-AZ51
B54: DIGICADCAM | C54: =G42+O42+W42+AA42+AF42+S64+K42+AK64+AP42+AU42+AZ42 | F54: DOCTORS FEE BEFORE DEDUCTION | G54: =G53/2+G55 | J54: DOCTORS FEE BEFORE DEDUCTION | K54: =K53/2+K55 | N54: DOCTORS PAY | O54: =(O53*50%)+O55 | V54: DOCTORS PAY | W54: =(W53*50%)+W55 | Z54: DOCTORS PAY | AA54: =(AA53*40%)+AA55 | AE54: DOCTORS PAY | AF54: =(AF53*50%)+AF55 | AO54: DOCTORS PAY | AP54: =(AP53*45%)+AP55 | AT54: DOCTORS PAY | AU54: =(AU53*50%)+AU55 | AY54: DOCTORS PAY | AZ54: =(AZ53*45%)+AZ55
B55: OTHER LAB | C55: =G43+O43+K43+S65+W43+AA43+AF43+AK65+AP43+AU43+AZ43 | F55: ADJUSTMENTS (+) | J55: ADJUSTMENTS (+) | N55: ADJUSTMENTS (+) | V55: ADJUSTMENTS (+) | Z55: ADJUSTMENTS (+) | AE55: ADJUSTMENTS (+) | AO55: ADJUSTMENTS (+) | AT55: ADJUSTMENTS (+) | AY55: ADJUSTMENTS (+)
B56: ORTHO (B+B) | C56: =G38+K38+O38+S60+W38+AA38+AF38+AK60 | F56: ADJUSTMENTS (-) | G56: =G61+G65 | H56: ADDN MARKETING& MEDISAVE ADMIN | J56: ADJUSTMENTS (-) | K56: =K61+K65 | L56: ADDN MARKETING | N56: ADJUSTMENTS (-) | O56: =O61+O65 | P56: ADDN MARKETING & MEDISAVE ADMIN | V56: ADJUSTMENTS (-) | W56: =W61+W65 | X56: ADDN MKTRG & MEDISAVE ADMIN | Z56: ADJUSTMENTS (-) | AA56: =AA61+AA65 | AB56: MARKETING FEE & MEDISAVE ADMIN | AE56: ADJUSTMENTS (-) | AF56: =AF61+AF65 | AG56: MARKETING FEE & MEDISAVE ADMIN | AO56: ADJUSTMENTS (-) | AP56: =AP61+AP65 | AQ56: MARKETING FEE & MEDISAVE ADMIN | AT56: ADJUSTMENTS (-) | AU56: =AU61+AU65 | AV56: MARKETING FEE & MEDISAVE ADMIN | AY56: ADJUSTMENTS (-) | AZ56: =AZ61+AZ65 | BA56: MARKETING FEE & MEDISAVE ADMIN
B57: ABUTMENT | C57: =O39+G39+K39+S61+AA39+W39+AF39+AK61 | F57: NET PAY | G57: =G54-G56 | J57: NET PAY | K57: =K54-K56 | N57: NET PAY | O57: =O54-O56 | V57: NET PAY | W57: =W54-W56 | Z57: NET PAY | AA57: =AA54-AA56 | AE57: NET PAY | AF57: =AF54-AF56 | AO57: NET PAY | AP57: =AP54-AP56 | AT57: NET PAY | AU57: =AU54-AU56 | AY57: NET PAY | AZ57: =AZ54-AZ56
B58: REFUND / REFERRAL | C58: =G47+K47+O47+S69+W47+AA47+AF47+AK69 | R58: ICC-5 | AJ58: ICC-5
B59: DOCTORS PAY | C59: =G54+K54+O54+W54+AA54+AF54+AP54+AU54+AZ54 | F59: MEDISAVE ADMIN FEE CALCULATION: | J59: MEDISAVE ADMIN FEE CALCULATION: | N59: MEDISAVE ADMIN FEE CALCULATION: | R59: PRODUCTS | V59: MEDISAVE ADMIN FEE CALCULATION: | Z59: MEDISAVE ADMIN FEE CALCULATION: | AE59: MEDISAVE ADMIN FEE CALCULATION: | AJ59: PRODUCTS | AO59: MEDISAVE ADMIN FEE CALCULATION: | AT59: MEDISAVE ADMIN FEE CALCULATION: | AY59: MEDISAVE ADMIN FEE CALCULATION:
B60: NURSE PAY (BASIC PAY) | F60: Medisave Claim | G60: Admin Fee | H60: REMARKS | J60: Medisave Claim | K60: Admin Fee | L60: REMARKS | N60: Medisave Claim | O60: Admin Fee | P60: REMARKS | R60: ORTHO (B+B) | V60: Medisave Claim | W60: Admin Fee | X60: REMARKS | Z60: Medisave Claim | AA60: Admin Fee | AB60: REMARKS | AE60: Medisave Claim | AF60: Admin Fee | AG60: REMARKS | AJ60: ORTHO (B+B) | AO60: Medisave Claim | AP60: Admin Fee | AQ60: REMARKS | AT60: Medisave Claim | AU60: Admin Fee | AV60: REMARKS | AY60: Medisave Claim | AZ60: Admin Fee | BA60: REMARKS
B61: NURSE PAY (INCENTIVE) | G61: =F61*20 | K61: =J61*20 | O61: =N61*20 | R61: ABUTMENTS | W61: =V61*20 | AA61: =Z61*20 | AF61: =AE61*20 | AJ61: ABUTMENTS | AP61: =AO61*20 | AU61: =AT61*20 | AZ61: =AY61*20
B62: NURSE TRANSFER FEE | R62: IMPLANT | AJ62: IMPLANT
B63: TANK CULTURE | C63: 163.5 | F63: ADDITIONAL MARKETING: | J63: ADDITIONAL MARKETING: | N63: ADDITIONAL MARKETING: | R63: SKY LAB | V63: ADDITIONAL MARKETING: | Z63: ADDITIONAL MARKETING: | AE63: ADDITIONAL MARKETING: | AJ63: SKY LAB | AO63: ADDITIONAL MARKETING: | AT63: ADDITIONAL MARKETING: | AY63: ADDITIONAL MARKETING:
B64: SHARP BIN | F64: MONTH | G64: AMOUNT | H64: REMARKS | J64: MONTH | K64: AMOUNT | L64: REMARKS | N64: MONTH | O64: AMOUNT | P64: REMARKS | R64: DIGICADCAM | V64: MONTH | W64: AMOUNT | X64: REMARKS | Z64: MONTH | AA64: AMOUNT | AB64: REMARKS | AE64: MONTH | AF64: AMOUNT | AG64: REMARKS | AJ64: DIGICADCAM | AO64: MONTH | AP64: AMOUNT | AQ64: REMARKS | AT64: MONTH | AU64: AMOUNT | AV64: REMARKS | AY64: MONTH | AZ64: AMOUNT | BA64: REMARKS
B65: COURIER | C65: 129.44 | F65: =B3 | J65: =F65 | K65: 120 | N65: =F65 | O65: 300 | R65: OTHER LAB | V65: =V3 | W65: 75 | Z65: =V65 | AE65: =AE3 | AF65: 120 | AJ65: OTHER LAB | AO65: =AO3 | AP65: 120 | AT65: =AT3 | AU65: 120 | AY65: =AY3 | AZ65: 60
B66: REPAIR & MAINTENANCE | R66: INVISALIGN | AJ66: INVISALIGN
B67: MOM LEVY | C67: =300+800+400 | F67: OTHERS: (CPF,PERSONAL REFUND, COURSEFEE) | J67: OTHERS: (CPF,PERSONAL REFUND, COURSEFEE) | N67: OTHERS: (CPF,PERSONAL REFUND, COURSEFEE) | R67: TRANSFER (+) | V67: OTHERS: (CPF,PERSONAL REFUND, COURSEFEE) | Z67: OTHERS: (CPF,PERSONAL REFUND, COURSEFEE) | AE67: OTHERS: (CPF,PERSONAL REFUND, COURSEFEE) | AJ67: TRANSFER (+) | AO67: OTHERS: (CPF,PERSONAL REFUND, COURSEFEE) | AT67: OTHERS: (CPF,PERSONAL REFUND, COURSEFEE) | AY67: OTHERS: (CPF,PERSONAL REFUND, COURSEFEE)
R68: TRANSFER (-) | AJ68: TRANSFER (-)
F69: DETAILS | G69: AMOUNT | J69: DETAILS | K69: AMOUNT | N69: DETAILS | O69: AMOUNT | R69: REFUND | V69: DETAILS | W69: AMOUNT | Z69: DETAILS | AA69: AMOUNT | AE69: DETAILS | AF69: AMOUNT | AJ69: REFUND | AO69: DETAILS | AP69: AMOUNT | AT69: DETAILS | AU69: AMOUNT | AY69: DETAILS | AZ69: AMOUNT
F70: CPF CONT SALARY | R70: VOUCHER | AJ70: SEDATION | AY70: CPF SAL | AZ70: 1872
R71: RETAINERS/BT/SPLINT | AJ71: RETAINERS/BT/SPLINT | AY71: FROM DEC 2025 NEGATIVE AMT | AZ71: 1099.93
B72: TOTAL | C72: =B31-C34-C35-C58-C36-C37-C42-C43-C38-C46-C39-C45-C48-C49-C51-C50-C55-C54-C53-C59-C60-C61-C62-C47-C63-C40-C64-C41-C67-C66-C65-C90-C91-C92-C93-C94-C95-C68-C69-C70 | R72: INSTALLMENT | AJ72: INSTALLMENT
B73: FOR INCENTIVE % | C73: =B31-C34-C35-C58-C42-C43-C46-C45-C48-C44-C49-C50-C47-C63-C40-C64-C41-C65-C93-C95-C94-C66-C92-C90-C68-C69-C70 | R73: DEDUCTIONS | AJ73: DEDUCTIONS
B74: PERCENT | C74: =VLOOKUP(C73,'% RATES INCENTIVES'!C:D,2,TRUE)
A75: INCOME LESS GST | B75: =B31-C35 | C75: =C72/B75*100 | D75: % | R75: TOTAL | S75: =#REF!-S34-S35-S59-S58-S60-S61-S62-S63-S64-S65-S66+S67-S68-S69-S70-S71-S72-S73 | AJ75: TOTAL | AK75: =#REF!-AK34-AK35-AK58-AK59-AK60-AK61-AK62-AK63-AK64-AK65-AK66+AK67-AK68-AK69-AK70-AK71-AK72-AK73
R76: DOCTORS PAY | S76: =(S75*50%)+S77 | AJ76: DOCTORS PAY | AK76: =(AK75*50%)+AK77
B77: MEDISAVE ADMIN | C77: =G61+K61+O61+S83+W61+AA61+AF61+AK83+AP61+AU61+AZ61 | D77: =C77/20 | F77: TOTAL PAYMENT | G77: =G57-G70-G74-G75-G71-G72-G73 | J77: TOTAL PAYMENT | K77: =K57-K70-K74-K75-K71-K72-K73 | N77: TOTAL PAYMENT | O77: =O57-O70-O74-O75-O71-O72-O73 | R77: ADJUSTMENTS (+) | V77: TOTAL PAYMENT | W77: =W57-W70-W74-W75-W71-W72-W73 | Z77: TOTAL PAYMENT | AA77: =AA57-AA70-AA74-AA75-AA71-AA72-AA73 | AE77: TOTAL PAYMENT | AF77: =AF57-AF70-AF74-AF75-AF71-AF72-AF73 | AJ77: ADJUSTMENTS (+) | AO77: TOTAL PAYMENT | AP77: =AP57-AP70-AP74-AP75-AP71-AP72-AP73 | AT77: TOTAL PAYMENT | AU77: =AU57-AU70-AU74-AU75-AU71-AU72-AU73 | AY77: TOTAL PAYMENT | AZ77: =AZ57-AZ70-AZ74-AZ75-AZ71-AZ72-AZ73
B78: ADDITIONAL MARKETING | C78: =G65+K65+O65+S87+W65+AA65+AF65+AP65+AU65 | R78: ADJUSTMENTS (-) | S78: =S83+S87 | AJ78: ADJUSTMENTS (-) | AK78: =AK83+AK87 | AL78: MARKETING FEE & MEDISAVE ADMIN
B79: DOCTORS PERSONAL DEDUCTION | C79: =G70+G74+G75+K70+K74+K75+O70+O74+O75+S92+S96+S97+W70+W74+W75+AA70+AA74+AA75+AF70+AF74+AF75+G71+G72+G73+K71+K72+K73+O71+O72+O73+S93+S94+S95+W71+W72+W73+AA71+AA72+AA73+AF71+AF72+AF73+AP70+AP71+AP72+AP73+AP74+AP75+AU70+AU71+AU72+AU73+AU74+AU75+AZ70+AZ71+AZ72+AZ73+AZ74+AZ75 | R79: NET PAY | S79: =S76-S78 | AJ79: NET PAY | AK79: =AK76-AK78
B80: TOTAL | C80: =SUM(C77:C79)
B81: TOTAL ICC-5 | C81: =G36+K36+O36+S58+AA36+W36+AF36+AP36+AU36+AZ36 | R81: MEDISAVE ADMIN FEE CALCULATION: | AJ81: MEDISAVE ADMIN FEE CALCULATION:
R82: Medisave Claim | S82: Admin Fee | T82: REMARKS | AJ82: Medisave Claim | AK82: Admin Fee | AL82: REMARKS
B83: NURSES FEE-REVENUE | C83: =(C60+C61+C62)/B31 | S83: =R83*20 | AK83: =AJ83*20
B84: CONSUMABLE EXCL OFFICE RENT - REVENUE | C84: =(C49+C46+C48)/B31
B85: OFFICE RENT & ADMIN STAFF - REVENUE | C85: =(C45/B31) | R85: ADDITIONAL MARKETING: | AJ85: ADDITIONAL MARKETING:
B86: MARKETING - REVENUE | C86: =C50/B31 | R86: MONTH | S86: AMOUNT | T86: REMARKS | AJ86: MONTH | AK86: AMOUNT | AL86: REMARKS
R87: =R3 | AJ87: =AJ3
B88: FOR INCENTIVE % KORENE | C88: =VLOOKUP(C73,'% RATES INCENTIVES CLEMENTI'!C:D,2,TRUE)
R89: OTHERS: (CPF,PERSONAL REFUND, COURSEFEE) | AJ89: OTHERS: (CPF,PERSONAL REFUND, COURSEFEE)
R91: DETAILS | S91: AMOUNT | AJ91: DETAILS | AK91: AMOUNT
AH92: feb 2191
R99: TOTAL CHEQUE AMOUNT | S99: =S79-S92-S96-S97-S93-S94-S95 | AJ99: TOTAL CHEQUE AMOUNT | AK99: =AK79-AK92-AK96-AK97-AK93-AK94-AK95

Sheet HOLLAND SETTLEMENT CALC NEW
A3: MONTH/YEAR: | B3: 46023 | E3: MONTH/YEAR: | F3: =B3 | I3: MONTH/YEAR: | J3: =B3 | M3: MONTH/YEAR: | N3: =B3 | Q3: MONTH/YEAR: | R3: =B3 | U3: MONTH/YEAR: | V3: =B3 | Y3: MONTH/YEAR: | Z3: =B3 | AD3: MONTH/YEAR: | AE3: =B3 | AI3: MONTH/YEAR: | AJ3: =AE3 | AN3: MONTH/YEAR: | AO3: =AE3 | AS3: MONTH/YEAR: | AT3: =AO3 | AX3: MONTH/YEAR: | AY3: =V3
A4: BRANCH: | B4: CASA DENTAL HOLLAND PTE LTD | E4: BRANCH: | F4: =B4 | I4: BRANCH: | J4: =B4 | M4: BRANCH: | N4: =B4 | Q4: BRANCH: | R4: CASA DENTAL AMK PTE LTD | U4: BRANCH: | V4: =B4 | Y4: BRANCH: | Z4: =B4 | AD4: BRANCH: | AE4: =B4 | AI4: BRANCH: | AJ4: CASA DENTAL AMK PTE LTD | AN4: BRANCH: | AO4: =AE4 | AS4: BRANCH: | AT4: =AO4 | AX4: BRANCH: | AY4: =V4
A5: ALL PROVIDERS SETTLEMENT | E5: DR CHAN KC | I5: DR JASMINE LEE | M5: DR ANDREW YIN | Q5: DR KALIE | U5: DR CHARLENE YAP | Y5: DR JEAN CHONG | AD5: DR NG WAN TING | AI5: DR ANDREW YIN | AN5: DR KAREN LEONG | AS5: DR NICHOLAS LIEW | AX5: DR ROLAND FOO
C6: ADMIN CHARGES | G6: ADMIN CHARGES | J6: TOTALS | K6: ADMIN CHARGES | O6: ADMIN CHARGES | S6: ADMIN CHARGES | W6: ADMIN CHARGES | AA6: ADMIN CHARGES | AF6: ADMIN CHARGES | AK6: ADMIN CHARGES | AP6: ADMIN CHARGES | AU6: ADMIN CHARGES | AZ6: ADMIN CHARGES
A7: AIA | C7: =B7*0.05*1.09 | E7: AIA | G7: =F7*0.05*1.09 | I7: AIA | K7: =J7*0.05*1.09 | M7: AIA | O7: =N7*0.05*1.09 | Q7: AIA | S7: =R7*0.05*1.09 | U7: AIA | W7: =V7*0.05*1.09 | Y7: AIA | AA7: =Z7*0.05*1.09 | AD7: AIA | AF7: =AE7*0.05*1.09 | AI7: AIA | AK7: =AJ7*0.05*1.09 | AN7: AIA | AP7: =AO7*0.05*1.09 | AS7: AIA | AU7: =AT7*0.05*1.09 | AX7: AIA | AZ7: =AY7*0.05*1.09
A8: ALLIANCE | C8: =B8*0.05*1.09 | E8: ALLIANCE | G8: =F8*0.05*1.09 | I8: ALLIANCE | K8: =J8*0.05*1.09 | M8: ALLIANCE | O8: =N8*0.05*1.09 | U8: ALLIANCE | W8: =V8*0.05*1.09 | Y8: ALLIANCE | AA8: =Z8*0.05*1.09 | AD8: ALLIANCE | AF8: =AE8*0.05*1.09 | AN8: ALLIANCE | AP8: =AO8*0.05*1.09 | AS8: ALLIANCE | AU8: =AT8*0.05*1.09 | AX8: ALLIANCE | AZ8: =AY8*0.05*1.09
A9: AMEX | C9: =B9*0.0195 | E9: AMEX | G9: =F9*0.0195 | I9: AMEX | K9: =J9*0.0195 | M9: AMEX | O9: =N9*0.0195 | Q9: AMEX | S9: =R9*0.0195 | U9: AMEX | W9: =V9*0.0195 | Y9: AMEX | AA9: =Z9*0.0195 | AD9: AMEX | AF9: =AE9*0.0195 | AI9: AMEX | AK9: =AJ9*0.0195 | AN9: AMEX | AP9: =AO9*0.0195 | AS9: AMEX | AU9: =AT9*0.0195 | AX9: AMEX | AZ9: =AY9*0.0195
A10: BABYBONUS | C10: =B10*0.008 | E10: BABYBONUS | G10: =F10*0.008 | I10: BABYBONUS | K10: =J10*0.008 | M10: BABYBONUS | O10: =N10*0.008 | U10: BABYBONUS | W10: =V10*0.008 | Y10: BABYBONUS | AA10: =Z10*0.008 | AD10: BABYBONUS | AF10: =AE10*0.008 | AN10: BABYBONUS | AP10: =AO10*0.008 | AS10: BABYBONUS | AU10: =AT10*0.008 | AX10: BABYBONUS | AZ10: =AY10*0.008
A11: CASH | E11: CASH | I11: CASH | M11: CASH | Q11: ALLIANCE | S11: =R11*0.05*1.09 | U11: CASH | Y11: CASH | AD11: CASH | AI11: ALLIANCE | AK11: =AJ11*0.05*1.09 | AN11: CASH | AS11: CASH | AX11: CASH
A12: CASA VOUCHER | E12: CASA VOUCHER | I12: CASA VOUCHER | M12: CASA VOUCHER | Q12: CASH | U12: CASA VOUCHER | Y12: CASA VOUCHER | AD12: CASA VOUCHER | AI12: CASH | AN12: CASA VOUCHER | AS12: CASA VOUCHER | AX12: CASA VOUCHER
A13: CDC VOUCHER | E13: CDC VOUCHER | I13: CDC VOUCHER | M13: CDC VOUCHER | Q13: CASA VOUCHER | U13: CDC VOUCHER | Y13: CDC VOUCHER | AD13: CDC VOUCHER | AI13: CASA VOUCHER | AN13: CDC VOUCHER | AS13: CDC VOUCHER | AX13: CDC VOUCHER
A14: CHAS | E14: CHAS | I14: CHAS | M14: CHAS | U14: CHAS | Y14: CHAS | AD14: CHAS | AN14: CHAS | AS14: CHAS | AX14: CHAS
A15: CYNERGY | E15: CYNERGY | I15: CYNERGY | M15: CYNERGY | U15: CYNERGY | Y15: CYNERGY | AD15: CYNERGY | AN15: CYNERGY | AS15: CYNERGY | AX15: CYNERGY
A16: DA ADEPT HEALTH | C16: =B16*8% | E16: DA ADEPT HEALTH | G16: =F16*8% | I16: DA ADEPT HEALTH | K16: =J16*8% | M16: DA ADEPT HEALTH | O16: =N16*8% | U16: DA ADEPT HEALTH | W16: =V16*8% | Y16: DA ADEPT HEALTH | AA16: =Z16*8% | AD16: DA ADEPT HEALTH | AF16: =AE16*8% | AN16: DA ADEPT HEALTH | AP16: =AO16*8% | AS16: DA ADEPT HEALTH | AU16: =AT16*8% | AX16: DA ADEPT HEALTH | AZ16: =AY16*8%
A17: DEPOSIT | C17: =G17+K17+O17+O17+S17+W17+AA17+AF17+AP17+AU17+AZ17 | E17: DEPOSIT | I17: DEPOSIT | M17: DEPOSIT | Q17: DEPOSIT | S17: 0 | U17: DEPOSIT | Y17: DEPOSIT | AD17: DEPOSIT | AI17: DEPOSIT | AN17: DEPOSIT | AS17: DEPOSIT | AX17: DEPOSIT
A18: IHP | C18: =B18*0.051*1.09 | E18: IHP | G18: =F18*0.051*1.09 | I18: IHP | K18: =J18*0.051*1.09 | M18: IHP | O18: =N18*0.051*1.09 | U18: IHP | W18: =V18*0.051*1.09 | Y18: IHP | AA18: =Z18*0.051*1.09 | AD18: IHP | AF18: =AE18*0.051*1.09 | AN18: IHP | AP18: =AO18*0.051*1.09 | AS18: IHP | AU18: =AT18*0.051*1.09 | AX18: IHP | AZ18: =AY18*0.051*1.09
A19: JCB | C19: =B19*0.15*1.09 | E19: JCB | G19: =F19*0.15*1.09 | I19: JCB | K19: =J19*0.15*1.09 | M19: JCB | O19: =N19*0.15*1.09 | U19: JCB | W19: =V19*0.15*1.09 | Y19: JCB | AA19: =Z19*0.15*1.09 | AD19: JCB | AF19: =AE19*0.15*1.09 | AN19: JCB | AP19: =AO19*0.15*1.09 | AS19: JCB | AU19: =AT19*0.15*1.09 | AX19: JCB | AZ19: =AY19*0.15*1.09
A20: MASTER | C20: =B20*0.021 | E20: MASTER | G20: =F20*0.021 | I20: MASTER | K20: =J20*0.021 | M20: MASTER | O20: =N20*0.021 | U20: MASTER | W20: =V20*0.021 | Y20: MASTER | AA20: =Z20*0.021 | AD20: MASTER | AF20: =AE20*0.021 | AN20: MASTER | AP20: =AO20*0.021 | AS20: MASTER | AU20: =AT20*0.021 | AX20: MASTER | AZ20: =AY20*0.021
A21: MEDISAVE | E21: MEDISAVE | I21: MEDISAVE | M21: MEDISAVE | U21: MEDISAVE | Y21: MEDISAVE | AD21: MEDISAVE | AN21: MEDISAVE | AS21: MEDISAVE | AX21: MEDISAVE
A22: mednefits | C22: =B22*20% | E22: mednefits | G22: =F22*20% | I22: mednefits | K22: =J22*20% | M22: mednefits | O22: =N22*20% | U22: mednefits | W22: =V22*20% | Y22: mednefits | AA22: =Z22*20% | AD22: mednefits | AF22: =AE22*20% | AN22: mednefits | AP22: =AO22*20% | AS22: mednefits | AU22: =AT22*20% | AX22: mednefits | AZ22: =AY22*20%
A23: MHC | C23: =B23*0.15*1.09 | E23: MHC | G23: =F23*0.15*1.09 | I23: MHC | K23: =J23*0.15*1.09 | M23: MHC | O23: =N23*0.15*1.09 | U23: MHC | W23: =V23*0.15*1.09 | Y23: MHC | AA23: =Z23*0.15*1.09 | AD23: MHC | AF23: =AE23*0.15*1.09 | AN23: MHC | AP23: =AO23*0.15*1.09 | AS23: MHC | AU23: =AT23*0.15*1.09 | AX23: MHC | AZ23: =AY23*0.15*1.09
A24: NETS | C24: =B24*0.008 | E24: NETS | G24: =F24*0.008 | I24: NETS | K24: =J24*0.008 | M24: NETS | O24: =N24*0.008 | U24: NETS | W24: =V24*0.008 | Y24: NETS | AA24: =Z24*0.008 | AD24: NETS | AF24: =AE24*0.008 | AN24: NETS | AP24: =AO24*0.008 | AS24: NETS | AU24: =AT24*0.008 | AX24: NETS | AZ24: =AY24*0.008
A25: PARKWAY | C25: =B25*10% | E25: PARKWAY | G25: =F25*10% | I25: PARKWAY | K25: =J25*10% | M25: PARKWAY | O25: =N25*10% | U25: PARKWAY | W25: =V25*10% | Y25: PARKWAY | AA25: =Z25*10% | AD25: PARKWAY | AF25: =AE25*10% | AN25: PARKWAY | AP25: =AO25*10% | AS25: PARKWAY | AU25: =AT25*10% | AX25: PARKWAY | AZ25: =AY25*10%
A26: PAYNOW | E26: PAYNOW | I26: PAYNOW | M26: PAYNOW | U26: PAYNOW | Y26: PAYNOW | AD26: PAYNOW | AN26: PAYNOW | AS26: PAYNOW | AX26: PAYNOW
A27: RHI | E27: RHI | I27: RHI | M27: RHI | U27: RHI | Y27: RHI | AD27: RHI | AN27: RHI | AS27: RHI | AX27: RHI
A28: SAH | C28: =B28*8% | E28: SAH | G28: =F28*8% | I28: SAH | K28: =J28*8% | M28: SAH | O28: =N28*8% | U28: SAH | W28: =V28*8% | Y28: SAH | AA28: =Z28*8% | AD28: SAH | AF28: =AE28*8% | AN28: SAH | AP28: =AO28*8% | AS28: SAH | AU28: =AT28*8% | AX28: SAH | AZ28: =AY28*8%
A29: UNION PAY | C29: =B29*2.5% | E29: UNION PAY | G29: =F29*2.5% | I29: UNION PAY | K29: =J29*2.5% | M29: UNION PAY | O29: =N29*2.5% | U29: UNION PAY | W29: =V29*2.5% | Y29: UNION PAY | AA29: =Z29*2.5% | AD29: UNION PAY | AF29: =AE29*2.5% | AN29: UNION PAY | AP29: =AO29*2.5% | AS29: UNION PAY | AU29: =AT29*2.5% | AX29: UNION PAY | AZ29: =AY29*2.5%
A30: VISA | C30: =B30*0.021 | E30: VISA | G30: =F30*0.021 | I30: VISA | K30: =J30*0.021 | M30: VISA | O30: =N30*0.021 | U30: VISA | W30: =V30*0.021 | Y30: VISA | AA30: =Z30*0.021 | AD30: VISA | AF30: =AE30*0.021 | AN30: VISA | AP30: =AO30*0.021 | AS30: VISA | AU30: =AT30*0.021 | AX30: VISA | AZ30: =AY30*0.021
A31: TOTAL INCOME | B31: =SUM(B7:B30) | C31: =SUM(C7:C30) | E31: DR TOTAL INCOME | F31: =SUM(F7:F30) | G31: =SUM(G7:G30) | I31: DR TOTAL INCOME | J31: =SUM(J7:J30) | K31: =SUM(K7:K30) | M31: DR TOTAL INCOME | N31: =SUM(N7:N30) | O31: =SUM(O7:O30) | U31: DR TOTAL INCOME | V31: =SUM(V7:V30) | W31: =SUM(W7:W30) | Y31: DR TOTAL INCOME | Z31: =SUM(Z7:Z30) | AA31: =SUM(AA7:AA30) | AD31: DR TOTAL INCOME | AE31: =SUM(AE7:AE30) | AF31: =SUM(AF7:AF30) | AN31: DR TOTAL INCOME | AO31: =SUM(AO7:AO30) | AP31: =SUM(AP7:AP30) | AS31: DR TOTAL INCOME | AT31: =SUM(AT7:AT30) | AU31: =SUM(AU7:AU30) | AX31: DR TOTAL INCOME | AY31: =SUM(AY7:AY30) | AZ31: =SUM(AZ7:AZ30)
B33: EXPENSES | F33: DEDUCTIONS | H33: REMARKS | J33: DEDUCTIONS | L33: REMARKS | N33: DEDUCTIONS | P33: REMARKS | R33: DEDUCTIONS | T33: REMARKS | V33: DEDUCTIONS | X33: REMARKS | Z33: DEDUCTIONS | AB33: REMARKS | AE33: DEDUCTIONS | AG33: REMARKS | AJ33: DEDUCTIONS | AL33: REMARKS | AO33: DEDUCTIONS | AQ33: REMARKS | AT33: DEDUCTIONS | AV33: REMARKS | AY33: DEDUCTIONS | BA33: REMARKS
B34: ADMIN FEE | C34: =SUM(C7:C30) | F34: ADMIN CHARGES | G34: =G31 | J34: ADMIN CHARGES | K34: =K31 | N34: ADMIN CHARGES | O34: =O31 | R34: ADMIN CHARGES | S34: =#REF! | V34: ADMIN CHARGES | W34: =W31 | Z34: ADMIN CHARGES | AA34: =AA31 | AE34: ADMIN CHARGES | AF34: =AF31 | AJ34: ADMIN CHARGES | AK34: =#REF! | AO34: ADMIN CHARGES | AP34: =AP31 | AT34: ADMIN CHARGES | AU34: =AU31 | AY34: ADMIN CHARGES | AZ34: =AZ31
B35: GST | C35: =K35+O35+AA35+AF35+AM35+AP35+T35+W35+AU35+AZ35 | F35: GST | J35: GST | N35: GST | R35: GST | V35: GST | Z35: GST | AE35: GST | AJ35: GST | AO35: GST | AT35: GST | AY35: GST
B36: RENTAL | F36: ICC-5 | J36: ICC-5 | N36: ICC-5 | V36: ICC-5 | Z36: ICC-5 | AE36: ICC-5 | AO36: ICC-5 | AT36: ICC-5 | AY36: ICC-5
B37: LOAN INTEREST | F37: PRODUCTS | J37: PRODUCTS | N37: PRODUCTS | V37: PRODUCTS | Z37: PRODUCTS | AE37: PRODUCTS | AO37: PRODUCTS | AT37: PRODUCTS | AY37: PRODUCTS
B38: IRAS TAX | C38: 22590 | D38: NOV 2025 $45215 | F38: ORTHO (B+B) | J38: ORTHO (B+B) | N38: ORTHO (B+B) | V38: ORTHO (B+B) | Z38: ORTHO (B+B) | AE38: ORTHO (B+B) | AO38: ORTHO (B+B) | AT38: ORTHO (B+B) | AY38: ORTHO (B+B)
B39: CK SECRETARIAL / ACCOUNTS SERVICES | D39: DEC25-MAR26 $22590 | F39: ABUTMENTS | J39: ABUTMENTS | N39: ABUTMENTS | V39: ABUTMENTS | Z39: ABUTMENTS | AE39: ABUTMENTS | AO39: ABUTMENTS | AT39: ABUTMENTS | AY39: ABUTMENTS
B40: TOWN COUNCIL | C40: 286.13 | F40: IMPLANT | J40: IMPLANT | N40: IMPLANT | V40: IMPLANT | Z40: IMPLANT | AE40: IMPLANT | AO40: IMPLANT | AT40: IMPLANT | AY40: IMPLANT
B41: SERVICE & CONSERVANCY CHARGES | C41: 800 | F41: SKY LAB | J41: SKY LAB | N41: SKY LAB | V41: SKY LAB | Z41: SKY LAB | AE41: SKY LAB | AO41: SKY LAB | AT41: SKY LAB | AY41: SKY LAB
B42: SP | F42: DIGICADCAM | J42: DIGICADCAM | N42: DIGICADCAM | V42: DIGICADCAM | Z42: DIGICADCAM | AE42: DIGICADCAM | AO42: DIGICADCAM | AT42: DIGICADCAM | AY42: DIGICADCAM
B43: SINGTEL | F43: OTHER LAB | J43: OTHER LAB | N43: OTHER LAB | V43: OTHER LAB | Z43: OTHER LAB | AE43: OTHER LAB | AO43: OTHER LAB | AT43: OTHER LAB | AY43: OTHER LAB
B44: PRODUCTS | C44: =G37+K37+O37+S59+W37+AA37+AF37+AK59+AP37+AU37+AZ37 | F44: INVISALIGN | J44: INVISALIGN | N44: INVISALIGN | V44: INVISALIGN | Z44: INVISALIGN | AE44: INVISALIGN | AO44: INVISALIGN | AT44: INVISALIGN | AY44: INVISALIGN
B45: ADMIN STAFF & OFFICE RENTAL | F45: TRANSFER (+) | J45: TRANSFER (+) | N45: TRANSFER (+) | V45: TRANSFER (+) | Z45: TRANSFER (+) | AE45: TRANSFER (+) | AO45: TRANSFER (+) | AT45: TRANSFER (+) | AY45: TRANSFER (+)
B46: SUPPLIERS | F46: TRANSFER (-) | J46: TRANSFER (-) | N46: TRANSFER (-) | V46: TRANSFER (-) | Z46: TRANSFER (-) | AE46: TRANSFER (-) | AO46: TRANSFER (-) | AT46: TRANSFER (-) | AY46: TRANSFER (-)
B47: VOUCHER | C47: =B12 | F47: REFUND/REFERRAL | J47: REFUND/REFERRAL | N47: REFUND/REFERRAL | V47: REFUND | Z47: REFUND | AE47: REFUND | AO47: REFUND | AT47: REFUND | AY47: REFUND
B48: PETTY CASH | F48: VOUCHER | G48: =F12 | J48: VOUCHER | N48: VOUCHER | V48: VOUCHER | Z48: VOUCHER | AE48: SEDATION | AO48: SEDATION | AT48: SEDATION | AY48: SEDATION
B49: STOCKS / CONSUMABLES FEES | F49: RETAINERS/BT/SPLINT | J49: RETAINERS/BT/SPLINT | N49: RETAINERS/BT/SPLINT | V49: RETAINERS/BT/SPLINT | Z49: RETAINERS/BT/SPLINT | AE49: RETAINERS/BT/SPLINT | AO49: RETAINERS/BT/SPLINT | AT49: RETAINERS/BT/SPLINT | AY49: RETAINERS/BT/SPLINT
B50: MARKETING FEE | F50: INSTALLMENT | J50: INSTALLMENT | N50: INSTALLMENT | V50: INSTALLMENT | Z50: INSTALLMENT | AE50: INSTALLMENT | AO50: INSTALLMENT | AT50: INSTALLMENT | AY50: INSTALLMENT
B51: INVISALIGN | C51: =G44+K44+O44+S66+W44+AA44+AF44+AK66 | F51: DEDUCTIONS | J51: DEDUCTIONS | N51: DEDUCTIONS | V51: DEDUCTIONS | Z51: DEDUCTIONS | AE51: DEDUCTIONS | AO51: DEDUCTIONS | AT51: DEDUCTIONS | AY51: DEDUCTIONS
B52: IMPLANT | C52: =G40+O40+S62+W40+AA40+AF40+K40+AK62+AP40+AU40+AZ40
B53: SKYLAB | C53: =G41+O41+W41+S63+K41+AA41+AF41+AK63+AP41+AU41+AZ41 | F53: TOTAL | G53: =F31-G34-G35-G37-G36-G38-G39-G40-G41-G42-G43-G44+G45-G46-G47-G48-G49-G50-G51 | J53: TOTAL | K53: =J31-K34-K35-K36-K37-K38-K39-K40-K41-K42-K43-K44+K45-K46-K47-K48-K49-K50-K51 | N53: TOTAL | O53: =N31-O34-O35-O36-O37-O38-O39-O40-O41-O42-O43-O44+O45-O46-O47-O48-O49-O50-O51 | V53: TOTAL | W53: =V31-W34-W35-W36-W37-W38-W39-W40-W41-W42-W43-W44+W45-W46-W47-W48-W49-W50-W51 | Z53: TOTAL | AA53: =Z31-AA34-AA35-AA36-AA37-AA38-AA39-AA40-AA41-AA42-AA43-AA44+AA45-AA46-AA47-AA48-AA49-AA50-AA51 | AE53: TOTAL | AF53: =AE31-AF34-AF35-AF36-AF37-AF38-AF39-AF40-AF41-AF42-AF43-AF44+AF45-AF46-AF47-AF48-AF49-AF50-AF51 | AO53: TOTAL | AP53: =AO31-AP34-AP35-AP36-AP37-AP38-AP39-AP40-AP41-AP42-AP43-AP44+AP45-AP46-AP47-AP48-AP49-AP50-AP51 | AT53: TOTAL | AU53: =AT31-AU34-AU35-AU36-AU37-AU38-AU39-AU40-AU41-AU42-AU43-AU44+AU45-AU46-AU47-AU48-AU49-AU50-AU51 | AY53: TOTAL | AZ53: =AY31-AZ34-AZ35-AZ36-AZ37-AZ38-AZ39-AZ40-AZ41-AZ42-AZ43-AZ44+AZ45-AZ46-AZ47-AZ48-AZ49-AZ50-AZ51
B54: DIGICADCAM | C54: =G42+O42+W42+AA42+AF42+S64+K42+AK64+AP42+AU42+AZ42 | F54: DOCTORS FEE BEFORE DEDUCTION | G54: =G53/2+G55 | J54: DOCTORS FEE BEFORE DEDUCTION | K54: =K53/2+K55 | N54: DOCTORS PAY | O54: =(O53*50%)+O55 | V54: DOCTORS PAY | W54: =(W53*45%)+W55 | Z54: DOCTORS PAY | AA54: =(AA53*45%)+AA55 | AE54: DOCTORS PAY | AF54: =(AF53*50%)+AF55 | AO54: DOCTORS PAY | AP54: =(AP53*45%)+AP55 | AT54: DOCTORS PAY | AU54: =(AU53*45%)+AU55 | AY54: DOCTORS PAY | AZ54: =(AZ53*50%)+AZ55
B55: OTHER LAB | C55: =G43+O43+K43+S65+W43+AA43+AF43+AK65+AP43+AU43+AZ43 | F55: ADJUSTMENTS (+) | J55: ADJUSTMENTS (+) | N55: ADJUSTMENTS (+) | V55: ADJUSTMENTS (+) | Z55: ADJUSTMENTS (+) | AE55: ADJUSTMENTS (+) | AO55: ADJUSTMENTS (+) | AT55: ADJUSTMENTS (+) | AY55: ADJUSTMENTS (+)
B56: ORTHO (B+B) | C56: =G38+K38+O38+S60+W38+AA38+AF38+AK60 | F56: ADJUSTMENTS (-) | G56: =G61+G65 | H56: ADDN MARKETING& MEDISAVE ADMIN | J56: ADJUSTMENTS (-) | K56: =K61+K65 | L56: ADDN MARKETING | N56: ADJUSTMENTS (-) | O56: =O61+O65 | P56: ADDN MARKETING & MEDISAVE ADMIN | V56: ADJUSTMENTS (-) | W56: =W61+W65 | X56: ADDN MKTRG & MEDISAVE ADMIN | Z56: ADJUSTMENTS (-) | AA56: =AA61+AA65 | AB56: MARKETING FEE & MEDISAVE ADMIN | AE56: ADJUSTMENTS (-) | AF56: =AF61+AF65 | AG56: MARKETING FEE & MEDISAVE ADMIN | AO56: ADJUSTMENTS (-) | AP56: =AP61+AP65 | AQ56: MARKETING FEE & MEDISAVE ADMIN | AT56: ADJUSTMENTS (-) | AU56: =AU61+AU65 | AV56: MARKETING FEE & MEDISAVE ADMIN | AY56: ADJUSTMENTS (-) | AZ56: =AZ61+AZ65 | BA56: MARKETING FEE & MEDISAVE ADMIN
B57: ABUTMENT | C57: =O39+G39+K39+S61+AA39+W39+AF39+AK61 | F57: NET PAY | G57: =G54-G56 | J57: NET PAY | K57: =K54-K56 | N57: NET PAY | O57: =O54-O56 | V57: NET PAY | W57: =W54-W56 | Z57: NET PAY | AA57: =AA54-AA56 | AE57: NET PAY | AF57: =AF54-AF56 | AO57: NET PAY | AP57: =AP54-AP56 | AT57: NET PAY | AU57: =AU54-AU56 | AY57: NET PAY | AZ57: =AZ54-AZ56
B58: REFUND / REFERRAL | C58: =G47+K47+O47+S69+W47+AA47+AF47+AK69 | R58: ICC-5 | AJ58: ICC-5
B59: DOCTORS PAY | C59: =G54+K54+O54+W54+AA54+AF54+AP54+AU54+AZ54 | F59: MEDISAVE ADMIN FEE CALCULATION: | J59: MEDISAVE ADMIN FEE CALCULATION: | N59: MEDISAVE ADMIN FEE CALCULATION: | R59: PRODUCTS | V59: MEDISAVE ADMIN FEE CALCULATION: | Z59: MEDISAVE ADMIN FEE CALCULATION: | AE59: MEDISAVE ADMIN FEE CALCULATION: | AJ59: PRODUCTS | AO59: MEDISAVE ADMIN FEE CALCULATION: | AT59: MEDISAVE ADMIN FEE CALCULATION: | AY59: MEDISAVE ADMIN FEE CALCULATION:
B60: NURSE PAY (BASIC PAY) | F60: Medisave Claim | G60: Admin Fee | H60: REMARKS | J60: Medisave Claim | K60: Admin Fee | L60: REMARKS | N60: Medisave Claim | O60: Admin Fee | P60: REMARKS | R60: ORTHO (B+B) | V60: Medisave Claim | W60: Admin Fee | X60: REMARKS | Z60: Medisave Claim | AA60: Admin Fee | AB60: REMARKS | AE60: Medisave Claim | AF60: Admin Fee | AG60: REMARKS | AJ60: ORTHO (B+B) | AO60: Medisave Claim | AP60: Admin Fee | AQ60: REMARKS | AT60: Medisave Claim | AU60: Admin Fee | AV60: REMARKS | AY60: Medisave Claim | AZ60: Admin Fee | BA60: REMARKS
B61: NURSE PAY (INCENTIVE) | G61: =F61*20 | K61: =J61*20 | O61: =N61*20 | R61: ABUTMENTS | W61: =V61*20 | AA61: =Z61*20 | AF61: =AE61*20 | AJ61: ABUTMENTS | AP61: =AO61*20 | AU61: =AT61*20 | AZ61: =AY61*20
B62: NURSE TRANSFER FEE | R62: IMPLANT | AJ62: IMPLANT
B63: TANK CULTURE | C63: 163.5 | F63: ADDITIONAL MARKETING: | J63: ADDITIONAL MARKETING: | N63: ADDITIONAL MARKETING: | R63: SKY LAB | V63: ADDITIONAL MARKETING: | Z63: ADDITIONAL MARKETING: | AE63: ADDITIONAL MARKETING: | AJ63: SKY LAB | AO63: ADDITIONAL MARKETING: | AT63: ADDITIONAL MARKETING: | AY63: ADDITIONAL MARKETING:
B64: SHARP BIN | F64: MONTH | G64: AMOUNT | H64: REMARKS | J64: MONTH | K64: AMOUNT | L64: REMARKS | N64: MONTH | O64: AMOUNT | P64: REMARKS | R64: DIGICADCAM | V64: MONTH | W64: AMOUNT | X64: REMARKS | Z64: MONTH | AA64: AMOUNT | AB64: REMARKS | AE64: MONTH | AF64: AMOUNT | AG64: REMARKS | AJ64: DIGICADCAM | AO64: MONTH | AP64: AMOUNT | AQ64: REMARKS | AT64: MONTH | AU64: AMOUNT | AV64: REMARKS | AY64: MONTH | AZ64: AMOUNT | BA64: REMARKS
B65: COURIER | C65: 129.44 | F65: =B3 | J65: =F65 | K65: 60 | N65: =F65 | O65: 300 | R65: OTHER LAB | V65: =V3 | W65: 240 | Z65: =V65 | AA65: 120 | AE65: =AE3 | AJ65: OTHER LAB | AO65: =AO3 | AP65: 180 | AT65: =AT3 | AU65: 120 | AY65: =AY3 | AZ65: 180
B66: REPAIR & MAINTENANCE | R66: INVISALIGN | AJ66: INVISALIGN
B67: MOM LEVY | C67: 1985.39 | F67: OTHERS: (CPF,PERSONAL REFUND, COURSEFEE) | J67: OTHERS: (CPF,PERSONAL REFUND, COURSEFEE) | N67: OTHERS: (CPF,PERSONAL REFUND, COURSEFEE) | R67: TRANSFER (+) | V67: OTHERS: (CPF,PERSONAL REFUND, COURSEFEE) | Z67: OTHERS: (CPF,PERSONAL REFUND, COURSEFEE) | AE67: OTHERS: (CPF,PERSONAL REFUND, COURSEFEE) | AJ67: TRANSFER (+) | AO67: OTHERS: (CPF,PERSONAL REFUND, COURSEFEE) | AT67: OTHERS: (CPF,PERSONAL REFUND, COURSEFEE) | AY67: OTHERS: (CPF,PERSONAL REFUND, COURSEFEE)
R68: TRANSFER (-) | AJ68: TRANSFER (-)
F69: DETAILS | G69: AMOUNT | J69: DETAILS | K69: AMOUNT | N69: DETAILS | O69: AMOUNT | R69: REFUND | V69: DETAILS | W69: AMOUNT | Z69: DETAILS | AA69: AMOUNT | AE69: DETAILS | AF69: AMOUNT | AJ69: REFUND | AO69: DETAILS | AP69: AMOUNT | AT69: DETAILS | AU69: AMOUNT | AY69: DETAILS | AZ69: AMOUNT
F70: CPF CONT SALARY | R70: VOUCHER | AJ70: SEDATION
R71: RETAINERS/BT/SPLINT | AJ71: RETAINERS/BT/SPLINT
B72: TOTAL | C72: =B31-C34-C35-C58-C36-C37-C42-C43-C38-C46-C39-C45-C48-C49-C51-C50-C55-C54-C53-C59-C60-C61-C62-C47-C63-C40-C64-C41-C67-C66-C65-C90-C91-C92-C93-C94-C95-C68-C69-C70 | R72: INSTALLMENT | AJ72: INSTALLMENT
B73: FOR INCENTIVE % | C73: =B31-C34-C35-C58-C42-C43-C46-C45-C48-C44-C49-C50-C47-C63-C40-C64-C41-C65-C93-C95-C94-C66-C92-C90-C68-C69-C70 | R73: DEDUCTIONS | AJ73: DEDUCTIONS
B74: PERCENT ANGEL | C74: =VLOOKUP(C73,'% RATES INCENTIVES HOLLAND'!C:D,2,TRUE)
A75: INCOME LESS GST | B75: =B31-C35 | C75: =C72/B75*100 | D75: % | R75: TOTAL | S75: =#REF!-S34-S35-S59-S58-S60-S61-S62-S63-S64-S65-S66+S67-S68-S69-S70-S71-S72-S73 | AJ75: TOTAL | AK75: =#REF!-AK34-AK35-AK58-AK59-AK60-AK61-AK62-AK63-AK64-AK65-AK66+AK67-AK68-AK69-AK70-AK71-AK72-AK73
R76: DOCTORS PAY | S76: =(S75*50%)+S77 | AJ76: DOCTORS PAY | AK76: =(AK75*50%)+AK77
B77: MEDISAVE ADMIN | C77: =G61+K61+O61+S83+W61+AA61+AF61+AK83+AP61+AU61+AZ61 | D77: =C77/20 | F77: TOTAL PAYMENT | G77: =G57-G70-G74-G75-G71-G72-G73 | J77: TOTAL PAYMENT | K77: =K57-K70-K74-K75-K71-K72-K73 | L77: TRF TO AMK IN FEB 2026 | N77: TOTAL PAYMENT | O77: =O57-O70-O74-O75-O71-O72-O73 | R77: ADJUSTMENTS (+) | V77: TOTAL PAYMENT | W77: =W57-W70-W74-W75-W71-W72-W73 | Z77: TOTAL PAYMENT | AA77: =AA57-AA70-AA74-AA75-AA71-AA72-AA73 | AE77: TOTAL PAYMENT | AF77: =AF57-AF70-AF74-AF75-AF71-AF72-AF73 | AJ77: ADJUSTMENTS (+) | AO77: TOTAL PAYMENT | AP77: =AP57-AP70-AP74-AP75-AP71-AP72-AP73 | AT77: TOTAL PAYMENT | AU77: =AU57-AU70-AU74-AU75-AU71-AU72-AU73 | AY77: TOTAL PAYMENT | AZ77: =AZ57-AZ70-AZ74-AZ75-AZ71-AZ72-AZ73
B78: ADDITIONAL MARKETING | C78: =G65+K65+O65+S87+W65+AA65+AF65+AP65+AU65+AZ65 | R78: ADJUSTMENTS (-) | S78: =S83+S87 | AJ78: ADJUSTMENTS (-) | AK78: =AK83+AK87 | AL78: MARKETING FEE & MEDISAVE ADMIN
B79: DOCTORS PERSONAL DEDUCTION | C79: =G70+G74+G75+K70+K74+K75+O70+O74+O75+S92+S96+S97+W70+W74+W75+AA70+AA74+AA75+AF70+AF74+AF75+G71+G72+G73+K71+K72+K73+O71+O72+O73+S93+S94+S95+W71+W72+W73+AA71+AA72+AA73+AF71+AF72+AF73+AP70+AP71+AP72+AP73+AP74+AP75+AU70+AU71+AU72+AU73+AU74+AU75+AZ70+AZ71+AZ72+AZ73+AZ74+AZ75 | R79: NET PAY | S79: =S76-S78 | AJ79: NET PAY | AK79: =AK76-AK78
B80: TOTAL | C80: =SUM(C77:C79)
B81: TOTAL ICC-5 | C81: =G36+K36+O36+S58+AA36+W36+AF36+AP36+AU36+AZ36 | R81: MEDISAVE ADMIN FEE CALCULATION: | AJ81: MEDISAVE ADMIN FEE CALCULATION:
R82: Medisave Claim | S82: Admin Fee | T82: REMARKS | AJ82: Medisave Claim | AK82: Admin Fee | AL82: REMARKS
B83: NURSES FEE-REVENUE | C83: =(C60+C61+C62)/B31 | S83: =R83*20 | AK83: =AJ83*20
B84: CONSUMABLE EXCL OFFICE RENT - REVENUE | C84: =(C49+C46+C48)/B31
B85: OFFICE RENT & ADMIN STAFF - REVENUE | C85: =(C45/B31) | R85: ADDITIONAL MARKETING: | AJ85: ADDITIONAL MARKETING:
B86: MARKETING - REVENUE | C86: =C50/B31 | R86: MONTH | S86: AMOUNT | T86: REMARKS | AJ86: MONTH | AK86: AMOUNT | AL86: REMARKS
R87: =R3 | AJ87: =AJ3
B88: FOR INCENTIVE % YITONG | C88: =VLOOKUP(C73,'% RATES INCENTIVES'!C:D,2,TRUE)
R89: OTHERS: (CPF,PERSONAL REFUND, COURSEFEE) | AJ89: OTHERS: (CPF,PERSONAL REFUND, COURSEFEE)
R91: DETAILS | S91: AMOUNT | AJ91: DETAILS | AK91: AMOUNT
AH92: feb 2191
R99: TOTAL CHEQUE AMOUNT | S99: =S79-S92-S96-S97-S93-S94-S95 | AJ99: TOTAL CHEQUE AMOUNT | AK99: =AK79-AK92-AK96-AK97-AK93-AK94-AK95

Sheet ADM SETTLEMENT CALC NEW
A3: MONTH/YEAR: | B3: 46023 | E3: MONTH/YEAR: | F3: =B3 | I3: MONTH/YEAR: | J3: =B3 | M3: MONTH/YEAR: | N3: =B3 | Q3: MONTH/YEAR: | R3: =B3 | U3: MONTH/YEAR: | V3: =B3 | Y3: MONTH/YEAR: | Z3: =B3 | AD3: MONTH/YEAR: | AE3: =B3 | AI3: MONTH/YEAR: | AJ3: =AE3 | AN3: MONTH/YEAR: | AO3: =AE3 | AS3: MONTH/YEAR: | AT3: =AO3 | AX3: MONTH/YEAR: | AY3: =V3
A4: BRANCH: | B4: CASA DENTAL ADMIRALTY | E4: BRANCH: | F4: =B4 | I4: BRANCH: | J4: =B4 | M4: BRANCH: | N4: =B4 | Q4: BRANCH: | R4: CASA DENTAL AMK PTE LTD | U4: BRANCH: | V4: =B4 | Y4: BRANCH: | Z4: =B4 | AD4: BRANCH: | AE4: =B4 | AI4: BRANCH: | AJ4: CASA DENTAL AMK PTE LTD | AN4: BRANCH: | AO4: =AE4 | AS4: BRANCH: | AT4: =AO4 | AX4: BRANCH: | AY4: =V4
A5: ALL PROVIDERS SETTLEMENT | E5: DR CHAN KC | I5: DR CHAN CHIEN CHI | M5: DR CELINE TEO | Q5: DR KALIE | U5: DR KEEFE SIM | Y5: DR JENNIFER HOANG | AD5: DR HUANG JIAWEN | AI5: DR ANDREW YIN | AN5: DR YVETTE CHOW | AS5: DR PETER KEITH | AX5: DR ROLAND FOO
C6: ADMIN CHARGES | G6: ADMIN CHARGES | K6: ADMIN CHARGES | O6: ADMIN CHARGES | S6: ADMIN CHARGES | W6: ADMIN CHARGES | AA6: ADMIN CHARGES | AF6: ADMIN CHARGES | AK6: ADMIN CHARGES | AP6: ADMIN CHARGES | AU6: ADMIN CHARGES | AZ6: ADMIN CHARGES
A7: AIA | C7: =B7*0.05*1.09 | E7: AIA | G7: =F7*0.05*1.09 | I7: AIA | K7: =J7*0.05*1.09 | M7: AIA | O7: =N7*0.05*1.09 | Q7: AIA | S7: =R7*0.05*1.09 | U7: AIA | W7: =V7*0.05*1.09 | Y7: AIA | AA7: =Z7*0.05*1.09 | AD7: AIA | AF7: =AE7*0.05*1.09 | AI7: AIA | AK7: =AJ7*0.05*1.09 | AN7: AIA | AP7: =AO7*0.05*1.09 | AS7: AIA | AU7: =AT7*0.05*1.09 | AX7: AIA | AZ7: =AY7*0.05*1.09
A8: ALLIANCE | C8: =B8*0.05*1.09 | E8: ALLIANCE | G8: =F8*0.05*1.09 | I8: ALLIANCE | K8: =J8*0.05*1.09 | M8: ALLIANCE | O8: =N8*0.05*1.09 | U8: ALLIANCE | W8: =V8*0.05*1.09 | Y8: ALLIANCE | AA8: =Z8*0.05*1.09 | AD8: ALLIANCE | AF8: =AE8*0.05*1.09 | AN8: ALLIANCE | AP8: =AO8*0.05*1.09 | AS8: ALLIANCE | AU8: =AT8*0.05*1.09 | AX8: ALLIANCE | AZ8: =AY8*0.05*1.09
A9: AMEX | C9: =B9*0.0195 | E9: AMEX | G9: =F9*0.0195 | I9: AMEX | K9: =J9*0.0195 | M9: AMEX | O9: =N9*0.0195 | Q9: AMEX | S9: =R9*0.0195 | U9: AMEX | W9: =V9*0.0195 | Y9: AMEX | AA9: =Z9*0.0195 | AD9: AMEX | AF9: =AE9*0.0195 | AI9: AMEX | AK9: =AJ9*0.0195 | AN9: AMEX | AP9: =AO9*0.0195 | AS9: AMEX | AU9: =AT9*0.0195 | AX9: AMEX | AZ9: =AY9*0.0195
A10: BABYBONUS | C10: =B10*0.008 | E10: BABYBONUS | G10: =F10*0.008 | I10: BABYBONUS | K10: =J10*0.008 | M10: BABYBONUS | O10: =N10*0.008 | U10: BABYBONUS | W10: =V10*0.008 | Y10: BABYBONUS | AA10: =Z10*0.008 | AD10: BABYBONUS | AF10: =AE10*0.008 | AN10: BABYBONUS | AP10: =AO10*0.008 | AS10: BABYBONUS | AU10: =AT10*0.008 | AX10: BABYBONUS | AZ10: =AY10*0.008
A11: CASH | E11: CASH | I11: CASH | M11: CASH | Q11: ALLIANCE | S11: =R11*0.05*1.09 | U11: CASH | Y11: CASH | AD11: CASH | AI11: ALLIANCE | AK11: =AJ11*0.05*1.09 | AN11: CASH | AS11: CASH | AX11: CASH
A12: CASA VOUCHER | E12: CASA VOUCHER | I12: CASA VOUCHER | M12: CASA VOUCHER | Q12: CASH | U12: CASA VOUCHER | Y12: CASA VOUCHER | AD12: CASA VOUCHER | AI12: CASH | AN12: CASA VOUCHER | AS12: CASA VOUCHER | AX12: CASA VOUCHER
A13: CDC VOUCHER | E13: CDC VOUCHER | I13: CDC VOUCHER | M13: CDC VOUCHER | Q13: CASA VOUCHER | U13: CDC VOUCHER | Y13: CDC VOUCHER | AD13: CDC VOUCHER | AI13: CASA VOUCHER | AN13: CDC VOUCHER | AS13: CDC VOUCHER | AX13: CDC VOUCHER
A14: CHAS | E14: CHAS | I14: CHAS | M14: CHAS | U14: CHAS | Y14: CHAS | AD14: CHAS | AN14: CHAS | AS14: CHAS | AX14: CHAS
A15: CYNERGY | E15: CYNERGY | I15: CYNERGY | M15: CYNERGY | U15: CYNERGY | Y15: CYNERGY | AD15: CYNERGY | AN15: CYNERGY | AS15: CYNERGY | AX15: CYNERGY
A16: DA ADEPT HEALTH | C16: =B16*8% | E16: DA ADEPT HEALTH | G16: =F16*8% | I16: DA ADEPT HEALTH | K16: =J16*8% | M16: DA ADEPT HEALTH | O16: =N16*8% | U16: DA ADEPT HEALTH | W16: =V16*8% | Y16: DA ADEPT HEALTH | AA16: =Z16*8% | AD16: DA ADEPT HEALTH | AF16: =AE16*8% | AN16: DA ADEPT HEALTH | AP16: =AO16*8% | AS16: DA ADEPT HEALTH | AU16: =AT16*8% | AX16: DA ADEPT HEALTH | AZ16: =AY16*8%
A17: DEPOSIT | C17: =G17+K17+O17+O17+S17+W17+AA17+AF17+AP17+AU17+AZ17 | E17: DEPOSIT | I17: DEPOSIT | M17: DEPOSIT | Q17: DEPOSIT | S17: 0 | U17: DEPOSIT | Y17: DEPOSIT | AD17: DEPOSIT | AI17: DEPOSIT | AN17: DEPOSIT | AS17: DEPOSIT | AX17: DEPOSIT
A18: IHP | C18: =B18*0.051*1.09 | E18: IHP | G18: =F18*0.051*1.09 | I18: IHP | K18: =J18*0.051*1.09 | M18: IHP | O18: =N18*0.051*1.09 | U18: IHP | W18: =V18*0.051*1.09 | Y18: IHP | AA18: =Z18*0.051*1.09 | AD18: IHP | AF18: =AE18*0.051*1.09 | AN18: IHP | AP18: =AO18*0.051*1.09 | AS18: IHP | AU18: =AT18*0.051*1.09 | AX18: IHP | AZ18: =AY18*0.051*1.09
A19: JCB | C19: =B19*0.15*1.09 | E19: JCB | G19: =F19*0.15*1.09 | I19: JCB | K19: =J19*0.15*1.09 | M19: JCB | O19: =N19*0.15*1.09 | U19: JCB | W19: =V19*0.15*1.09 | Y19: JCB | AA19: =Z19*0.15*1.09 | AD19: JCB | AF19: =AE19*0.15*1.09 | AN19: JCB | AP19: =AO19*0.15*1.09 | AS19: JCB | AU19: =AT19*0.15*1.09 | AX19: JCB | AZ19: =AY19*0.15*1.09
A20: MASTER | C20: =B20*0.021 | E20: MASTER | G20: =F20*0.021 | I20: MASTER | K20: =J20*0.021 | M20: MASTER | O20: =N20*0.021 | U20: MASTER | W20: =V20*0.021 | Y20: MASTER | AA20: =Z20*0.021 | AD20: MASTER | AF20: =AE20*0.021 | AN20: MASTER | AP20: =AO20*0.021 | AS20: MASTER | AU20: =AT20*0.021 | AX20: MASTER | AZ20: =AY20*0.021
A21: MEDISAVE | E21: MEDISAVE | I21: MEDISAVE | M21: MEDISAVE | U21: MEDISAVE | Y21: MEDISAVE | AD21: MEDISAVE | AN21: MEDISAVE | AS21: MEDISAVE | AX21: MEDISAVE
A22: mednefits | C22: =B22*20% | E22: mednefits | G22: =F22*20% | I22: mednefits | K22: =J22*20% | M22: mednefits | O22: =N22*20% | U22: mednefits | W22: =V22*20% | Y22: mednefits | AA22: =Z22*20% | AD22: mednefits | AF22: =AE22*20% | AN22: mednefits | AP22: =AO22*20% | AS22: mednefits | AU22: =AT22*20% | AX22: mednefits | AZ22: =AY22*20%
A23: MHC | C23: =B23*0.15*1.09 | E23: MHC | G23: =F23*0.15*1.09 | I23: MHC | K23: =J23*0.15*1.09 | M23: MHC | O23: =N23*0.15*1.09 | U23: MHC | W23: =V23*0.15*1.09 | Y23: MHC | AA23: =Z23*0.15*1.09 | AD23: MHC | AF23: =AE23*0.15*1.09 | AN23: MHC | AP23: =AO23*0.15*1.09 | AS23: MHC | AU23: =AT23*0.15*1.09 | AX23: MHC | AZ23: =AY23*0.15*1.09
A24: NETS | C24: =B24*0.008 | E24: NETS | G24: =F24*0.008 | I24: NETS | K24: =J24*0.008 | M24: NETS | O24: =N24*0.008 | U24: NETS | W24: =V24*0.008 | Y24: NETS | AA24: =Z24*0.008 | AD24: NETS | AF24: =AE24*0.008 | AN24: NETS | AP24: =AO24*0.008 | AS24: NETS | AU24: =AT24*0.008 | AX24: NETS | AZ24: =AY24*0.008
A25: PARKWAY | C25: =B25*10% | E25: PARKWAY | G25: =F25*10% | I25: PARKWAY | K25: =J25*10% | M25: PARKWAY | O25: =N25*10% | U25: PARKWAY | W25: =V25*10% | Y25: PARKWAY | AA25: =Z25*10% | AD25: PARKWAY | AF25: =AE25*10% | AN25: PARKWAY | AP25: =AO25*10% | AS25: PARKWAY | AU25: =AT25*10% | AX25: PARKWAY | AZ25: =AY25*10%
A26: PAYNOW | E26: PAYNOW | I26: PAYNOW | M26: PAYNOW | U26: PAYNOW | Y26: PAYNOW | AD26: PAYNOW | AN26: PAYNOW | AS26: PAYNOW | AX26: PAYNOW
A27: RHI | E27: RHI | I27: RHI | M27: RHI | U27: RHI | Y27: RHI | AD27: RHI | AN27: RHI | AS27: RHI | AX27: RHI
A28: SAH | C28: =B28*8% | E28: SAH | G28: =F28*8% | I28: SAH | K28: =J28*8% | M28: SAH | O28: =N28*8% | U28: SAH | W28: =V28*8% | Y28: SAH | AA28: =Z28*8% | AD28: SAH | AF28: =AE28*8% | AN28: SAH | AP28: =AO28*8% | AS28: SAH | AU28: =AT28*8% | AX28: SAH | AZ28: =AY28*8%
A29: UNION PAY | C29: =B29*2.5% | E29: UNION PAY | G29: =F29*2.5% | I29: UNION PAY | K29: =J29*2.5% | M29: UNION PAY | O29: =N29*2.5% | U29: UNION PAY | W29: =V29*2.5% | Y29: UNION PAY | AA29: =Z29*2.5% | AD29: UNION PAY | AF29: =AE29*2.5% | AN29: UNION PAY | AP29: =AO29*2.5% | AS29: UNION PAY | AU29: =AT29*2.5% | AX29: UNION PAY | AZ29: =AY29*2.5%
A30: VISA | C30: =B30*0.021 | E30: VISA | G30: =F30*0.021 | I30: VISA | K30: =J30*0.021 | M30: VISA | O30: =N30*0.021 | U30: VISA | W30: =V30*0.021 | Y30: VISA | AA30: =Z30*0.021 | AD30: VISA | AF30: =AE30*0.021 | AN30: VISA | AP30: =AO30*0.021 | AS30: VISA | AU30: =AT30*0.021 | AX30: VISA | AZ30: =AY30*0.021
A31: TOTAL INCOME | B31: =SUM(B7:B30) | C31: =SUM(C7:C30) | E31: DR TOTAL INCOME | F31: =SUM(F7:F30) | G31: =SUM(G7:G30) | I31: DR TOTAL INCOME | J31: =SUM(J7:J30) | K31: =SUM(K7:K30) | M31: DR TOTAL INCOME | N31: =SUM(N7:N30) | O31: =SUM(O7:O30) | U31: DR TOTAL INCOME | V31: =SUM(V7:V30) | W31: =SUM(W7:W30) | Y31: DR TOTAL INCOME | Z31: =SUM(Z7:Z30) | AA31: =SUM(AA7:AA30) | AD31: DR TOTAL INCOME | AE31: =SUM(AE7:AE30) | AF31: =SUM(AF7:AF30) | AN31: DR TOTAL INCOME | AO31: =SUM(AO7:AO30) | AP31: =SUM(AP7:AP30) | AS31: DR TOTAL INCOME | AT31: =SUM(AT7:AT30) | AU31: =SUM(AU7:AU30) | AX31: DR TOTAL INCOME | AY31: =SUM(AY7:AY30) | AZ31: =SUM(AZ7:AZ30)
B33: EXPENSES | F33: DEDUCTIONS | H33: REMARKS | J33: DEDUCTIONS | L33: REMARKS | N33: DEDUCTIONS | P33: REMARKS | R33: DEDUCTIONS | T33: REMARKS | V33: DEDUCTIONS | X33: REMARKS | Z33: DEDUCTIONS | AB33: REMARKS | AE33: DEDUCTIONS | AG33: REMARKS | AJ33: DEDUCTIONS | AL33: REMARKS | AO33: DEDUCTIONS | AQ33: REMARKS | AT33: DEDUCTIONS | AV33: REMARKS | AY33: DEDUCTIONS | BA33: REMARKS
B34: ADMIN FEE | C34: =SUM(C7:C30) | F34: ADMIN CHARGES | G34: =G31 | J34: ADMIN CHARGES | K34: =K31 | N34: ADMIN CHARGES | O34: =O31 | R34: ADMIN CHARGES | S34: =#REF! | V34: ADMIN CHARGES | W34: =W31 | Z34: ADMIN CHARGES | AA34: =AA31 | AE34: ADMIN CHARGES | AF34: =AF31 | AJ34: ADMIN CHARGES | AK34: =#REF! | AO34: ADMIN CHARGES | AP34: =AP31 | AT34: ADMIN CHARGES | AU34: =AU31 | AY34: ADMIN CHARGES | AZ34: =AZ31
B35: GST | C35: =K35+O35+AA35+AF35+AM35+AP35+T35+W35+AU35+AZ35 | F35: GST | J35: GST | N35: GST | R35: GST | V35: GST | Z35: GST | AE35: GST | AJ35: GST | AO35: GST | AT35: GST | AY35: GST
B36: RENTAL | F36: ICC-5 | J36: ICC-5 | N36: ICC-5 | V36: ICC-5 | Z36: ICC-5 | AE36: ICC-5 | AO36: ICC-5 | AT36: ICC-5 | AY36: ICC-5
B37: LOAN INTEREST | F37: PRODUCTS | J37: PRODUCTS | N37: PRODUCTS | V37: PRODUCTS | Z37: PRODUCTS | AE37: PRODUCTS | AO37: PRODUCTS | AT37: PRODUCTS | AY37: PRODUCTS
B38: IRAS TAX | C38: 181.05 | D38: JAN 181.05 | F38: ORTHO (B+B) | J38: ORTHO (B+B) | N38: ORTHO (B+B) | V38: ORTHO (B+B) | Z38: ORTHO (B+B) | AE38: ORTHO (B+B) | AO38: ORTHO (B+B) | AT38: ORTHO (B+B) | AY38: ORTHO (B+B)
B39: CK SECRETARIAL / ACCOUNTS SERVICES | D39: FEB 50895 | F39: ABUTMENTS | J39: ABUTMENTS | N39: ABUTMENTS | V39: ABUTMENTS | Z39: ABUTMENTS | AE39: ABUTMENTS | AO39: ABUTMENTS | AT39: ABUTMENTS | AY39: ABUTMENTS
B40: TOWN COUNCIL | C40: 286.13 | D40: MAR-JUN 25420 | F40: IMPLANT | J40: IMPLANT | N40: IMPLANT | V40: IMPLANT | Z40: IMPLANT | AE40: IMPLANT | AO40: IMPLANT | AT40: IMPLANT | AY40: IMPLANT
B41: SERVICE & CONSERVANCY CHARGES | C41: 800 | F41: SKY LAB | J41: SKY LAB | N41: SKY LAB | V41: SKY LAB | Z41: SKY LAB | AE41: SKY LAB | AO41: SKY LAB | AT41: SKY LAB | AY41: SKY LAB
B42: SP | F42: DIGICADCAM | J42: DIGICADCAM | N42: DIGICADCAM | V42: DIGICADCAM | Z42: DIGICADCAM | AE42: DIGICADCAM | AO42: DIGICADCAM | AT42: DIGICADCAM | AY42: DIGICADCAM
B43: SINGTEL | F43: OTHER LAB | J43: OTHER LAB | N43: OTHER LAB | V43: OTHER LAB | Z43: OTHER LAB | AE43: OTHER LAB | AO43: OTHER LAB | AT43: OTHER LAB | AY43: OTHER LAB
B44: PRODUCTS | C44: =G37+K37+O37+S59+W37+AA37+AF37+AK59+AP37+AU37+AZ37 | F44: INVISALIGN | J44: INVISALIGN | N44: INVISALIGN | V44: INVISALIGN | Z44: INVISALIGN | AE44: INVISALIGN | AO44: INVISALIGN | AT44: INVISALIGN | AY44: INVISALIGN
B45: ADMIN STAFF & OFFICE RENTAL | F45: TRANSFER (+) | J45: TRANSFER (+) | N45: TRANSFER (+) | V45: TRANSFER (+) | Z45: TRANSFER (+) | AE45: TRANSFER (+) | AO45: TRANSFER (+) | AT45: TRANSFER (+) | AY45: TRANSFER (+)
B46: SUPPLIERS | F46: TRANSFER (-) | J46: TRANSFER (-) | N46: TRANSFER (-) | V46: TRANSFER (-) | Z46: TRANSFER (-) | AE46: TRANSFER (-) | AO46: TRANSFER (-) | AT46: TRANSFER (-) | AY46: TRANSFER (-)
B47: VOUCHER | C47: =B12 | F47: REFUND/REFERRAL | J47: REFUND/REFERRAL | N47: REFUND/REFERRAL | V47: REFUND | Z47: REFUND | AE47: REFUND | AO47: REFUND | AT47: REFUND | AY47: REFUND
B48: PETTY CASH | F48: VOUCHER | G48: =F12 | J48: VOUCHER | N48: VOUCHER | V48: VOUCHER | Z48: VOUCHER | AE48: SEDATION | AO48: SEDATION | AT48: SEDATION | AY48: SEDATION
B49: STOCKS / CONSUMABLES FEES | F49: RETAINERS/BT/SPLINT | J49: RETAINERS/BT/SPLINT | N49: RETAINERS/BT/SPLINT | V49: RETAINERS/BT/SPLINT | Z49: RETAINERS/BT/SPLINT | AE49: RETAINERS/BT/SPLINT | AO49: RETAINERS/BT/SPLINT | AT49: RETAINERS/BT/SPLINT | AY49: RETAINERS/BT/SPLINT
B50: MARKETING FEE | F50: INSTALLMENT | J50: INSTALLMENT | N50: INSTALLMENT | V50: INSTALLMENT | Z50: INSTALLMENT | AE50: INSTALLMENT | AO50: INSTALLMENT | AT50: INSTALLMENT | AY50: INSTALLMENT
B51: INVISALIGN | C51: =G44+K44+O44+S66+W44+AA44+AF44+AK66+AP44+AU44 | F51: DEDUCTIONS | J51: DEDUCTIONS | N51: DEDUCTIONS | V51: DEDUCTIONS | Z51: DEDUCTIONS | AE51: DEDUCTIONS | AO51: DEDUCTIONS | AT51: DEDUCTIONS | AY51: DEDUCTIONS
B52: IMPLANT | C52: =G40+O40+S62+W40+AA40+AF40+K40+AK62+AP40+AU40
B53: SKYLAB | C53: =G41+O41+W41+S63+K41+AA41+AF41+AK63+AP41+AU41 | F53: TOTAL | G53: =F31-G34-G35-G37-G36-G38-G39-G40-G41-G42-G43-G44+G45-G46-G47-G48-G49-G50-G51 | J53: TOTAL | K53: =J31-K34-K35-K36-K37-K38-K39-K40-K41-K42-K43-K44+K45-K46-K47-K48-K49-K50-K51 | N53: TOTAL | O53: =N31-O34-O35-O36-O37-O38-O39-O40-O41-O42-O43-O44+O45-O46-O47-O48-O49-O50-O51 | V53: TOTAL | W53: =V31-W34-W35-W36-W37-W38-W39-W40-W41-W42-W43-W44+W45-W46-W47-W48-W49-W50-W51 | Z53: TOTAL | AA53: =Z31-AA34-AA35-AA36-AA37-AA38-AA39-AA40-AA41-AA42-AA43-AA44+AA45-AA46-AA47-AA48-AA49-AA50-AA51 | AE53: TOTAL | AF53: =AE31-AF34-AF35-AF36-AF37-AF38-AF39-AF40-AF41-AF42-AF43-AF44+AF45-AF46-AF47-AF48-AF49-AF50-AF51 | AO53: TOTAL | AP53: =AO31-AP34-AP35-AP36-AP37-AP38-AP39-AP40-AP41-AP42-AP43-AP44+AP45-AP46-AP47-AP48-AP49-AP50-AP51 | AT53: TOTAL | AU53: =AT31-AU34-AU35-AU36-AU37-AU38-AU39-AU40-AU41-AU42-AU43-AU44+AU45-AU46-AU47-AU48-AU49-AU50-AU51 | AY53: TOTAL | AZ53: =AY31-AZ34-AZ35-AZ36-AZ37-AZ38-AZ39-AZ40-AZ41-AZ42-AZ43-AZ44+AZ45-AZ46-AZ47-AZ48-AZ49-AZ50-AZ51
B54: DIGICADCAM | C54: =G42+O42+W42+AA42+AF42+S64+K42+AK64+AP42+AU42 | F54: DOCTORS FEE BEFORE DEDUCTION | G54: =G53/2+G55 | J54: DOCTORS FEE BEFORE DEDUCTION | K54: =K53/2+K55 | N54: DOCTORS PAY | O54: =(O53*50%)+O55 | V54: DOCTORS PAY | W54: =(W53*50%)+W55 | Z54: DOCTORS PAY | AA54: =(AA53*50%)+AA55 | AE54: DOCTORS PAY | AF54: =(AF53*40%)+AF55 | AO54: DOCTORS PAY | AP54: =(AP53*45%)+AP55 | AT54: DOCTORS PAY | AU54: =(AU53*50%)+AU55 | AY54: DOCTORS PAY | AZ54: =(AZ53*50%)+AZ55
B55: OTHER LAB | C55: =G43+O43+K43+S65+W43+AA43+AF43+AK65+AP43+AU43 | F55: ADJUSTMENTS (+) | J55: ADJUSTMENTS (+) | N55: ADJUSTMENTS (+) | V55: ADJUSTMENTS (+) | Z55: ADJUSTMENTS (+) | AE55: ADJUSTMENTS (+) | AO55: ADJUSTMENTS (+) | AT55: ADJUSTMENTS (+) | AY55: ADJUSTMENTS (+)
B56: ORTHO (B+B) | C56: =G38+K38+O38+S60+W38+AA38+AF38+AK60+AP38+AU38 | F56: ADJUSTMENTS (-) | G56: =G61+G65 | H56: ADDN MARKETING& MEDISAVE ADMIN | J56: ADJUSTMENTS (-) | K56: =K61+K65 | L56: ADDN MARKETING & MEDISAVE ADMIN | N56: ADJUSTMENTS (-) | O56: =O61+O65 | P56: ADDN MARKETING & MEDISAVE ADMIN | V56: ADJUSTMENTS (-) | W56: =W61+W65 | X56: ADDN MKTRG & MEDISAVE ADMIN | Z56: ADJUSTMENTS (-) | AA56: =AA61+AA65 | AB56: MARKETING FEE & MEDISAVE ADMIN | AE56: ADJUSTMENTS (-) | AF56: =AF61+AF65 | AG56: MARKETING FEE & MEDISAVE ADMIN | AO56: ADJUSTMENTS (-) | AP56: =AP61+AP65 | AQ56: MARKETING FEE & MEDISAVE ADMIN | AT56: ADJUSTMENTS (-) | AU56: =AU61+AU65 | AV56: MARKETING FEE & MEDISAVE ADMIN | AY56: ADJUSTMENTS (-) | AZ56: =AZ61+AZ65 | BA56: MARKETING FEE & MEDISAVE ADMIN
B57: ABUTMENT | C57: =O39+G39+K39+S61+AA39+W39+AF39+AK61 | F57: NET PAY | G57: =G54-G56 | J57: NET PAY | K57: =K54-K56 | N57: NET PAY | O57: =O54-O56 | V57: NET PAY | W57: =W54-W56 | Z57: NET PAY | AA57: =AA54-AA56 | AE57: NET PAY | AF57: =AF54-AF56 | AO57: NET PAY | AP57: =AP54-AP56 | AT57: NET PAY | AU57: =AU54-AU56 | AY57: NET PAY | AZ57: =AZ54-AZ56
B58: REFUND / REFERRAL | C58: =G47+K47+O47+S69+W47+AA47+AF47+AK69 | R58: ICC-5 | AJ58: ICC-5
B59: DOCTORS PAY | C59: =G54+K54+O54+W54+AA54+AF54+AP54+AU54+AZ54 | F59: MEDISAVE ADMIN FEE CALCULATION: | J59: MEDISAVE ADMIN FEE CALCULATION: | N59: MEDISAVE ADMIN FEE CALCULATION: | R59: PRODUCTS | V59: MEDISAVE ADMIN FEE CALCULATION: | Z59: MEDISAVE ADMIN FEE CALCULATION: | AE59: MEDISAVE ADMIN FEE CALCULATION: | AJ59: PRODUCTS | AO59: MEDISAVE ADMIN FEE CALCULATION: | AT59: MEDISAVE ADMIN FEE CALCULATION: | AY59: MEDISAVE ADMIN FEE CALCULATION:
B60: NURSE PAY (BASIC PAY) | F60: Medisave Claim | G60: Admin Fee | H60: REMARKS | J60: Medisave Claim | K60: Admin Fee | L60: REMARKS | N60: Medisave Claim | O60: Admin Fee | P60: REMARKS | R60: ORTHO (B+B) | V60: Medisave Claim | W60: Admin Fee | X60: REMARKS | Z60: Medisave Claim | AA60: Admin Fee | AB60: REMARKS | AE60: Medisave Claim | AF60: Admin Fee | AG60: REMARKS | AJ60: ORTHO (B+B) | AO60: Medisave Claim | AP60: Admin Fee | AQ60: REMARKS | AT60: Medisave Claim | AU60: Admin Fee | AV60: REMARKS | AY60: Medisave Claim | AZ60: Admin Fee | BA60: REMARKS
B61: NURSE PAY (INCENTIVE) | G61: =F61*20 | K61: =J61*20 | O61: =N61*20 | R61: ABUTMENTS | W61: =V61*20 | AA61: =Z61*20 | AF61: =AE61*20 | AJ61: ABUTMENTS | AP61: =AO61*20 | AT61: 2 | AU61: =AT61*20 | AZ61: =AY61*20
B62: NURSE TRANSFER FEE | R62: IMPLANT | AJ62: IMPLANT
B63: TANK CULTURE | C63: 163.5 | F63: ADDITIONAL MARKETING: | J63: ADDITIONAL MARKETING: | N63: ADDITIONAL MARKETING: | R63: SKY LAB | V63: ADDITIONAL MARKETING: | Z63: ADDITIONAL MARKETING: | AE63: ADDITIONAL MARKETING: | AJ63: SKY LAB | AO63: ADDITIONAL MARKETING: | AT63: ADDITIONAL MARKETING: | AY63: ADDITIONAL MARKETING:
B64: SHARP BIN | F64: MONTH | G64: AMOUNT | H64: REMARKS | J64: MONTH | K64: AMOUNT | L64: REMARKS | N64: MONTH | O64: AMOUNT | P64: REMARKS | R64: DIGICADCAM | V64: MONTH | W64: AMOUNT | X64: REMARKS | Z64: MONTH | AA64: AMOUNT | AB64: REMARKS | AE64: MONTH | AF64: AMOUNT | AG64: REMARKS | AJ64: DIGICADCAM | AO64: MONTH | AP64: AMOUNT | AQ64: REMARKS | AT64: MONTH | AU64: AMOUNT | AV64: REMARKS | AY64: MONTH | AZ64: AMOUNT | BA64: REMARKS
B65: COURIER | C65: 129.44 | F65: =B3 | J65: =F65 | K65: 120 | N65: =F65 | O65: 150 | R65: OTHER LAB | V65: =V3 | W65: 150 | Z65: =V65 | AA65: 180 | AE65: =AE3 | AF65: 150 | AJ65: OTHER LAB | AO65: =AO3 | AP65: 120 | AT65: =AT3 | AU65: 150 | AY65: =AY3
B66: REPAIR & MAINTENANCE | R66: INVISALIGN | AJ66: INVISALIGN
B67: MOM LEVY | C67: =400+400+600 | F67: OTHERS: (CPF,PERSONAL REFUND, COURSEFEE) | J67: OTHERS: (CPF,PERSONAL REFUND, COURSEFEE) | N67: OTHERS: (CPF,PERSONAL REFUND, COURSEFEE) | R67: TRANSFER (+) | V67: OTHERS: (CPF,PERSONAL REFUND, COURSEFEE) | Z67: OTHERS: (CPF,PERSONAL REFUND, COURSEFEE) | AE67: OTHERS: (CPF,PERSONAL REFUND, COURSEFEE) | AJ67: TRANSFER (+) | AO67: OTHERS: (CPF,PERSONAL REFUND, COURSEFEE) | AT67: OTHERS: (CPF,PERSONAL REFUND, COURSEFEE) | AY67: OTHERS: (CPF,PERSONAL REFUND, COURSEFEE)
B68: PURCHASE PC | R68: TRANSFER (-) | AJ68: TRANSFER (-)
F69: DETAILS | G69: AMOUNT | J69: DETAILS | K69: AMOUNT | N69: DETAILS | O69: AMOUNT | R69: REFUND | V69: DETAILS | W69: AMOUNT | Z69: DETAILS | AA69: AMOUNT | AE69: DETAILS | AF69: AMOUNT | AJ69: REFUND | AO69: DETAILS | AP69: AMOUNT | AT69: DETAILS | AU69: AMOUNT | AY69: DETAILS | AZ69: AMOUNT
F70: CPF CONT SALARY | R70: VOUCHER | AJ70: SEDATION
AJ71: RETAINERS/BT/SPLINT
B72: TOTAL | C72: =B31-C34-C35-C58-C36-C37-C42-C43-C38-C46-C39-C45-C48-C49-C51-C50-C55-C54-C53-C59-C60-C61-C62-C47-C63-C40-C64-C41-C67-C66-C65-C90-C91-C92-C93-C94-C95-C68-C69-C70 | AJ72: INSTALLMENT
B73: FOR INCENTIVE % | C73: =B31-C34-C35-C58-C42-C43-C46-C45-C48-C44-C49-C50-C47-C63-C40-C64-C41-C65-C93-C95-C94-C66-C92-C90-C68-C69-C70 | AJ73: DEDUCTIONS
B74: PERCENT | C74: =VLOOKUP(C73,'% RATES INCENTIVES'!C:D,2,TRUE)
A75: INCOME LESS GST | B75: =B31-C35 | C75: =C72/B75*100 | D75: % | R75: TOTAL | S75: =#REF!-S34-S35-S59-S58-S60-S61-S62-S63-S64-S65-S66+S67-S68-S69-S70-S71-S72-S73 | AJ75: TOTAL | AK75: =#REF!-AK34-AK35-AK58-AK59-AK60-AK61-AK62-AK63-AK64-AK65-AK66+AK67-AK68-AK69-AK70-AK71-AK72-AK73
R76: DOCTORS PAY | S76: =(S75*50%)+S77 | AJ76: DOCTORS PAY | AK76: =(AK75*50%)+AK77
B77: MEDISAVE ADMIN | C77: =G61+K61+O61+S83+W61+AA61+AF61+AK83+AP61+AU61 | D77: =C77/20 | F77: TOTAL PAYMENT | G77: =G57-G70-G74-G75-G71-G72-G73 | J77: TOTAL PAYMENT | K77: =K57-K70-K74-K75-K71-K72-K73 | N77: TOTAL PAYMENT | O77: =O57-O70-O74-O75-O71-O72-O73 | R77: ADJUSTMENTS (+) | V77: TOTAL PAYMENT | W77: =W57-W70-W74-W75-W71-W72-W73 | Z77: TOTAL PAYMENT | AA77: =AA57-AA70-AA74-AA75-AA71-AA72-AA73 | AE77: TOTAL PAYMENT | AF77: =AF57-AF70-AF74-AF75-AF71-AF72-AF73 | AJ77: ADJUSTMENTS (+) | AO77: TOTAL PAYMENT | AP77: =AP57-AP70-AP74-AP75-AP71-AP72-AP73 | AT77: TOTAL PAYMENT | AU77: =AU57-AU70-AU74-AU75-AU71-AU72-AU73 | AY77: TOTAL PAYMENT | AZ77: =AZ57-AZ70-AZ74-AZ75-AZ71-AZ72-AZ73
B78: ADDITIONAL MARKETING | C78: =G65+K65+O65+S87+W65+AA65+AF65+AP65+AU65+AZ65 | R78: ADJUSTMENTS (-) | S78: =S83+S87 | AJ78: ADJUSTMENTS (-) | AK78: =AK83+AK87 | AL78: MARKETING FEE & MEDISAVE ADMIN
B79: DOCTORS PERSONAL DEDUCTION | C79: =G70+G74+G75+K70+K74+K75+O70+O74+O75+S92+S96+S97+W70+W74+W75+AA70+AA74+AA75+AF70+AF74+AF75+G71+G72+G73+K71+K72+K73+O71+O72+O73+S93+S94+S95+W71+W72+W73+AA71+AA72+AA73+AF71+AF72+AF73+AP70+AP71+AP72+AP73+AP74+AP75+AU70+AU71+AU72+AU73+AU74+AU75+AZ70+AZ71+AZ72+AZ73+AZ74+AZ75 | R79: NET PAY | S79: =S76-S78 | AJ79: NET PAY | AK79: =AK76-AK78
B80: TOTAL | C80: =SUM(C77:C79)
B81: TOTAL ICC-5 | C81: =G36+K36+O36+S58+AA36+W36+AF36+AP36+AU36+AZ36 | R81: MEDISAVE ADMIN FEE CALCULATION: | AJ81: MEDISAVE ADMIN FEE CALCULATION:
R82: Medisave Claim | S82: Admin Fee | T82: REMARKS | AJ82: Medisave Claim | AK82: Admin Fee | AL82: REMARKS
B83: NURSES FEE-REVENUE | C83: =(C60+C61+C62)/B31 | S83: =R83*20 | AK83: =AJ83*20
B84: CONSUMABLE EXCL OFFICE RENT - REVENUE | C84: =(C49+C46+C48)/B31
B85: OFFICE RENT & ADMIN STAFF - REVENUE | C85: =(C45/B31) | R85: ADDITIONAL MARKETING: | AJ85: ADDITIONAL MARKETING:
B86: MARKETING - REVENUE | C86: =C50/B31 | R86: MONTH | S86: AMOUNT | T86: REMARKS | AJ86: MONTH | AK86: AMOUNT | AL86: REMARKS
R87: =R3 | AJ87: =AJ3
R89: OTHERS: (CPF,PERSONAL REFUND, COURSEFEE) | AJ89: OTHERS: (CPF,PERSONAL REFUND, COURSEFEE)
R91: DETAILS | S91: AMOUNT | AJ91: DETAILS | AK91: AMOUNT
AH92: feb 2191
R99: TOTAL CHEQUE AMOUNT | S99: =S79-S92-S96-S97-S93-S94-S95 | AJ99: TOTAL CHEQUE AMOUNT | AK99: =AK79-AK92-AK96-AK97-AK93-AK94-AK95

Sheet BB SETTLEMENT CALC NEW
A3: MONTH/YEAR: | B3: 46023 | E3: MONTH/YEAR: | F3: =B3 | I3: MONTH/YEAR: | J3: =B3 | M3: MONTH/YEAR: | N3: =B3 | Q3: MONTH/YEAR: | R3: =B3 | U3: MONTH/YEAR: | V3: =B3 | Y3: MONTH/YEAR: | Z3: =B3 | AD3: MONTH/YEAR: | AE3: =B3 | AI3: MONTH/YEAR: | AJ3: =AE3
A4: BRANCH: | B4: CASA DENTAL BUKIT BATOK PTE LTD | E4: BRANCH: | F4: =B4 | I4: BRANCH: | J4: =F4 | M4: BRANCH: | N4: =J4 | Q4: BRANCH: | R4: CASA DENTAL AMK PTE LTD | U4: BRANCH: | V4: =N4 | Y4: BRANCH: | Z4: =V4 | AD4: BRANCH: | AE4: =Z4 | AI4: BRANCH: | AJ4: CASA DENTAL AMK PTE LTD
A5: ALL PROVIDERS SETTLEMENT | E5: DR ANGELA TRAN | I5: DR JENNIFER HOANG | M5: DR KALIE CHIA | Q5: DR KALIE | U5: DR YVETTE CHOW | Y5: DR PETER KEITH | AD5: DR NICHOLAS LIEW | AI5: DR ANDREW YIN
C6: ADMIN CHARGES | G6: ADMIN CHARGES | J6: TOTALS | K6: ADMIN CHARGES | O6: ADMIN CHARGES | S6: ADMIN CHARGES | W6: ADMIN CHARGES | AA6: ADMIN CHARGES | AF6: ADMIN CHARGES | AK6: ADMIN CHARGES
A7: AIA | C7: =B7*0.05*1.09 | E7: AIA | G7: =F7*0.05*1.09 | I7: AIA | K7: =J7*0.05*1.09 | M7: AIA | O7: =N7*0.05*1.09 | Q7: AIA | S7: =R7*0.05*1.09 | U7: AIA | W7: =V7*0.05*1.09 | Y7: AIA | AA7: =Z7*0.05*1.09 | AD7: AIA | AF7: =AE7*0.05*1.09 | AI7: AIA | AK7: =AJ7*0.05*1.09
A8: ALLIANCE | C8: =B8*0.05*1.09 | E8: ALLIANCE | G8: =F8*0.05*1.09 | I8: ALLIANCE | K8: =J8*0.05*1.09 | M8: ALLIANCE | O8: =N8*0.05*1.09 | U8: ALLIANCE | W8: =V8*0.05*1.09 | Y8: ALLIANCE | AA8: =Z8*0.05*1.09 | AD8: ALLIANCE | AF8: =AE8*0.05*1.09
A9: AMEX | C9: =B9*0.0195 | E9: AMEX | G9: =F9*0.0195 | I9: AMEX | K9: =J9*0.0195 | M9: AMEX | O9: =N9*0.0195 | Q9: AMEX | S9: =R9*0.0195 | U9: AMEX | W9: =V9*0.0195 | Y9: AMEX | AA9: =Z9*0.0195 | AD9: AMEX | AF9: =AE9*0.0195 | AI9: AMEX | AK9: =AJ9*0.0195
A10: BABYBONUS | C10: =B10*0.008 | E10: BABYBONUS | G10: =F10*0.008 | I10: BABYBONUS | K10: =J10*0.008 | M10: BABYBONUS | O10: =N10*0.008 | U10: BABYBONUS | W10: =V10*0.008 | Y10: BABYBONUS | AA10: =Z10*0.008 | AD10: BABYBONUS | AF10: =AE10*0.008
A11: CASH | E11: CASH | I11: CASH | M11: CASH | Q11: ALLIANCE | S11: =R11*0.05*1.09 | U11: CASH | Y11: CASH | AD11: CASH | AI11: ALLIANCE | AK11: =AJ11*0.05*1.09
A12: CASA VOUCHER | E12: CASA VOUCHER | I12: CASA VOUCHER | M12: CASA VOUCHER | Q12: CASH | U12: CASA VOUCHER | Y12: CASA VOUCHER | AD12: CASA VOUCHER | AI12: CASH
A13: CDC VOUCHER | E13: CDC VOUCHER | I13: CDC VOUCHER | M13: CDC VOUCHER | Q13: CASA VOUCHER | U13: CDC VOUCHER | Y13: CDC VOUCHER | AD13: CDC VOUCHER | AI13: CASA VOUCHER
A14: CHAS | E14: CHAS | I14: CHAS | M14: CHAS | U14: CHAS | Y14: CHAS | AD14: CHAS
A15: CYNERGY | E15: CYNERGY | I15: CYNERGY | M15: CYNERGY | U15: CYNERGY | Y15: CYNERGY | AD15: CYNERGY
A16: DA ADEPT HEALTH | C16: =B16*8% | E16: DA ADEPT HEALTH | G16: =F16*8% | I16: DA ADEPT HEALTH | K16: =J16*8% | M16: DA ADEPT HEALTH | O16: =N16*8% | U16: DA ADEPT HEALTH | W16: =V16*8% | Y16: DA ADEPT HEALTH | AA16: =Z16*8% | AD16: DA ADEPT HEALTH | AF16: =AE16*8%
A17: DEPOSIT | C17: =G17+K17+O17+O17+S17+W17+AA17+AF17 | E17: DEPOSIT | I17: DEPOSIT | M17: DEPOSIT | Q17: DEPOSIT | S17: 0 | U17: DEPOSIT | Y17: DEPOSIT | AD17: DEPOSIT | AI17: DEPOSIT
A18: IHP | C18: =B18*0.051*1.09 | E18: IHP | G18: =F18*0.051*1.09 | I18: IHP | K18: =J18*0.051*1.09 | M18: IHP | O18: =N18*0.051*1.09 | U18: IHP | W18: =V18*0.051*1.09 | Y18: IHP | AA18: =Z18*0.051*1.09 | AD18: IHP | AF18: =AE18*0.051*1.09
A19: JCB | C19: =B19*0.15*1.09 | E19: JCB | G19: =F19*0.15*1.09 | I19: JCB | K19: =J19*0.15*1.09 | M19: JCB | O19: =N19*0.15*1.09 | U19: JCB | W19: =V19*0.15*1.09 | Y19: JCB | AA19: =Z19*0.15*1.09 | AD19: JCB | AF19: =AE19*0.15*1.09
A20: MASTER | C20: =B20*0.0225 | E20: MASTER | G20: =F20*0.0225 | I20: MASTER | K20: =J20*0.0225 | M20: MASTER | O20: =N20*0.0225 | U20: MASTER | W20: =V20*0.0225 | Y20: MASTER | AA20: =Z20*0.0225 | AD20: MASTER | AF20: =AE20*0.0225
A21: MEDISAVE | E21: MEDISAVE | I21: MEDISAVE | M21: MEDISAVE | U21: MEDISAVE | Y21: MEDISAVE | AD21: MEDISAVE
A22: mednefits | C22: =B22*20% | E22: mednefits | G22: =F22*20% | I22: mednefits | K22: =J22*20% | M22: mednefits | O22: =N22*20% | U22: mednefits | W22: =V22*20% | Y22: mednefits | AA22: =Z22*20% | AD22: mednefits | AF22: =AE22*20%
A23: MHC | C23: =B23*0.15*1.09 | E23: MHC | G23: =F23*0.15*1.09 | I23: MHC | K23: =J23*0.15*1.09 | M23: MHC | O23: =N23*0.15*1.09 | U23: MHC | W23: =V23*0.15*1.09 | Y23: MHC | AA23: =Z23*0.15*1.09 | AD23: MHC | AF23: =AE23*0.15*1.09
A24: NETS | C24: =B24*0.008 | E24: NETS | G24: =F24*0.008 | I24: NETS | K24: =J24*0.008 | M24: NETS | O24: =N24*0.008 | U24: NETS | W24: =V24*0.008 | Y24: NETS | AA24: =Z24*0.008 | AD24: NETS | AF24: =AE24*0.008
A25: PARKWAY | C25: =B25*10% | E25: PARKWAY | G25: =F25*10% | I25: PARKWAY | K25: =J25*10% | M25: PARKWAY | O25: =N25*10% | U25: PARKWAY | W25: =V25*10% | Y25: PARKWAY | AA25: =Z25*10% | AD25: PARKWAY | AF25: =AE25*10%
A26: PAYNOW | E26: PAYNOW | I26: PAYNOW | M26: PAYNOW | U26: PAYNOW | Y26: PAYNOW | AD26: PAYNOW
A27: RHI | E27: RHI | I27: RHI | M27: RHI | U27: RHI | Y27: RHI | AD27: RHI
A28: SAH | C28: =B28*8% | E28: SAH | G28: =F28*8% | I28: SAH | K28: =J28*8% | M28: SAH | O28: =N28*8% | U28: SAH | W28: =V28*8% | Y28: SAH | AA28: =Z28*8% | AD28: SAH | AF28: =AE28*8%
A29: UNION PAY | C29: =B29*2.5% | E29: UNION PAY | G29: =F29*2.5% | I29: UNION PAY | K29: =J29*2.5% | M29: UNION PAY | O29: =N29*2.5% | U29: UNION PAY | W29: =V29*2.5% | Y29: UNION PAY | AA29: =Z29*2.5% | AD29: UNION PAY | AF29: =AE29*2.5%
A30: VISA | C30: =B30*0.0225 | E30: VISA | G30: =F30*0.0225 | I30: VISA | K30: =J30*0.0225 | M30: VISA | O30: =N30*0.0225 | U30: VISA | W30: =V30*0.0225 | Y30: VISA | AA30: =Z30*0.0225 | AD30: VISA | AF30: =AE30*0.0225
A31: TOTAL INCOME | B31: =SUM(B7:B30) | C31: =SUM(C7:C30) | E31: DR TOTAL INCOME | F31: =SUM(F7:F30) | G31: =SUM(G7:G30) | I31: DR TOTAL INCOME | J31: =SUM(J7:J30) | K31: =SUM(K7:K30) | M31: DR TOTAL INCOME | N31: =SUM(N7:N30) | O31: =SUM(O7:O30) | U31: DR TOTAL INCOME | V31: =SUM(V7:V30) | W31: =SUM(W7:W30) | Y31: DR TOTAL INCOME | Z31: =SUM(Z7:Z30) | AA31: =SUM(AA7:AA30) | AD31: DR TOTAL INCOME | AE31: =SUM(AE7:AE30) | AF31: =SUM(AF7:AF30)
B33: EXPENSES | F33: DEDUCTIONS | H33: REMARKS | J33: DEDUCTIONS | L33: REMARKS | N33: DEDUCTIONS | P33: REMARKS | R33: DEDUCTIONS | T33: REMARKS | V33: DEDUCTIONS | X33: REMARKS | Z33: DEDUCTIONS | AB33: REMARKS | AE33: DEDUCTIONS | AG33: REMARKS | AJ33: DEDUCTIONS | AL33: REMARKS
B34: ADMIN FEE | C34: =SUM(C7:C30) | F34: ADMIN CHARGES | G34: =G31 | J34: ADMIN CHARGES | K34: =K31 | N34: ADMIN CHARGES | O34: =O31 | R34: ADMIN CHARGES | S34: =#REF! | V34: ADMIN CHARGES | W34: =W31 | Z34: ADMIN CHARGES | AA34: =AA31 | AE34: ADMIN CHARGES | AF34: =AF31 | AJ34: ADMIN CHARGES | AK34: =#REF!
B35: GST | C35: =G35+K35+O35+S35+W35+AA35+AF35+AK35 | F35: GST | J35: GST | N35: GST | R35: GST | V35: GST | Z35: GST | AE35: GST | AJ35: GST
B36: RENTAL | F36: ICC-5 | J36: ICC-5 | N36: ICC-5 | V36: ICC-5 | Z36: ICC-5 | AE36: ICC-5
B37: LOAN INTEREST | C37: 22.12 | F37: PRODUCTS | J37: PRODUCTS | N37: PRODUCTS | V37: PRODUCTS | Z37: PRODUCTS | AE37: PRODUCTS
B38: IRAS TAX | C38: 12386.28 | D38: 46023 | F38: ORTHO (B+B) | J38: ORTHO (B+B) | N38: ORTHO (B+B) | V38: ORTHO (B+B) | Z38: ORTHO (B+B) | AE38: ORTHO (B+B)
B39: CK SECRETARIAL / ACCOUNTS SERVICES | D39: 12386.28 | F39: ABUTMENTS | J39: ABUTMENTS | N39: ABUTMENTS | V39: ABUTMENTS | Z39: ABUTMENTS | AE39: ABUTMENTS
B40: TOWN COUNCIL | F40: IMPLANT | J40: IMPLANT | N40: IMPLANT | V40: IMPLANT | Z40: IMPLANT | AE40: IMPLANT
B41: SERVICE & CONSERVANCY CHARGES | F41: SKY LAB | J41: SKY LAB | N41: SKY LAB | V41: SKY LAB | Z41: SKY LAB | AE41: SKY LAB
B42: SP | F42: DIGICADCAM | J42: DIGICADCAM | N42: DIGICADCAM | V42: DIGICADCAM | Z42: DIGICADCAM | AE42: DIGICADCAM
B43: SINGTEL | F43: OTHER LAB | J43: OTHER LAB | N43: OTHER LAB | V43: OTHER LAB | Z43: OTHER LAB | AE43: OTHER LAB
B44: PRODUCTS | C44: =G37+K37+O37+S59+W37+AA37+AF37+AK59 | F44: INVISALIGN | J44: INVISALIGN | N44: INVISALIGN | V44: INVISALIGN | Z44: INVISALIGN | AE44: INVISALIGN
B45: ADMIN STAFF & OFFICE RENTAL | F45: TRANSFER (+) | J45: TRANSFER (+) | N45: TRANSFER (+) | V45: TRANSFER (+) | Z45: TRANSFER (+) | AE45: TRANSFER (+)
B46: SUPPLIERS | F46: TRANSFER (-) | J46: TRANSFER (-) | N46: TRANSFER (-) | V46: TRANSFER (-) | Z46: TRANSFER (-) | AE46: TRANSFER (-)
B47: VOUCHER | C47: =B12 | F47: REFUND/REFERRAL | J47: REFUND/REFERRAL | N47: REFUND/REFERRAL | V47: REFUND | Z47: REFUND | AE47: REFUND
B48: PETTY CASH | F48: VOUCHER | J48: VOUCHER | N48: VOUCHER | V48: VOUCHER | Z48: VOUCHER | AE48: SEDATION
B49: STOCKS / CONSUMABLES FEES | F49: RETAINERS/BT/SPLINT | J49: RETAINERS/BT/SPLINT | N49: RETAINERS/BT/SPLINT | V49: RETAINERS/BT/SPLINT | Z49: RETAINERS/BT/SPLINT | AE49: RETAINERS/BT/SPLINT
B50: MARKETING FEE | F50: INSTALLMENT | J50: INSTALLMENT | N50: INSTALLMENT | V50: INSTALLMENT | Z50: INSTALLMENT | AE50: INSTALLMENT
B51: INVISALIGN | C51: =G44+K44+O44+S66+W44+AA44+AF44+AK66 | F51: DEDUCTIONS | J51: DEDUCTIONS | N51: DEDUCTIONS | V51: DEDUCTIONS | Z51: DEDUCTIONS | AE51: DEDUCTIONS
B52: IMPLANT | C52: =G40+O40+S62+W40+AA40+AF40+K40+AK62
B53: SKYLAB | C53: =G41+O41+W41+S63+K41+AA41+AF41+AK63 | F53: TOTAL | G53: =F31-G34-G35-G37-G36-G38-G39-G40-G41-G42-G43-G44+G45-G46-G47-G48-G49-G50-G51 | J53: TOTAL | K53: =J31-K34-K35-K36-K37-K38-K39-K40-K41-K42-K43-K44+K45-K46-K47-K48-K49-K50-K51 | N53: TOTAL | O53: =N31-O34-O35-O36-O37-O38-O39-O40-O41-O42-O43-O44+O45-O46-O47-O48-O49-O50-O51 | V53: TOTAL | W53: =V31-W34-W35-W36-W37-W38-W39-W40-W41-W42-W43-W44+W45-W46-W47-W48-W49-W50-W51 | Z53: TOTAL | AA53: =Z31-AA34-AA35-AA36-AA37-AA38-AA39-AA40-AA41-AA42-AA43-AA44+AA45-AA46-AA47-AA48-AA49-AA50-AA51 | AE53: TOTAL | AF53: =AE31-AF34-AF35-AF36-AF37-AF38-AF39-AF40-AF41-AF42-AF43-AF44+AF45-AF46-AF47-AF48-AF49-AF50-AF51
B54: DIGICADCAM | C54: =G42+O42+W42+AA42+AF42+S64+K42+AK64 | F54: DOCTORS FEE BEFORE DEDUCTION | G54: =G53/2+G55 | J54: DOCTORS FEE BEFORE DEDUCTION | K54: =K53/2+K55 | N54: DOCTORS PAY | O54: =(O53*50%)+O55 | V54: DOCTORS PAY | W54: =(W53*45%)+W55 | Z54: DOCTORS PAY | AA54: =(AA53*50%)+AA55 | AE54: DOCTORS PAY | AF54: =(AF53*45%)+AF55
B55: OTHER LAB | C55: =G43+O43+K43+S65+W43+AA43+AF43+AK65 | F55: ADJUSTMENTS (+) | J55: ADJUSTMENTS (+) | N55: ADJUSTMENTS (+) | V55: ADJUSTMENTS (+) | Z55: ADJUSTMENTS (+) | AE55: ADJUSTMENTS (+)
B56: ORTHO (B+B) | C56: =G38+K38+O38+S60+W38+AA38+AF38+AK60 | F56: ADJUSTMENTS (-) | G56: =G61+G65 | H56: ADDN MARKETING& MEDISAVE ADMIN | J56: ADJUSTMENTS (-) | K56: =K61+K65 | L56: ADDN MARKETING | N56: ADJUSTMENTS (-) | O56: =O61+O65 | P56: ADDN MARKETING & MEDISAVE ADMIN | V56: ADJUSTMENTS (-) | W56: =W61+W65 | X56: ADDN MKTRG & MEDISAVE ADMIN | Z56: ADJUSTMENTS (-) | AA56: =AA61+AA65 | AB56: MEDISAVE ADMIN | AE56: ADJUSTMENTS (-) | AF56: =AF61+AF65 | AG56: MARKETING FEE & MEDISAVE ADMIN
B57: ABUTMENT | C57: =O39+G39+K39+S61+AA39+W39+AF39+AK61 | F57: NET PAY | G57: =G54-G56 | J57: NET PAY | K57: =K54-K56 | N57: NET PAY | O57: =O54-O56 | V57: NET PAY | W57: =W54-W56 | Z57: NET PAY | AA57: =AA54-AA56 | AE57: NET PAY | AF57: =AF54-AF56
B58: REFUND / REFERRAL | C58: =G47+K47+O47+S69+W47+AA47+AF47+AK69 | R58: ICC-5 | AJ58: ICC-5
B59: DOCTORS PAY | C59: =G54+K54+O54+W54+AA54+AF54 | F59: MEDISAVE ADMIN FEE CALCULATION: | J59: MEDISAVE ADMIN FEE CALCULATION: | N59: MEDISAVE ADMIN FEE CALCULATION: | R59: PRODUCTS | V59: MEDISAVE ADMIN FEE CALCULATION: | Z59: MEDISAVE ADMIN FEE CALCULATION: | AE59: MEDISAVE ADMIN FEE CALCULATION: | AJ59: PRODUCTS
B60: NURSE PAY (BASIC PAY) | F60: Medisave Claim | G60: Admin Fee | H60: REMARKS | J60: Medisave Claim | K60: Admin Fee | L60: REMARKS | N60: Medisave Claim | O60: Admin Fee | P60: REMARKS | R60: ORTHO (B+B) | V60: Medisave Claim | W60: Admin Fee | X60: REMARKS | Z60: Medisave Claim | AA60: Admin Fee | AB60: REMARKS | AE60: Medisave Claim | AF60: Admin Fee | AG60: REMARKS | AJ60: ORTHO (B+B)
B61: NURSE PAY (INCENTIVE) | G61: =F61*20 | K61: =J61*20 | O61: =N61*20 | R61: ABUTMENTS | W61: =V61*20 | AA61: =Z61*20 | AF61: =AE61*20 | AJ61: ABUTMENTS
B62: NURSE TRANSFER FEE | R62: IMPLANT | AJ62: IMPLANT
B63: TANK CULTURE | C63: 163.5 | F63: ADDITIONAL MARKETING: | J63: ADDITIONAL MARKETING: | N63: ADDITIONAL MARKETING: | R63: SKY LAB | V63: ADDITIONAL MARKETING: | Z63: ADDITIONAL MARKETING: | AE63: ADDITIONAL MARKETING: | AJ63: SKY LAB
B64: SHARP BIN | F64: MONTH | G64: AMOUNT | H64: REMARKS | J64: MONTH | K64: AMOUNT | L64: REMARKS | N64: MONTH | O64: AMOUNT | P64: REMARKS | R64: DIGICADCAM | V64: MONTH | W64: AMOUNT | X64: REMARKS | Z64: MONTH | AA64: AMOUNT | AB64: REMARKS | AE64: MONTH | AF64: AMOUNT | AG64: REMARKS | AJ64: DIGICADCAM
B65: COURIER | C65: 129.44 | F65: =B3 | G65: 60 | J65: =F65 | K65: 120 | N65: =F65 | O65: 300 | R65: OTHER LAB | V65: =V3 | W65: 180 | Z65: =V65 | AA65: 75 | AE65: =AE3 | AF65: 180 | AJ65: OTHER LAB
B66: REPAIR & MAINTENANCE | R66: INVISALIGN | AJ66: INVISALIGN
B67: MOM LEVY | C67: 1500 | F67: OTHERS: (CPF,PERSONAL REFUND, COURSEFEE) | J67: OTHERS: (CPF,PERSONAL REFUND, COURSEFEE) | N67: OTHERS: (CPF,PERSONAL REFUND, COURSEFEE) | R67: TRANSFER (+) | V67: OTHERS: (CPF,PERSONAL REFUND, COURSEFEE) | Z67: OTHERS: (CPF,PERSONAL REFUND, COURSEFEE) | AE67: OTHERS: (CPF,PERSONAL REFUND, COURSEFEE) | AJ67: TRANSFER (+)
B68: PURCHASE PC | R68: TRANSFER (-) | AJ68: TRANSFER (-)
B69: PURCHASE INSTRUMENTS | F69: DETAILS | G69: AMOUNT | J69: DETAILS | K69: AMOUNT | N69: DETAILS | O69: AMOUNT | R69: REFUND | V69: DETAILS | W69: AMOUNT | Z69: DETAILS | AA69: AMOUNT | AE69: DETAILS | AF69: AMOUNT | AJ69: REFUND
R70: VOUCHER | AJ70: SEDATION
R71: RETAINERS/BT/SPLINT | AJ71: RETAINERS/BT/SPLINT
B72: TOTAL | C72: =B31-C34-C35-C58-C36-C37-C42-C43-C38-C46-C39-C45-C48-C49-C51-C50-C55-C54-C53-C59-C60-C61-C62-C47-C63-C40-C64-C41-C67-C66-C65-C90-C91-C92-C93-C94-C95-C68-C69-C70 | R72: INSTALLMENT | AJ72: INSTALLMENT
B73: FOR INCENTIVE % | C73: =B31-C34-C35-C58-C42-C43-C46-C45-C48-C44-C49-C50-C47-C63-C40-C64-C41-C65-C93-C95-C94-C66-C92-C90-C68-C69-C70 | R73: DEDUCTIONS | AJ73: DEDUCTIONS
B74: PERCENT | C74: =VLOOKUP(C73,'% RATES INCENTIVES'!C:D,2,TRUE)
A75: INCOME LESS GST | B75: =B31-C35 | C75: =C72/B75*100 | D75: % | R75: TOTAL | S75: =#REF!-S34-S35-S59-S58-S60-S61-S62-S63-S64-S65-S66+S67-S68-S69-S70-S71-S72-S73 | AJ75: TOTAL | AK75: =#REF!-AK34-AK35-AK58-AK59-AK60-AK61-AK62-AK63-AK64-AK65-AK66+AK67-AK68-AK69-AK70-AK71-AK72-AK73
R76: DOCTORS PAY | S76: =(S75*50%)+S77 | AJ76: DOCTORS PAY | AK76: =(AK75*50%)+AK77
B77: MEDISAVE ADMIN | C77: =G61+K61+O61+S83+W61+AA61+AF61+AK83 | D77: =C77/20 | F77: TOTAL PAYMENT | G77: =G57-G70-G74-G75-G71-G72-G73 | J77: TOTAL PAYMENT | K77: =K57-K70-K74-K75-K71-K72-K73 | N77: TOTAL PAYMENT | O77: =O57-O70-O74-O75-O71-O72-O73 | R77: ADJUSTMENTS (+) | V77: TOTAL PAYMENT | W77: =W57-W70-W74-W75-W71-W72-W73 | Z77: TOTAL PAYMENT | AA77: =AA57-AA70-AA74-AA75-AA71-AA72-AA73 | AE77: TOTAL PAYMENT | AF77: =AF57-AF70-AF74-AF75-AF71-AF72-AF73 | AJ77: ADJUSTMENTS (+)
B78: ADDITIONAL MARKETING | C78: =G65+K65+O65+S87+W65+AA65+AF65 | R78: ADJUSTMENTS (-) | S78: =S83+S87 | AJ78: ADJUSTMENTS (-) | AK78: =AK83+AK87 | AL78: MARKETING FEE & MEDISAVE ADMIN
B79: DOCTORS PERSONAL DEDUCTION | C79: =G70+G74+G75+K70+K74+K75+O70+O74+O75+S92+S96+S97+W70+W74+W75+AA70+AA74+AA75+AF70+AF74+AF75+G71+G72+G73+K71+K72+K73+O71+O72+O73+S93+S94+S95+W71+W72+W73+AA71+AA72+AA73+AF71+AF72+AF73 | R79: NET PAY | S79: =S76-S78 | AJ79: NET PAY | AK79: =AK76-AK78
B80: TOTAL | C80: =SUM(C77:C79)
B81: TOTAL ICC-5 | C81: =G36+K36+O36+S58+AA36+W36+AF36 | R81: MEDISAVE ADMIN FEE CALCULATION: | AJ81: MEDISAVE ADMIN FEE CALCULATION:
R82: Medisave Claim | S82: Admin Fee | T82: REMARKS | AJ82: Medisave Claim | AK82: Admin Fee | AL82: REMARKS
B83: NURSES FEE-REVENUE | C83: =(C60+C61+C62)/B31 | S83: =R83*20 | AK83: =AJ83*20
B84: CONSUMABLE EXCL OFFICE RENT - REVENUE | C84: =(C49+C46+C48)/B31
B85: OFFICE RENT & ADMIN STAFF - REVENUE | C85: =(C45/B31) | R85: ADDITIONAL MARKETING: | AJ85: ADDITIONAL MARKETING:
B86: MARKETING - REVENUE | C86: =C50/B31 | R86: MONTH | S86: AMOUNT | T86: REMARKS | AJ86: MONTH | AK86: AMOUNT | AL86: REMARKS
R87: =R3 | AJ87: =AJ3
R89: OTHERS: (CPF,PERSONAL REFUND, COURSEFEE) | AJ89: OTHERS: (CPF,PERSONAL REFUND, COURSEFEE)
R91: DETAILS | S91: AMOUNT | AJ91: DETAILS | AK91: AMOUNT
AH92: feb 2191
R99: TOTAL CHEQUE AMOUNT | S99: =S79-S92-S96-S97-S93-S94-S95 | AJ99: TOTAL CHEQUE AMOUNT | AK99: =AK79-AK92-AK96-AK97-AK93-AK94-AK95

Sheet WDLS SETTLEMENT CAL NEW
A3: MONTH/YEAR: | B3: 46023 | E3: MONTH/YEAR: | F3: =B3 | I3: MONTH/YEAR: | J3: =B3 | M3: MONTH/YEAR: | N3: =B3 | Q3: MONTH/YEAR: | R3: =B3 | U3: MONTH/YEAR: | V3: =B3 | Y3: MONTH/YEAR: | Z3: =B3 | AD3: MONTH/YEAR: | AE3: =B3 | AI3: MONTH/YEAR: | AJ3: =AE3 | AN3: MONTH/YEAR: | AO3: =AE3 | AS3: MONTH/YEAR: | AT3: =AO3 | AX3: MONTH/YEAR: | AY3: =V3
A4: BRANCH: | B4: CASA DENTAL WOODLANDS PTE LTD | E4: BRANCH: | F4: =B4 | I4: BRANCH: | J4: =B4 | M4: BRANCH: | N4: =B4 | Q4: BRANCH: | R4: CASA DENTAL AMK PTE LTD | U4: BRANCH: | V4: =B4 | Y4: BRANCH: | Z4: =B4 | AD4: BRANCH: | AE4: =B4 | AI4: BRANCH: | AJ4: CASA DENTAL AMK PTE LTD | AN4: BRANCH: | AO4: =AE4 | AS4: BRANCH: | AT4: =AO4 | AX4: BRANCH: | AY4: =V4
A5: ALL PROVIDERS SETTLEMENT | E5: DR CHAN KC | I5: DR CHAN CHIEN CHI | M5: DR CELINE TEO | Q5: DR KALIE | U5: DR ROLAND FOO | Y5: DR JENNIFER HOANG | AD5: DR ESTHER HOH | AI5: DR ANDREW YIN | AN5: DR YVETTE CHOW | AS5: DR PETER KEITH | AX5: DR ROLAND FOO
C6: ADMIN CHARGES | G6: ADMIN CHARGES | J6: TOTALS | K6: ADMIN CHARGES | O6: ADMIN CHARGES | S6: ADMIN CHARGES | W6: ADMIN CHARGES | AA6: ADMIN CHARGES | AF6: ADMIN CHARGES | AK6: ADMIN CHARGES | AP6: ADMIN CHARGES | AU6: ADMIN CHARGES | AZ6: ADMIN CHARGES
A7: AIA | C7: =B7*0.05*1.09 | E7: AIA | G7: =F7*0.05*1.09 | I7: AIA | K7: =J7*0.05*1.09 | M7: AIA | O7: =N7*0.05*1.09 | Q7: AIA | S7: =R7*0.05*1.09 | U7: AIA | W7: =V7*0.05*1.09 | Y7: AIA | AA7: =Z7*0.05*1.09 | AD7: AIA | AF7: =AE7*0.05*1.09 | AI7: AIA | AK7: =AJ7*0.05*1.09 | AN7: AIA | AP7: =AO7*0.05*1.09 | AS7: AIA | AU7: =AT7*0.05*1.09 | AX7: AIA | AZ7: =AY7*0.05*1.09
A8: ALLIANCE | C8: =B8*0.05*1.09 | E8: ALLIANCE | G8: =F8*0.05*1.09 | I8: ALLIANCE | K8: =J8*0.05*1.09 | M8: ALLIANCE | O8: =N8*0.05*1.09 | U8: ALLIANCE | W8: =V8*0.05*1.09 | Y8: ALLIANCE | AA8: =Z8*0.05*1.09 | AD8: ALLIANCE | AF8: =AE8*0.05*1.09 | AN8: ALLIANCE | AP8: =AO8*0.05*1.09 | AS8: ALLIANCE | AU8: =AT8*0.05*1.09 | AX8: ALLIANCE | AZ8: =AY8*0.05*1.09
A9: AMEX | C9: =B9*0.0195 | E9: AMEX | G9: =F9*0.0195 | I9: AMEX | K9: =J9*0.0195 | M9: AMEX | O9: =N9*0.0195 | Q9: AMEX | S9: =R9*0.0195 | U9: AMEX | W9: =V9*0.0195 | Y9: AMEX | AA9: =Z9*0.0195 | AD9: AMEX | AF9: =AE9*0.0195 | AI9: AMEX | AK9: =AJ9*0.0195 | AN9: AMEX | AP9: =AO9*0.0195 | AS9: AMEX | AU9: =AT9*0.0195 | AX9: AMEX | AZ9: =AY9*0.0195
A10: BABYBONUS | C10: =B10*0.008 | E10: BABYBONUS | G10: =F10*0.008 | I10: BABYBONUS | K10: =J10*0.008 | M10: BABYBONUS | O10: =N10*0.008 | U10: BABYBONUS | W10: =V10*0.008 | Y10: BABYBONUS | AA10: =Z10*0.008 | AD10: BABYBONUS | AF10: =AE10*0.008 | AN10: BABYBONUS | AP10: =AO10*0.008 | AS10: BABYBONUS | AU10: =AT10*0.008 | AX10: BABYBONUS | AZ10: =AY10*0.008
A11: CASH | E11: CASH | I11: CASH | M11: CASH | Q11: ALLIANCE | S11: =R11*0.05*1.09 | U11: CASH | Y11: CASH | AD11: CASH | AI11: ALLIANCE | AK11: =AJ11*0.05*1.09 | AN11: CASH | AS11: CASH | AX11: CASH
A12: CASA VOUCHER | E12: CASA VOUCHER | I12: CASA VOUCHER | M12: CASA VOUCHER | Q12: CASH | U12: CASA VOUCHER | Y12: CASA VOUCHER | AD12: CASA VOUCHER | AI12: CASH | AN12: CASA VOUCHER | AS12: CASA VOUCHER | AX12: CASA VOUCHER
A13: CDC VOUCHER | E13: CDC VOUCHER | I13: CDC VOUCHER | M13: CDC VOUCHER | Q13: CASA VOUCHER | U13: CDC VOUCHER | Y13: CDC VOUCHER | AD13: CDC VOUCHER | AI13: CASA VOUCHER | AN13: CDC VOUCHER | AS13: CDC VOUCHER | AX13: CDC VOUCHER
A14: CHAS | E14: CHAS | I14: CHAS | M14: CHAS | U14: CHAS | Y14: CHAS | AD14: CHAS | AN14: CHAS | AS14: CHAS | AX14: CHAS
A15: CYNERGY | E15: CYNERGY | I15: CYNERGY | M15: CYNERGY | U15: CYNERGY | Y15: CYNERGY | AD15: CYNERGY | AN15: CYNERGY | AS15: CYNERGY | AX15: CYNERGY
A16: DA ADEPT HEALTH | C16: =B16*8% | E16: DA ADEPT HEALTH | G16: =F16*8% | I16: DA ADEPT HEALTH | K16: =J16*8% | M16: DA ADEPT HEALTH | O16: =N16*8% | U16: DA ADEPT HEALTH | W16: =V16*8% | Y16: DA ADEPT HEALTH | AA16: =Z16*8% | AD16: DA ADEPT HEALTH | AF16: =AE16*8% | AN16: DA ADEPT HEALTH | AP16: =AO16*8% | AS16: DA ADEPT HEALTH | AU16: =AT16*8% | AX16: DA ADEPT HEALTH | AZ16: =AY16*8%
A17: DEPOSIT | C17: =G17+K17+O17+O17+S17+W17+AA17+AF17+AP17+AU17+AZ17 | E17: DEPOSIT | I17: DEPOSIT | M17: DEPOSIT | Q17: DEPOSIT | S17: 0 | U17: DEPOSIT | Y17: DEPOSIT | AD17: DEPOSIT | AI17: DEPOSIT | AN17: DEPOSIT | AS17: DEPOSIT | AX17: DEPOSIT
A18: IHP | C18: =B18*0.051*1.09 | E18: IHP | G18: =F18*0.051*1.09 | I18: IHP | K18: =J18*0.051*1.09 | M18: IHP | O18: =N18*0.051*1.09 | U18: IHP | W18: =V18*0.051*1.09 | Y18: IHP | AA18: =Z18*0.051*1.09 | AD18: IHP | AF18: =AE18*0.051*1.09 | AN18: IHP | AP18: =AO18*0.051*1.09 | AS18: IHP | AU18: =AT18*0.051*1.09 | AX18: IHP | AZ18: =AY18*0.051*1.09
A19: JCB | C19: =B19*0.15*1.09 | E19: JCB | G19: =F19*0.15*1.09 | I19: JCB | K19: =J19*0.15*1.09 | M19: JCB | O19: =N19*0.15*1.09 | U19: JCB | W19: =V19*0.15*1.09 | Y19: JCB | AA19: =Z19*0.15*1.09 | AD19: JCB | AF19: =AE19*0.15*1.09 | AN19: JCB | AP19: =AO19*0.15*1.09 | AS19: JCB | AU19: =AT19*0.15*1.09 | AX19: JCB | AZ19: =AY19*0.15*1.09
A20: MASTER | C20: =B20*0.0225 | E20: MASTER | G20: =F20*0.021 | I20: MASTER | K20: =J20*0.0225 | M20: MASTER | O20: =N20*0.0225 | U20: MASTER | W20: =V20*0.0225 | Y20: MASTER | AA20: =Z20*0.0225 | AD20: MASTER | AF20: =AE20*0.0225 | AN20: MASTER | AP20: =AO20*0.0225 | AS20: MASTER | AU20: =AT20*0.0225 | AX20: MASTER | AZ20: =AY20*0.021
A21: MEDISAVE | E21: MEDISAVE | I21: MEDISAVE | M21: MEDISAVE | U21: MEDISAVE | Y21: MEDISAVE | AD21: MEDISAVE | AN21: MEDISAVE | AS21: MEDISAVE | AX21: MEDISAVE
A22: mednefits | C22: =B22*20% | E22: mednefits | G22: =F22*20% | I22: mednefits | K22: =J22*20% | M22: mednefits | O22: =N22*20% | U22: mednefits | W22: =V22*20% | Y22: mednefits | AA22: =Z22*20% | AD22: mednefits | AF22: =AE22*20% | AN22: mednefits | AP22: =AO22*20% | AS22: mednefits | AU22: =AT22*20% | AX22: mednefits | AZ22: =AY22*20%
A23: MHC | C23: =B23*0.15*1.09 | E23: MHC | G23: =F23*0.15*1.09 | I23: MHC | K23: =J23*0.15*1.09 | M23: MHC | O23: =N23*0.15*1.09 | U23: MHC | W23: =V23*0.15*1.09 | Y23: MHC | AA23: =Z23*0.15*1.09 | AD23: MHC | AF23: =AE23*0.15*1.09 | AN23: MHC | AP23: =AO23*0.15*1.09 | AS23: MHC | AU23: =AT23*0.15*1.09 | AX23: MHC | AZ23: =AY23*0.15*1.09
A24: NETS | C24: =B24*0.008 | E24: NETS | G24: =F24*0.008 | I24: NETS | K24: =J24*0.008 | M24: NETS | O24: =N24*0.008 | U24: NETS | W24: =V24*0.008 | Y24: NETS | AA24: =Z24*0.008 | AD24: NETS | AF24: =AE24*0.008 | AN24: NETS | AP24: =AO24*0.008 | AS24: NETS | AU24: =AT24*0.008 | AX24: NETS | AZ24: =AY24*0.008
A25: PARKWAY | C25: =B25*10% | E25: PARKWAY | G25: =F25*10% | I25: PARKWAY | K25: =J25*10% | M25: PARKWAY | O25: =N25*10% | U25: PARKWAY | W25: =V25*10% | Y25: PARKWAY | AA25: =Z25*10% | AD25: PARKWAY | AF25: =AE25*10% | AN25: PARKWAY | AP25: =AO25*10% | AS25: PARKWAY | AU25: =AT25*10% | AX25: PARKWAY | AZ25: =AY25*10%
A26: PAYNOW | E26: PAYNOW | I26: PAYNOW | M26: PAYNOW | U26: PAYNOW | Y26: PAYNOW | AD26: PAYNOW | AN26: PAYNOW | AS26: PAYNOW | AX26: PAYNOW
A27: RHI | E27: RHI | I27: RHI | M27: RHI | U27: RHI | Y27: RHI | AD27: RHI | AN27: RHI | AS27: RHI | AX27: RHI
A28: SAH | C28: =B28*8% | E28: SAH | G28: =F28*8% | I28: SAH | K28: =J28*8% | M28: SAH | O28: =N28*8% | U28: SAH | W28: =V28*8% | Y28: SAH | AA28: =Z28*8% | AD28: SAH | AF28: =AE28*8% | AN28: SAH | AP28: =AO28*8% | AS28: SAH | AU28: =AT28*8% | AX28: SAH | AZ28: =AY28*8%
A29: UNION PAY | C29: =B29*2.5% | E29: UNION PAY | G29: =F29*2.5% | I29: UNION PAY | K29: =J29*2.5% | M29: UNION PAY | O29: =N29*2.5% | U29: UNION PAY | W29: =V29*2.5% | Y29: UNION PAY | AA29: =Z29*2.5% | AD29: UNION PAY | AF29: =AE29*2.5% | AN29: UNION PAY | AP29: =AO29*2.5% | AS29: UNION PAY | AU29: =AT29*2.5% | AX29: UNION PAY | AZ29: =AY29*2.5%
A30: VISA | C30: =B30*0.0225 | E30: VISA | G30: =F30*0.021 | I30: VISA | K30: =J30*0.0225 | M30: VISA | O30: =N30*0.0225 | U30: VISA | W30: =V30*0.0225 | Y30: VISA | AA30: =Z30*0.0225 | AD30: VISA | AF30: =AE30*0.0225 | AN30: VISA | AP30: =AO30*0.0225 | AS30: VISA | AU30: =AT30*0.0225 | AX30: VISA | AZ30: =AY30*0.021
A31: TOTAL INCOME | B31: =SUM(B7:B30) | C31: =SUM(C7:C30) | E31: DR TOTAL INCOME | F31: =SUM(F7:F30) | G31: =SUM(G7:G30) | I31: DR TOTAL INCOME | J31: =SUM(J7:J30) | K31: =SUM(K7:K30) | M31: DR TOTAL INCOME | N31: =SUM(N7:N30) | O31: =SUM(O7:O30) | U31: DR TOTAL INCOME | V31: =SUM(V7:V30) | W31: =SUM(W7:W30) | Y31: DR TOTAL INCOME | Z31: =SUM(Z7:Z30) | AA31: =SUM(AA7:AA30) | AD31: DR TOTAL INCOME | AE31: =SUM(AE7:AE30) | AF31: =SUM(AF7:AF30) | AN31: DR TOTAL INCOME | AO31: =SUM(AO7:AO30) | AP31: =SUM(AP7:AP30) | AS31: DR TOTAL INCOME | AT31: =SUM(AT7:AT30) | AU31: =SUM(AU7:AU30) | AX31: DR TOTAL INCOME | AY31: =SUM(AY7:AY30) | AZ31: =SUM(AZ7:AZ30)
B33: EXPENSES | F33: DEDUCTIONS | H33: REMARKS | J33: DEDUCTIONS | L33: REMARKS | N33: DEDUCTIONS | P33: REMARKS | R33: DEDUCTIONS | T33: REMARKS | V33: DEDUCTIONS | X33: REMARKS | Z33: DEDUCTIONS | AB33: REMARKS | AE33: DEDUCTIONS | AG33: REMARKS | AJ33: DEDUCTIONS | AL33: REMARKS | AO33: DEDUCTIONS | AQ33: REMARKS | AT33: DEDUCTIONS | AV33: REMARKS | AY33: DEDUCTIONS | BA33: REMARKS
B34: ADMIN FEE | C34: =SUM(C7:C30) | F34: ADMIN CHARGES | G34: =G31 | J34: ADMIN CHARGES | K34: =K31 | N34: ADMIN CHARGES | O34: =O31 | R34: ADMIN CHARGES | S34: =#REF! | V34: ADMIN CHARGES | W34: =W31 | Z34: ADMIN CHARGES | AA34: =AA31 | AE34: ADMIN CHARGES | AF34: =AF31 | AJ34: ADMIN CHARGES | AK34: =#REF! | AO34: ADMIN CHARGES | AP34: =AP31 | AT34: ADMIN CHARGES | AU34: =AU31 | AY34: ADMIN CHARGES | AZ34: =AZ31
B35: GST | C35: =K35+O35+AA35+AF35+AM35+AP35+T35+W35+AU35+AZ35 | F35: GST | J35: GST | N35: GST | R35: GST | V35: GST | Z35: GST | AE35: GST | AJ35: GST | AO35: GST | AT35: GST | AY35: GST
B36: RENTAL | F36: ICC-5 | J36: ICC-5 | N36: ICC-5 | V36: ICC-5 | Z36: ICC-5 | AE36: ICC-5 | AO36: ICC-5 | AT36: ICC-5 | AY36: ICC-5
B37: LOAN INTEREST | F37: PRODUCTS | J37: PRODUCTS | N37: PRODUCTS | V37: PRODUCTS | Z37: PRODUCTS | AE37: PRODUCTS | AO37: PRODUCTS | AT37: PRODUCTS | AY37: PRODUCTS
B38: IRAS TAX | F38: ORTHO (B+B) | J38: ORTHO (B+B) | N38: ORTHO (B+B) | V38: ORTHO (B+B) | Z38: ORTHO (B+B) | AE38: ORTHO (B+B) | AO38: ORTHO (B+B) | AT38: ORTHO (B+B) | AY38: ORTHO (B+B)
B39: CK SECRETARIAL / ACCOUNTS SERVICES | F39: ABUTMENTS | J39: ABUTMENTS | N39: ABUTMENTS | V39: ABUTMENTS | Z39: ABUTMENTS | AE39: ABUTMENTS | AO39: ABUTMENTS | AT39: ABUTMENTS | AY39: ABUTMENTS
B40: TOWN COUNCIL | F40: IMPLANT | J40: IMPLANT | N40: IMPLANT | V40: IMPLANT | Z40: IMPLANT | AE40: IMPLANT | AO40: IMPLANT | AT40: IMPLANT | AY40: IMPLANT
B41: SERVICE & CONSERVANCY CHARGES | F41: SKY LAB | J41: SKY LAB | N41: SKY LAB | V41: SKY LAB | Z41: SKY LAB | AE41: SKY LAB | AO41: SKY LAB | AT41: SKY LAB | AY41: SKY LAB
B42: SP | F42: DIGICADCAM | J42: DIGICADCAM | N42: DIGICADCAM | V42: DIGICADCAM | Z42: DIGICADCAM | AE42: DIGICADCAM | AO42: DIGICADCAM | AT42: DIGICADCAM | AY42: DIGICADCAM
B43: SINGTEL | F43: OTHER LAB | J43: OTHER LAB | N43: OTHER LAB | V43: OTHER LAB | Z43: OTHER LAB | AE43: OTHER LAB | AO43: OTHER LAB | AT43: OTHER LAB | AY43: OTHER LAB
B44: PRODUCTS | C44: =G37+K37+O37+S59+W37+AA37+AF37+AK59+AP37+AU37+AZ37 | F44: INVISALIGN | J44: INVISALIGN | N44: INVISALIGN | V44: INVISALIGN | Z44: INVISALIGN | AE44: INVISALIGN | AO44: INVISALIGN | AT44: INVISALIGN | AY44: INVISALIGN
B45: ADMIN STAFF & OFFICE RENTAL | F45: TRANSFER (+) | J45: TRANSFER (+) | N45: TRANSFER (+) | V45: TRANSFER (+) | Z45: TRANSFER (+) | AE45: TRANSFER (+) | AO45: TRANSFER (+) | AT45: TRANSFER (+) | AY45: TRANSFER (+)
B46: SUPPLIERS | F46: TRANSFER (-) | J46: TRANSFER (-) | N46: TRANSFER (-) | V46: TRANSFER (-) | Z46: TRANSFER (-) | AE46: TRANSFER (-) | AO46: TRANSFER (-) | AT46: TRANSFER (-) | AY46: TRANSFER (-)
B47: VOUCHER | C47: =B12 | F47: REFUND/REFERRAL | J47: REFUND/REFERRAL | N47: REFUND/REFERRAL | V47: REFUND | Z47: REFUND | AE47: REFUND | AO47: REFUND | AT47: REFUND | AY47: REFUND
B48: PETTY CASH | F48: VOUCHER | G48: =F12 | J48: VOUCHER | N48: VOUCHER | V48: VOUCHER | Z48: VOUCHER | AE48: SEDATION | AO48: SEDATION | AT48: SEDATION | AY48: SEDATION
B49: STOCKS / CONSUMABLES FEES | F49: RETAINERS/BT/SPLINT | J49: RETAINERS/BT/SPLINT | N49: RETAINERS/BT/SPLINT | V49: RETAINERS/BT/SPLINT | Z49: RETAINERS/BT/SPLINT | AE49: RETAINERS/BT/SPLINT | AO49: RETAINERS/BT/SPLINT | AT49: RETAINERS/BT/SPLINT | AY49: RETAINERS/BT/SPLINT
B50: MARKETING FEE | F50: INSTALLMENT | J50: INSTALLMENT | N50: INSTALLMENT | V50: INSTALLMENT | Z50: INSTALLMENT | AE50: INSTALLMENT | AO50: INSTALLMENT | AT50: INSTALLMENT | AY50: INSTALLMENT
B51: INVISALIGN | C51: =G44+K44+O44+S66+W44+AA44+AF44+AK66+AP44+AU44 | F51: DEDUCTIONS | J51: DEDUCTIONS | N51: DEDUCTIONS | V51: DEDUCTIONS | Z51: DEDUCTIONS | AE51: DEDUCTIONS | AO51: DEDUCTIONS | AT51: DEDUCTIONS | AY51: DEDUCTIONS
B52: IMPLANT | C52: =G40+O40+S62+W40+AA40+AF40+K40+AK62
B53: SKYLAB | C53: =G41+O41+W41+S63+K41+AA41+AF41+AK63 | F53: TOTAL | G53: =F31-G34-G35-G37-G36-G38-G39-G40-G41-G42-G43-G44+G45-G46-G47-G48-G49-G50-G51 | J53: TOTAL | K53: =J31-K34-K35-K36-K37-K38-K39-K40-K41-K42-K43-K44+K45-K46-K47-K48-K49-K50-K51 | N53: TOTAL | O53: =N31-O34-O35-O36-O37-O38-O39-O40-O41-O42-O43-O44+O45-O46-O47-O48-O49-O50-O51 | V53: TOTAL | W53: =V31-W34-W35-W36-W37-W38-W39-W40-W41-W42-W43-W44+W45-W46-W47-W48-W49-W50-W51 | Z53: TOTAL | AA53: =Z31-AA34-AA35-AA36-AA37-AA38-AA39-AA40-AA41-AA42-AA43-AA44+AA45-AA46-AA47-AA48-AA49-AA50-AA51 | AE53: TOTAL | AF53: =AE31-AF34-AF35-AF36-AF37-AF38-AF39-AF40-AF41-AF42-AF43-AF44+AF45-AF46-AF47-AF48-AF49-AF50-AF51 | AO53: TOTAL | AP53: =AO31-AP34-AP35-AP36-AP37-AP38-AP39-AP40-AP41-AP42-AP43-AP44+AP45-AP46-AP47-AP48-AP49-AP50-AP51 | AT53: TOTAL | AU53: =AT31-AU34-AU35-AU36-AU37-AU38-AU39-AU40-AU41-AU42-AU43-AU44+AU45-AU46-AU47-AU48-AU49-AU50-AU51 | AY53: TOTAL | AZ53: =AY31-AZ34-AZ35-AZ36-AZ37-AZ38-AZ39-AZ40-AZ41-AZ42-AZ43-AZ44+AZ45-AZ46-AZ47-AZ48-AZ49-AZ50-AZ51
B54: DIGICADCAM | C54: =G42+O42+W42+AA42+AF42+S64+K42+AK64 | F54: DOCTORS FEE BEFORE DEDUCTION | G54: =G53/2+G55 | J54: DOCTORS FEE BEFORE DEDUCTION | K54: =K53/2+K55 | N54: DOCTORS PAY | O54: =(O53*50%)+O55 | V54: DOCTORS PAY | W54: =(W53*50%)+W55 | Z54: DOCTORS PAY | AA54: =(AA53*50%)+AA55 | AE54: DOCTORS PAY | AF54: =(AF53*50%)+AF55 | AO54: DOCTORS PAY | AP54: =(AP53*45%)+AP55 | AT54: DOCTORS PAY | AU54: =(AU53*50%)+AU55 | AY54: DOCTORS PAY | AZ54: =(AZ53*50%)+AZ55
B55: OTHER LAB | C55: =G43+O43+K43+S65+W43+AA43+AF43+AK65 | F55: ADJUSTMENTS (+) | J55: ADJUSTMENTS (+) | N55: ADJUSTMENTS (+) | V55: ADJUSTMENTS (+) | Z55: ADJUSTMENTS (+) | AE55: ADJUSTMENTS (+) | AO55: ADJUSTMENTS (+) | AT55: ADJUSTMENTS (+) | AY55: ADJUSTMENTS (+)
B56: ORTHO (B+B) | C56: =G38+K38+O38+S60+W38+AA38+AF38+AK60 | F56: ADJUSTMENTS (-) | G56: =G61+G65 | H56: ADDN MARKETING& MEDISAVE ADMIN | J56: ADJUSTMENTS (-) | K56: =K61+K65 | L56: ADDN MARKETING | N56: ADJUSTMENTS (-) | O56: =O61+O65 | P56: ADDN MARKETING & MEDISAVE ADMIN | V56: ADJUSTMENTS (-) | W56: =W61+W65 | X56: ADDN MKTRG & MEDISAVE ADMIN | Z56: ADJUSTMENTS (-) | AA56: =AA61+AA65 | AB56: MARKETING FEE & MEDISAVE ADMIN | AE56: ADJUSTMENTS (-) | AF56: =AF61+AF65 | AG56: MARKETING FEE & MEDISAVE ADMIN | AO56: ADJUSTMENTS (-) | AP56: =AP61+AP65 | AQ56: MARKETING FEE & MEDISAVE ADMIN | AT56: ADJUSTMENTS (-) | AU56: =AU61+AU65 | AV56: MARKETING FEE & MEDISAVE ADMIN | AY56: ADJUSTMENTS (-) | AZ56: =AZ61+AZ65 | BA56: MARKETING FEE & MEDISAVE ADMIN
B57: ABUTMENT | C57: =O39+G39+K39+S61+AA39+W39+AF39+AK61 | F57: NET PAY | G57: =G54-G56 | J57: NET PAY | K57: =K54-K56 | N57: NET PAY | O57: =O54-O56 | V57: NET PAY | W57: =W54-W56 | Z57: NET PAY | AA57: =AA54-AA56 | AE57: NET PAY | AF57: =AF54-AF56 | AO57: NET PAY | AP57: =AP54-AP56 | AT57: NET PAY | AU57: =AU54-AU56 | AY57: NET PAY | AZ57: =AZ54-AZ56
B58: REFUND / REFERRAL | C58: =G47+K47+O47+S69+W47+AA47+AF47+AK69 | R58: ICC-5 | AJ58: ICC-5
B59: DOCTORS PAY | C59: =G54+K54+O54+W54+AA54+AF54+AP54+AU54+AZ54 | F59: MEDISAVE ADMIN FEE CALCULATION: | J59: MEDISAVE ADMIN FEE CALCULATION: | N59: MEDISAVE ADMIN FEE CALCULATION: | R59: PRODUCTS | V59: MEDISAVE ADMIN FEE CALCULATION: | Z59: MEDISAVE ADMIN FEE CALCULATION: | AE59: MEDISAVE ADMIN FEE CALCULATION: | AJ59: PRODUCTS | AO59: MEDISAVE ADMIN FEE CALCULATION: | AT59: MEDISAVE ADMIN FEE CALCULATION: | AY59: MEDISAVE ADMIN FEE CALCULATION:
B60: NURSE PAY (BASIC PAY) | F60: Medisave Claim | G60: Admin Fee | H60: REMARKS | J60: Medisave Claim | K60: Admin Fee | L60: REMARKS | N60: Medisave Claim | O60: Admin Fee | P60: REMARKS | R60: ORTHO (B+B) | V60: Medisave Claim | W60: Admin Fee | X60: REMARKS | Z60: Medisave Claim | AA60: Admin Fee | AB60: REMARKS | AE60: Medisave Claim | AF60: Admin Fee | AG60: REMARKS | AJ60: ORTHO (B+B) | AO60: Medisave Claim | AP60: Admin Fee | AQ60: REMARKS | AT60: Medisave Claim | AU60: Admin Fee | AV60: REMARKS | AY60: Medisave Claim | AZ60: Admin Fee | BA60: REMARKS
B61: NURSE PAY (INCENTIVE) | G61: =F61*20 | K61: =J61*20 | O61: =N61*20 | R61: ABUTMENTS | W61: =V61*20 | AA61: =Z61*20 | AF61: =AE61*20 | AJ61: ABUTMENTS | AP61: =AO61*20 | AU61: =AT61*20 | AZ61: =AY61*20
B62: NURSE TRANSFER FEE | R62: IMPLANT | AJ62: IMPLANT
B63: TANK CULTURE | C63: 163.5 | F63: ADDITIONAL MARKETING: | J63: ADDITIONAL MARKETING: | N63: ADDITIONAL MARKETING: | R63: SKY LAB | V63: ADDITIONAL MARKETING: | Z63: ADDITIONAL MARKETING: | AE63: ADDITIONAL MARKETING: | AJ63: SKY LAB | AO63: ADDITIONAL MARKETING: | AT63: ADDITIONAL MARKETING: | AY63: ADDITIONAL MARKETING:
B64: SHARP BIN | F64: MONTH | G64: AMOUNT | H64: REMARKS | J64: MONTH | K64: AMOUNT | L64: REMARKS | N64: MONTH | O64: AMOUNT | P64: REMARKS | R64: DIGICADCAM | V64: MONTH | W64: AMOUNT | X64: REMARKS | Z64: MONTH | AA64: AMOUNT | AB64: REMARKS | AE64: MONTH | AF64: AMOUNT | AG64: REMARKS | AJ64: DIGICADCAM | AO64: MONTH | AP64: AMOUNT | AQ64: REMARKS | AT64: MONTH | AU64: AMOUNT | AV64: REMARKS | AY64: MONTH | AZ64: AMOUNT | BA64: REMARKS
B65: COURIER | C65: 129.44 | F65: =B3 | J65: =F65 | K65: 180 | N65: =F65 | O65: 150 | R65: OTHER LAB | V65: =V3 | W65: 120 | Z65: =V65 | AE65: =AE3 | AF65: 60 | AJ65: OTHER LAB | AO65: =AO3 | AT65: =AT3 | AY65: =AY3
B66: REPAIR & MAINTENANCE | R66: INVISALIGN | AJ66: INVISALIGN
B67: MOM LEVY | C67: =400+600 | F67: OTHERS: (CPF,PERSONAL REFUND, COURSEFEE) | J67: OTHERS: (CPF,PERSONAL REFUND, COURSEFEE) | N67: OTHERS: (CPF,PERSONAL REFUND, COURSEFEE) | R67: TRANSFER (+) | V67: OTHERS: (CPF,PERSONAL REFUND, COURSEFEE) | Z67: OTHERS: (CPF,PERSONAL REFUND, COURSEFEE) | AE67: OTHERS: (CPF,PERSONAL REFUND, COURSEFEE) | AJ67: TRANSFER (+) | AO67: OTHERS: (CPF,PERSONAL REFUND, COURSEFEE) | AT67: OTHERS: (CPF,PERSONAL REFUND, COURSEFEE) | AY67: OTHERS: (CPF,PERSONAL REFUND, COURSEFEE)
R68: TRANSFER (-) | AJ68: TRANSFER (-)
F69: DETAILS | G69: AMOUNT | J69: DETAILS | K69: AMOUNT | N69: DETAILS | O69: AMOUNT | R69: REFUND | V69: DETAILS | W69: AMOUNT | Z69: DETAILS | AA69: AMOUNT | AE69: DETAILS | AF69: AMOUNT | AJ69: REFUND | AO69: DETAILS | AP69: AMOUNT | AT69: DETAILS | AU69: AMOUNT | AY69: DETAILS | AZ69: AMOUNT
F70: CPF CONT SALARY | R70: VOUCHER | AJ70: SEDATION
AJ71: RETAINERS/BT/SPLINT
B72: TOTAL | C72: =B31-C34-C35-C58-C36-C37-C42-C43-C38-C46-C39-C45-C48-C49-C51-C50-C55-C54-C53-C59-C60-C61-C62-C47-C63-C40-C64-C41-C67-C66-C65-C90-C91-C92-C93-C94-C95-C68-C69-C70 | AJ72: INSTALLMENT
B73: FOR INCENTIVE % | C73: =B31-C34-C35-C58-C42-C43-C46-C45-C48-C44-C49-C50-C47-C63-C40-C64-C41-C65-C93-C95-C94-C66-C92-C90 | AJ73: DEDUCTIONS
B74: PERCENT | C74: =VLOOKUP(C73,'% RATES INCENTIVES'!C:D,2,TRUE)
A75: INCOME LESS GST | B75: =B31-C35 | C75: =C72/B75*100 | D75: % | R75: TOTAL | S75: =#REF!-S34-S35-S59-S58-S60-S61-S62-S63-S64-S65-S66+S67-S68-S69-S70-S71-S72-S73 | AJ75: TOTAL | AK75: =#REF!-AK34-AK35-AK58-AK59-AK60-AK61-AK62-AK63-AK64-AK65-AK66+AK67-AK68-AK69-AK70-AK71-AK72-AK73
R76: DOCTORS PAY | S76: =(S75*50%)+S77 | AJ76: DOCTORS PAY | AK76: =(AK75*50%)+AK77
B77: MEDISAVE ADMIN | C77: =G61+K61+O61+S83+W61+AA61+AF61+AK83 | D77: =C77/20 | F77: TOTAL PAYMENT | G77: =G57-G70-G74-G75-G71-G72-G73 | J77: TOTAL PAYMENT | K77: =K57-K70-K74-K75-K71-K72-K73 | N77: TOTAL PAYMENT | O77: =O57-O70-O74-O75-O71-O72-O73 | R77: ADJUSTMENTS (+) | V77: TOTAL PAYMENT | W77: =W57-W70-W74-W75-W71-W72-W73 | Z77: TOTAL PAYMENT | AA77: =AA57-AA70-AA74-AA75-AA71-AA72-AA73 | AE77: TOTAL PAYMENT | AF77: =AF57-AF70-AF74-AF75-AF71-AF72-AF73 | AJ77: ADJUSTMENTS (+) | AO77: TOTAL PAYMENT | AP77: =AP57-AP70-AP74-AP75-AP71-AP72-AP73 | AT77: TOTAL PAYMENT | AU77: =AU57-AU70-AU74-AU75-AU71-AU72-AU73 | AY77: TOTAL PAYMENT | AZ77: =AZ57-AZ70-AZ74-AZ75-AZ71-AZ72-AZ73
B78: ADDITIONAL MARKETING | C78: =G65+K65+O65+S87+W65+AA65+AF65+AP65+AU65+AZ65 | R78: ADJUSTMENTS (-) | S78: =S83+S87 | AJ78: ADJUSTMENTS (-) | AK78: =AK83+AK87 | AL78: MARKETING FEE & MEDISAVE ADMIN
B79: DOCTORS PERSONAL DEDUCTION | C79: =G70+G74+G75+K70+K74+K75+O70+O74+O75+S92+S96+S97+W70+W74+W75+AA70+AA74+AA75+AF70+AF74+AF75+G71+G72+G73+K71+K72+K73+O71+O72+O73+S93+S94+S95+W71+W72+W73+AA71+AA72+AA73+AF71+AF72+AF73+AP70+AP71+AP72+AP73+AP74+AP75+AU70+AU71+AU72+AU73+AU74+AU75+AZ70+AZ71+AZ72+AZ73+AZ74+AZ75 | R79: NET PAY | S79: =S76-S78 | AJ79: NET PAY | AK79: =AK76-AK78
B80: TOTAL | C80: =SUM(C77:C79)
B81: TOTAL ICC-5 | C81: =G36+K36+O36+S58+AA36+W36+AF36+AP36+AU36+AZ36 | R81: MEDISAVE ADMIN FEE CALCULATION: | AJ81: MEDISAVE ADMIN FEE CALCULATION:
R82: Medisave Claim | S82: Admin Fee | T82: REMARKS | AJ82: Medisave Claim | AK82: Admin Fee | AL82: REMARKS
B83: NURSES FEE-REVENUE | C83: =(C60+C61+C62)/B31 | S83: =R83*20 | AK83: =AJ83*20
B84: CONSUMABLE EXCL OFFICE RENT - REVENUE | C84: =(C49+C46+C48)/B31
B85: OFFICE RENT & ADMIN STAFF - REVENUE | C85: =(C45/B31) | R85: ADDITIONAL MARKETING: | AJ85: ADDITIONAL MARKETING:
B86: MARKETING - REVENUE | C86: =C50/B31 | R86: MONTH | S86: AMOUNT | T86: REMARKS | AJ86: MONTH | AK86: AMOUNT | AL86: REMARKS
R87: =R3 | AJ87: =AJ3
B88: PERCENT FHATEEN | C88: =VLOOKUP(C73,'[1]% RATES INCENTIVES WDLS'!C:D,2,TRUE)
R89: OTHERS: (CPF,PERSONAL REFUND, COURSEFEE) | AJ89: OTHERS: (CPF,PERSONAL REFUND, COURSEFEE)
R91: DETAILS | S91: AMOUNT | AJ91: DETAILS | AK91: AMOUNT
AH92: feb 2191
R99: TOTAL CHEQUE AMOUNT | S99: =S79-S92-S96-S97-S93-S94-S95 | AJ99: TOTAL CHEQUE AMOUNT | AK99: =AK79-AK92-AK96-AK97-AK93-AK94-AK95

Sheet BEDOK SETTLEMENT CAL NEW
A3: MONTH/YEAR: | B3: 46023 | E3: MONTH/YEAR: | F3: =B3 | I3: MONTH/YEAR: | J3: =B3 | M3: MONTH/YEAR: | N3: =B3 | Q3: MONTH/YEAR: | R3: =B3 | U3: MONTH/YEAR: | V3: =B3 | Y3: MONTH/YEAR: | Z3: =B3 | AD3: MONTH/YEAR: | AE3: =B3 | AI3: MONTH/YEAR: | AJ3: =AE3 | AN3: MONTH/YEAR: | AO3: =AE3 | AS3: MONTH/YEAR: | AT3: =AO3 | AX3: MONTH/YEAR: | AY3: =V3
A4: BRANCH: | B4: CASA DENTAL BEDOK PTE LTD | E4: BRANCH: | F4: =B4 | I4: BRANCH: | J4: =B4 | M4: BRANCH: | N4: =B4 | Q4: BRANCH: | R4: CASA DENTAL AMK PTE LTD | U4: BRANCH: | V4: =B4 | Y4: BRANCH: | Z4: =B4 | AD4: BRANCH: | AE4: =B4 | AI4: BRANCH: | AJ4: CASA DENTAL AMK PTE LTD | AN4: BRANCH: | AO4: =AE4 | AS4: BRANCH: | AT4: =AO4 | AX4: BRANCH: | AY4: =V4
A5: ALL PROVIDERS SETTLEMENT | E5: DR CHAN KC | I5: DR KEEFE SIM | M5: DR NG WAN TING | Q5: DR KALIE | U5: DR BRANDON ONG | Y5: DR KAREN LEONG | AD5: DR CHAN KC | AI5: DR ANDREW YIN | AN5: DR YVETTE CHOW | AS5: DR PETER KEITH | AX5: DR ROLAND FOO
C6: ADMIN CHARGES | G6: ADMIN CHARGES | J6: TOTALS | K6: ADMIN CHARGES | O6: ADMIN CHARGES | S6: ADMIN CHARGES | W6: ADMIN CHARGES | AA6: ADMIN CHARGES | AF6: ADMIN CHARGES | AK6: ADMIN CHARGES | AP6: ADMIN CHARGES | AU6: ADMIN CHARGES | AZ6: ADMIN CHARGES
A7: AIA | C7: =B7*0.05*1.09 | E7: AIA | G7: =F7*0.05*1.09 | I7: AIA | K7: =J7*0.05*1.09 | M7: AIA | O7: =N7*0.05*1.09 | Q7: AIA | S7: =R7*0.05*1.09 | U7: AIA | W7: =V7*0.05*1.09 | Y7: AIA | AA7: =Z7*0.05*1.09 | AD7: AIA | AF7: =AE7*0.05*1.09 | AI7: AIA | AK7: =AJ7*0.05*1.09 | AN7: AIA | AP7: =AO7*0.05*1.09 | AS7: AIA | AU7: =AT7*0.05*1.09 | AX7: AIA | AZ7: =AY7*0.05*1.09
A8: ALLIANCE | C8: =B8*0.05*1.09 | E8: ALLIANCE | G8: =F8*0.05*1.09 | I8: ALLIANCE | K8: =J8*0.05*1.09 | M8: ALLIANCE | O8: =N8*0.05*1.09 | U8: ALLIANCE | W8: =V8*0.05*1.09 | Y8: ALLIANCE | AA8: =Z8*0.05*1.09 | AD8: ALLIANCE | AF8: =AE8*0.05*1.09 | AN8: ALLIANCE | AP8: =AO8*0.05*1.09 | AS8: ALLIANCE | AU8: =AT8*0.05*1.09 | AX8: ALLIANCE | AZ8: =AY8*0.05*1.09
A9: AMEX | C9: =B9*0.0195 | E9: AMEX | G9: =F9*0.0195 | I9: AMEX | K9: =J9*0.0195 | M9: AMEX | O9: =N9*0.0195 | Q9: AMEX | S9: =R9*0.0195 | U9: AMEX | W9: =V9*0.0195 | Y9: AMEX | AA9: =Z9*0.0195 | AD9: AMEX | AF9: =AE9*0.0195 | AI9: AMEX | AK9: =AJ9*0.0195 | AN9: AMEX | AP9: =AO9*0.0195 | AS9: AMEX | AU9: =AT9*0.0195 | AX9: AMEX | AZ9: =AY9*0.0195
A10: BABYBONUS | C10: =B10*0.008 | E10: BABYBONUS | G10: =F10*0.008 | I10: BABYBONUS | K10: =J10*0.008 | M10: BABYBONUS | O10: =N10*0.008 | U10: BABYBONUS | W10: =V10*0.008 | Y10: BABYBONUS | AA10: =Z10*0.008 | AD10: BABYBONUS | AF10: =AE10*0.008 | AN10: BABYBONUS | AP10: =AO10*0.008 | AS10: BABYBONUS | AU10: =AT10*0.008 | AX10: BABYBONUS | AZ10: =AY10*0.008
A11: CASH | E11: CASH | I11: CASH | M11: CASH | Q11: ALLIANCE | S11: =R11*0.05*1.09 | U11: CASH | Y11: CASH | AD11: CASH | AI11: ALLIANCE | AK11: =AJ11*0.05*1.09 | AN11: CASH | AS11: CASH | AX11: CASH
A12: CASA VOUCHER | E12: CASA VOUCHER | I12: CASA VOUCHER | M12: CASA VOUCHER | Q12: CASH | U12: CASA VOUCHER | Y12: CASA VOUCHER | AD12: CASA VOUCHER | AI12: CASH | AN12: CASA VOUCHER | AS12: CASA VOUCHER | AX12: CASA VOUCHER
A13: CDC VOUCHER | E13: CDC VOUCHER | I13: CDC VOUCHER | M13: CDC VOUCHER | Q13: CASA VOUCHER | U13: CDC VOUCHER | Y13: CDC VOUCHER | AD13: CDC VOUCHER | AI13: CASA VOUCHER | AN13: CDC VOUCHER | AS13: CDC VOUCHER | AX13: CDC VOUCHER
A14: CHAS | E14: CHAS | I14: CHAS | M14: CHAS | U14: CHAS | Y14: CHAS | AD14: CHAS | AN14: CHAS | AS14: CHAS | AX14: CHAS
A15: CYNERGY | E15: CYNERGY | I15: CYNERGY | M15: CYNERGY | U15: CYNERGY | Y15: CYNERGY | AD15: CYNERGY | AN15: CYNERGY | AS15: CYNERGY | AX15: CYNERGY
A16: DA ADEPT HEALTH | C16: =B16*8% | E16: DA ADEPT HEALTH | G16: =F16*8% | I16: DA ADEPT HEALTH | K16: =J16*8% | M16: DA ADEPT HEALTH | O16: =N16*8% | U16: DA ADEPT HEALTH | W16: =V16*8% | Y16: DA ADEPT HEALTH | AA16: =Z16*8% | AD16: DA ADEPT HEALTH | AF16: =AE16*8% | AN16: DA ADEPT HEALTH | AP16: =AO16*8% | AS16: DA ADEPT HEALTH | AU16: =AT16*8% | AX16: DA ADEPT HEALTH | AZ16: =AY16*8%
A17: DEPOSIT | C17: =G17+K17+O17+O17+S17+W17+AA17+AF17+AP17+AU17+AZ17 | E17: DEPOSIT | I17: DEPOSIT | M17: DEPOSIT | Q17: DEPOSIT | S17: 0 | U17: DEPOSIT | Y17: DEPOSIT | AD17: DEPOSIT | AI17: DEPOSIT | AN17: DEPOSIT | AS17: DEPOSIT | AX17: DEPOSIT
A18: IHP | C18: =B18*0.051*1.09 | E18: IHP | G18: =F18*0.051*1.09 | I18: IHP | K18: =J18*0.051*1.09 | M18: IHP | O18: =N18*0.051*1.09 | U18: IHP | W18: =V18*0.051*1.09 | Y18: IHP | AA18: =Z18*0.051*1.09 | AD18: IHP | AF18: =AE18*0.051*1.09 | AN18: IHP | AP18: =AO18*0.051*1.09 | AS18: IHP | AU18: =AT18*0.051*1.09 | AX18: IHP | AZ18: =AY18*0.051*1.09
A19: JCB | C19: =B19*0.15*1.09 | E19: JCB | G19: =F19*0.15*1.09 | I19: JCB | K19: =J19*0.15*1.09 | M19: JCB | O19: =N19*0.15*1.09 | U19: JCB | W19: =V19*0.15*1.09 | Y19: JCB | AA19: =Z19*0.15*1.09 | AD19: JCB | AF19: =AE19*0.15*1.09 | AN19: JCB | AP19: =AO19*0.15*1.09 | AS19: JCB | AU19: =AT19*0.15*1.09 | AX19: JCB | AZ19: =AY19*0.15*1.09
A20: MASTER | C20: =B20*0.0225 | E20: MASTER | G20: =F20*0.021 | I20: MASTER | K20: =J20*0.0225 | M20: MASTER | O20: =N20*0.0225 | U20: MASTER | W20: =V20*0.0225 | Y20: MASTER | AA20: =Z20*0.0225 | AD20: MASTER | AF20: =AE20*0.0225 | AN20: MASTER | AP20: =AO20*0.0225 | AS20: MASTER | AU20: =AT20*0.0225 | AX20: MASTER | AZ20: =AY20*0.021
A21: MEDISAVE | E21: MEDISAVE | I21: MEDISAVE | M21: MEDISAVE | U21: MEDISAVE | Y21: MEDISAVE | AD21: MEDISAVE | AN21: MEDISAVE | AS21: MEDISAVE | AX21: MEDISAVE
A22: mednefits | C22: =B22*20% | E22: mednefits | G22: =F22*20% | I22: mednefits | K22: =J22*20% | M22: mednefits | O22: =N22*20% | U22: mednefits | W22: =V22*20% | Y22: mednefits | AA22: =Z22*20% | AD22: mednefits | AF22: =AE22*20% | AN22: mednefits | AP22: =AO22*20% | AS22: mednefits | AU22: =AT22*20% | AX22: mednefits | AZ22: =AY22*20%
A23: MHC | C23: =B23*0.15*1.09 | E23: MHC | G23: =F23*0.15*1.09 | I23: MHC | K23: =J23*0.15*1.09 | M23: MHC | O23: =N23*0.15*1.09 | U23: MHC | W23: =V23*0.15*1.09 | Y23: MHC | AA23: =Z23*0.15*1.09 | AD23: MHC | AF23: =AE23*0.15*1.09 | AN23: MHC | AP23: =AO23*0.15*1.09 | AS23: MHC | AU23: =AT23*0.15*1.09 | AX23: MHC | AZ23: =AY23*0.15*1.09
A24: NETS | C24: =B24*0.008 | E24: NETS | G24: =F24*0.008 | I24: NETS | K24: =J24*0.008 | M24: NETS | O24: =N24*0.008 | U24: NETS | W24: =V24*0.008 | Y24: NETS | AA24: =Z24*0.008 | AD24: NETS | AF24: =AE24*0.008 | AN24: NETS | AP24: =AO24*0.008 | AS24: NETS | AU24: =AT24*0.008 | AX24: NETS | AZ24: =AY24*0.008
A25: PARKWAY | C25: =B25*10% | E25: PARKWAY | G25: =F25*10% | I25: PARKWAY | K25: =J25*10% | M25: PARKWAY | O25: =N25*10% | U25: PARKWAY | W25: =V25*10% | Y25: PARKWAY | AA25: =Z25*10% | AD25: PARKWAY | AF25: =AE25*10% | AN25: PARKWAY | AP25: =AO25*10% | AS25: PARKWAY | AU25: =AT25*10% | AX25: PARKWAY | AZ25: =AY25*10%
A26: PAYNOW | E26: PAYNOW | I26: PAYNOW | M26: PAYNOW | U26: PAYNOW | Y26: PAYNOW | AD26: PAYNOW | AN26: PAYNOW | AS26: PAYNOW | AX26: PAYNOW
A27: RHI | E27: RHI | I27: RHI | M27: RHI | U27: RHI | Y27: RHI | AD27: RHI | AN27: RHI | AS27: RHI | AX27: RHI
A28: SAH | C28: =B28*8% | E28: SAH | G28: =F28*8% | I28: SAH | K28: =J28*8% | M28: SAH | O28: =N28*8% | U28: SAH | W28: =V28*8% | Y28: SAH | AA28: =Z28*8% | AD28: SAH | AF28: =AE28*8% | AN28: SAH | AP28: =AO28*8% | AS28: SAH | AU28: =AT28*8% | AX28: SAH | AZ28: =AY28*8%
A29: UNION PAY | C29: =B29*2.5% | E29: UNION PAY | G29: =F29*2.5% | I29: UNION PAY | K29: =J29*2.5% | M29: UNION PAY | O29: =N29*2.5% | U29: UNION PAY | W29: =V29*2.5% | Y29: UNION PAY | AA29: =Z29*2.5% | AD29: UNION PAY | AF29: =AE29*2.5% | AN29: UNION PAY | AP29: =AO29*2.5% | AS29: UNION PAY | AU29: =AT29*2.5% | AX29: UNION PAY | AZ29: =AY29*2.5%
A30: VISA | C30: =B30*0.0225 | E30: VISA | G30: =F30*0.021 | I30: VISA | K30: =J30*0.0225 | M30: VISA | O30: =N30*0.0225 | U30: VISA | W30: =V30*0.0225 | Y30: VISA | AA30: =Z30*0.0225 | AD30: VISA | AF30: =AE30*0.0225 | AN30: VISA | AP30: =AO30*0.0225 | AS30: VISA | AU30: =AT30*0.0225 | AX30: VISA | AZ30: =AY30*0.021
A31: TOTAL INCOME | B31: =SUM(B7:B30) | C31: =SUM(C7:C30) | E31: DR TOTAL INCOME | F31: =SUM(F7:F30) | G31: =SUM(G7:G30) | I31: DR TOTAL INCOME | J31: =SUM(J7:J30) | K31: =SUM(K7:K30) | M31: DR TOTAL INCOME | N31: =SUM(N7:N30) | O31: =SUM(O7:O30) | U31: DR TOTAL INCOME | V31: =SUM(V7:V30) | W31: =SUM(W7:W30) | Y31: DR TOTAL INCOME | Z31: =SUM(Z7:Z30) | AA31: =SUM(AA7:AA30) | AD31: DR TOTAL INCOME | AE31: =SUM(AE7:AE30) | AF31: =SUM(AF7:AF30) | AN31: DR TOTAL INCOME | AO31: =SUM(AO7:AO30) | AP31: =SUM(AP7:AP30) | AS31: DR TOTAL INCOME | AT31: =SUM(AT7:AT30) | AU31: =SUM(AU7:AU30) | AX31: DR TOTAL INCOME | AY31: =SUM(AY7:AY30) | AZ31: =SUM(AZ7:AZ30)
B33: EXPENSES | F33: DEDUCTIONS | H33: REMARKS | J33: DEDUCTIONS | L33: REMARKS | N33: DEDUCTIONS | P33: REMARKS | R33: DEDUCTIONS | T33: REMARKS | V33: DEDUCTIONS | X33: REMARKS | Z33: DEDUCTIONS | AB33: REMARKS | AE33: DEDUCTIONS | AG33: REMARKS | AJ33: DEDUCTIONS | AL33: REMARKS | AO33: DEDUCTIONS | AQ33: REMARKS | AT33: DEDUCTIONS | AV33: REMARKS | AY33: DEDUCTIONS | BA33: REMARKS
B34: ADMIN FEE | C34: =SUM(C7:C30) | F34: ADMIN CHARGES | G34: =G31 | J34: ADMIN CHARGES | K34: =K31 | N34: ADMIN CHARGES | O34: =O31 | R34: ADMIN CHARGES | S34: =#REF! | V34: ADMIN CHARGES | W34: =W31 | Z34: ADMIN CHARGES | AA34: =AA31 | AE34: ADMIN CHARGES | AF34: =AF31 | AJ34: ADMIN CHARGES | AK34: =#REF! | AO34: ADMIN CHARGES | AP34: =AP31 | AT34: ADMIN CHARGES | AU34: =AU31 | AY34: ADMIN CHARGES | AZ34: =AZ31
B35: GST | C35: =K35+O35+AA35+AF35+AM35+AP35+T35+W35+AU35+AZ35 | F35: GST | J35: GST | N35: GST | R35: GST | V35: GST | Z35: GST | AE35: GST | AJ35: GST | AO35: GST | AT35: GST | AY35: GST
B36: RENTAL | F36: ICC-5 | J36: ICC-5 | N36: ICC-5 | V36: ICC-5 | Z36: ICC-5 | AE36: ICC-5 | AO36: ICC-5 | AT36: ICC-5 | AY36: ICC-5
B37: LOAN INTEREST | F37: PRODUCTS | J37: PRODUCTS | N37: PRODUCTS | V37: PRODUCTS | Z37: PRODUCTS | AE37: PRODUCTS | AO37: PRODUCTS | AT37: PRODUCTS | AY37: PRODUCTS
B38: IRAS TAX | D38: feb 2026 $9950 | F38: ORTHO (B+B) | J38: ORTHO (B+B) | N38: ORTHO (B+B) | V38: ORTHO (B+B) | Z38: ORTHO (B+B) | AE38: ORTHO (B+B) | AO38: ORTHO (B+B) | AT38: ORTHO (B+B) | AY38: ORTHO (B+B)
B39: CK SECRETARIAL / ACCOUNTS SERVICES | D39: mar - jun 2026 $4950 | F39: ABUTMENTS | J39: ABUTMENTS | N39: ABUTMENTS | V39: ABUTMENTS | Z39: ABUTMENTS | AE39: ABUTMENTS | AO39: ABUTMENTS | AT39: ABUTMENTS | AY39: ABUTMENTS
B40: TOWN COUNCIL | F40: IMPLANT | J40: IMPLANT | N40: IMPLANT | V40: IMPLANT | Z40: IMPLANT | AE40: IMPLANT | AO40: IMPLANT | AT40: IMPLANT | AY40: IMPLANT
B41: SERVICE & CONSERVANCY CHARGES | F41: SKY LAB | J41: SKY LAB | N41: SKY LAB | V41: SKY LAB | Z41: SKY LAB | AE41: SKY LAB | AO41: SKY LAB | AT41: SKY LAB | AY41: SKY LAB
B42: SP | F42: DIGICADCAM | J42: DIGICADCAM | N42: DIGICADCAM | V42: DIGICADCAM | Z42: DIGICADCAM | AE42: DIGICADCAM | AO42: DIGICADCAM | AT42: DIGICADCAM | AY42: DIGICADCAM
B43: SINGTEL | F43: OTHER LAB | J43: OTHER LAB | N43: OTHER LAB | V43: OTHER LAB | Z43: OTHER LAB | AE43: OTHER LAB | AO43: OTHER LAB | AT43: OTHER LAB | AY43: OTHER LAB
B44: PRODUCTS | C44: =G37+K37+O37+S59+W37+AA37+AF37+AK59+AP37+AU37+AZ37 | F44: INVISALIGN | J44: INVISALIGN | N44: INVISALIGN | V44: INVISALIGN | Z44: INVISALIGN | AE44: INVISALIGN | AO44: INVISALIGN | AT44: INVISALIGN | AY44: INVISALIGN
B45: ADMIN STAFF & OFFICE RENTAL | F45: TRANSFER (+) | J45: TRANSFER (+) | N45: TRANSFER (+) | V45: TRANSFER (+) | Z45: TRANSFER (+) | AE45: TRANSFER (+) | AO45: TRANSFER (+) | AT45: TRANSFER (+) | AY45: TRANSFER (+)
B46: SUPPLIERS | F46: TRANSFER (-) | J46: TRANSFER (-) | N46: TRANSFER (-) | V46: TRANSFER (-) | Z46: TRANSFER (-) | AE46: TRANSFER (-) | AO46: TRANSFER (-) | AT46: TRANSFER (-) | AY46: TRANSFER (-)
B47: VOUCHER | C47: =B12 | F47: REFUND/REFERRAL | J47: REFUND/REFERRAL | N47: REFUND/REFERRAL | V47: REFUND | Z47: REFUND | AE47: REFUND | AO47: REFUND | AT47: REFUND | AY47: REFUND
B48: PETTY CASH | F48: VOUCHER | G48: =F12 | J48: VOUCHER | N48: VOUCHER | V48: VOUCHER | Z48: VOUCHER | AE48: SEDATION | AO48: SEDATION | AT48: SEDATION | AY48: SEDATION
B49: STOCKS / CONSUMABLES FEES | F49: RETAINERS/BT/SPLINT | J49: RETAINERS/BT/SPLINT | N49: RETAINERS/BT/SPLINT | V49: RETAINERS/BT/SPLINT | Z49: RETAINERS/BT/SPLINT | AE49: RETAINERS/BT/SPLINT | AO49: RETAINERS/BT/SPLINT | AT49: RETAINERS/BT/SPLINT | AY49: RETAINERS/BT/SPLINT
B50: MARKETING FEE | F50: INSTALLMENT | J50: INSTALLMENT | N50: INSTALLMENT | V50: INSTALLMENT | Z50: INSTALLMENT | AE50: INSTALLMENT | AO50: INSTALLMENT | AT50: INSTALLMENT | AY50: INSTALLMENT
B51: INVISALIGN | C51: =G44+K44+O44+S66+W44+AA44+AF44+AK66+AP44+AU44 | F51: DEDUCTIONS | J51: DEDUCTIONS | N51: DEDUCTIONS | V51: DEDUCTIONS | Z51: DEDUCTIONS | AE51: DEDUCTIONS | AO51: DEDUCTIONS | AT51: DEDUCTIONS | AY51: DEDUCTIONS
B52: IMPLANT | C52: =G40+O40+S62+W40+AA40+AF40+K40+AK62
B53: SKYLAB | C53: =G41+O41+W41+S63+K41+AA41+AF41+AK63 | F53: TOTAL | G53: =F31-G34-G35-G37-G36-G38-G39-G40-G41-G42-G43-G44+G45-G46-G47-G48-G49-G50-G51 | J53: TOTAL | K53: =J31-K34-K35-K36-K37-K38-K39-K40-K41-K42-K43-K44+K45-K46-K47-K48-K49-K50-K51 | N53: TOTAL | O53: =N31-O34-O35-O36-O37-O38-O39-O40-O41-O42-O43-O44+O45-O46-O47-O48-O49-O50-O51 | V53: TOTAL | W53: =V31-W34-W35-W36-W37-W38-W39-W40-W41-W42-W43-W44+W45-W46-W47-W48-W49-W50-W51 | Z53: TOTAL | AA53: =Z31-AA34-AA35-AA36-AA37-AA38-AA39-AA40-AA41-AA42-AA43-AA44+AA45-AA46-AA47-AA48-AA49-AA50-AA51 | AE53: TOTAL | AF53: =AE31-AF34-AF35-AF36-AF37-AF38-AF39-AF40-AF41-AF42-AF43-AF44+AF45-AF46-AF47-AF48-AF49-AF50-AF51 | AO53: TOTAL | AP53: =AO31-AP34-AP35-AP36-AP37-AP38-AP39-AP40-AP41-AP42-AP43-AP44+AP45-AP46-AP47-AP48-AP49-AP50-AP51 | AT53: TOTAL | AU53: =AT31-AU34-AU35-AU36-AU37-AU38-AU39-AU40-AU41-AU42-AU43-AU44+AU45-AU46-AU47-AU48-AU49-AU50-AU51 | AY53: TOTAL | AZ53: =AY31-AZ34-AZ35-AZ36-AZ37-AZ38-AZ39-AZ40-AZ41-AZ42-AZ43-AZ44+AZ45-AZ46-AZ47-AZ48-AZ49-AZ50-AZ51
B54: DIGICADCAM | C54: =G42+O42+W42+AA42+AF42+S64+K42+AK64 | F54: DOCTORS FEE BEFORE DEDUCTION | G54: =G53/2+G55 | J54: DOCTORS FEE BEFORE DEDUCTION | K54: =K53/2+K55 | N54: DOCTORS PAY | O54: =(O53*50%)+O55 | V54: DOCTORS PAY | W54: =(W53*45%)+W55 | Z54: DOCTORS PAY | AA54: =(AA53*45%)+AA55 | AE54: DOCTORS PAY | AF54: =(AF53*50%)+AF55 | AO54: DOCTORS PAY | AP54: =(AP53*45%)+AP55 | AT54: DOCTORS PAY | AU54: =(AU53*50%)+AU55 | AY54: DOCTORS PAY | AZ54: =(AZ53*50%)+AZ55
B55: OTHER LAB | C55: =G43+O43+K43+S65+W43+AA43+AF43+AK65 | F55: ADJUSTMENTS (+) | J55: ADJUSTMENTS (+) | N55: ADJUSTMENTS (+) | V55: ADJUSTMENTS (+) | Z55: ADJUSTMENTS (+) | AE55: ADJUSTMENTS (+) | AO55: ADJUSTMENTS (+) | AT55: ADJUSTMENTS (+) | AY55: ADJUSTMENTS (+)
B56: ORTHO (B+B) | C56: =G38+K38+O38+S60+W38+AA38+AF38+AK60 | F56: ADJUSTMENTS (-) | G56: =G61+G65 | H56: ADDN MARKETING& MEDISAVE ADMIN | J56: ADJUSTMENTS (-) | K56: =K61+K65 | L56: ADDN MARKETING | N56: ADJUSTMENTS (-) | O56: =O61+O65 | P56: ADDN MARKETING & MEDISAVE ADMIN | V56: ADJUSTMENTS (-) | W56: =W61+W65 | X56: ADDN MKTRG & MEDISAVE ADMIN | Z56: ADJUSTMENTS (-) | AA56: =AA61+AA65 | AB56: MARKETING FEE & MEDISAVE ADMIN | AE56: ADJUSTMENTS (-) | AF56: =AF61+AF65 | AG56: MARKETING FEE & MEDISAVE ADMIN | AO56: ADJUSTMENTS (-) | AP56: =AP61+AP65 | AQ56: MARKETING FEE & MEDISAVE ADMIN | AT56: ADJUSTMENTS (-) | AU56: =AU61+AU65 | AV56: MARKETING FEE & MEDISAVE ADMIN | AY56: ADJUSTMENTS (-) | AZ56: =AZ61+AZ65 | BA56: MARKETING FEE & MEDISAVE ADMIN
B57: ABUTMENT | C57: =O39+G39+K39+S61+AA39+W39+AF39+AK61 | F57: NET PAY | G57: =G54-G56 | J57: NET PAY | K57: =K54-K56 | N57: NET PAY | O57: =O54-O56 | V57: NET PAY | W57: =W54-W56 | Z57: NET PAY | AA57: =AA54-AA56 | AE57: NET PAY | AF57: =AF54-AF56 | AO57: NET PAY | AP57: =AP54-AP56 | AT57: NET PAY | AU57: =AU54-AU56 | AY57: NET PAY | AZ57: =AZ54-AZ56
B58: REFUND / REFERRAL | C58: =G47+K47+O47+S69+W47+AA47+AF47+AK69 | R58: ICC-5 | AJ58: ICC-5
B59: DOCTORS PAY | C59: =G54+K54+O54+W54+AA54+AF54+AP54+AU54+AZ54 | F59: MEDISAVE ADMIN FEE CALCULATION: | J59: MEDISAVE ADMIN FEE CALCULATION: | N59: MEDISAVE ADMIN FEE CALCULATION: | R59: PRODUCTS | V59: MEDISAVE ADMIN FEE CALCULATION: | Z59: MEDISAVE ADMIN FEE CALCULATION: | AE59: MEDISAVE ADMIN FEE CALCULATION: | AJ59: PRODUCTS | AO59: MEDISAVE ADMIN FEE CALCULATION: | AT59: MEDISAVE ADMIN FEE CALCULATION: | AY59: MEDISAVE ADMIN FEE CALCULATION:
B60: NURSE PAY (BASIC PAY) | F60: Medisave Claim | G60: Admin Fee | H60: REMARKS | J60: Medisave Claim | K60: Admin Fee | L60: REMARKS | N60: Medisave Claim | O60: Admin Fee | P60: REMARKS | R60: ORTHO (B+B) | V60: Medisave Claim | W60: Admin Fee | X60: REMARKS | Z60: Medisave Claim | AA60: Admin Fee | AB60: REMARKS | AE60: Medisave Claim | AF60: Admin Fee | AG60: REMARKS | AJ60: ORTHO (B+B) | AO60: Medisave Claim | AP60: Admin Fee | AQ60: REMARKS | AT60: Medisave Claim | AU60: Admin Fee | AV60: REMARKS | AY60: Medisave Claim | AZ60: Admin Fee | BA60: REMARKS
B61: NURSE PAY (INCENTIVE) | G61: =F61*20 | K61: =J61*20 | O61: =N61*20 | R61: ABUTMENTS | W61: =V61*20 | AA61: =Z61*20 | AF61: =AE61*20 | AJ61: ABUTMENTS | AP61: =AO61*20 | AU61: =AT61*20 | AZ61: =AY61*20
B62: NURSE TRANSFER FEE | R62: IMPLANT | AJ62: IMPLANT
B63: TANK CULTURE | C63: 163.5 | F63: ADDITIONAL MARKETING: | J63: ADDITIONAL MARKETING: | N63: ADDITIONAL MARKETING: | R63: SKY LAB | V63: ADDITIONAL MARKETING: | Z63: ADDITIONAL MARKETING: | AE63: ADDITIONAL MARKETING: | AJ63: SKY LAB | AO63: ADDITIONAL MARKETING: | AT63: ADDITIONAL MARKETING: | AY63: ADDITIONAL MARKETING:
B64: SHARP BIN | F64: MONTH | G64: AMOUNT | H64: REMARKS | J64: MONTH | K64: AMOUNT | L64: REMARKS | N64: MONTH | O64: AMOUNT | P64: REMARKS | R64: DIGICADCAM | V64: MONTH | W64: AMOUNT | X64: REMARKS | Z64: MONTH | AA64: AMOUNT | AB64: REMARKS | AE64: MONTH | AF64: AMOUNT | AG64: REMARKS | AJ64: DIGICADCAM | AO64: MONTH | AP64: AMOUNT | AQ64: REMARKS | AT64: MONTH | AU64: AMOUNT | AV64: REMARKS | AY64: MONTH | AZ64: AMOUNT | BA64: REMARKS
B65: COURIER | C65: 129.44 | F65: =B3 | J65: =F65 | K65: 150 | N65: =F65 | O65: 300 | R65: OTHER LAB | V65: =V3 | W65: 180 | Z65: =V65 | AE65: =AE3 | AJ65: OTHER LAB | AO65: =AO3 | AT65: =AT3 | AY65: =AY3
B66: REPAIR & MAINTENANCE | R66: INVISALIGN | AJ66: INVISALIGN
B67: MOM LEVY | C67: =400+400+138.11 | F67: OTHERS: (CPF,PERSONAL REFUND, COURSEFEE) | J67: OTHERS: (CPF,PERSONAL REFUND, COURSEFEE) | N67: OTHERS: (CPF,PERSONAL REFUND, COURSEFEE) | R67: TRANSFER (+) | V67: OTHERS: (CPF,PERSONAL REFUND, COURSEFEE) | Z67: OTHERS: (CPF,PERSONAL REFUND, COURSEFEE) | AE67: OTHERS: (CPF,PERSONAL REFUND, COURSEFEE) | AJ67: TRANSFER (+) | AO67: OTHERS: (CPF,PERSONAL REFUND, COURSEFEE) | AT67: OTHERS: (CPF,PERSONAL REFUND, COURSEFEE) | AY67: OTHERS: (CPF,PERSONAL REFUND, COURSEFEE)
R68: TRANSFER (-) | AJ68: TRANSFER (-)
F69: DETAILS | G69: AMOUNT | J69: DETAILS | K69: AMOUNT | N69: DETAILS | O69: AMOUNT | R69: REFUND | V69: DETAILS | W69: AMOUNT | Z69: DETAILS | AA69: AMOUNT | AE69: DETAILS | AF69: AMOUNT | AJ69: REFUND | AO69: DETAILS | AP69: AMOUNT | AT69: DETAILS | AU69: AMOUNT | AY69: DETAILS | AZ69: AMOUNT
F70: CPF CONT SALARY | R70: VOUCHER | AJ70: SEDATION
AJ71: RETAINERS/BT/SPLINT
B72: TOTAL | C72: =B31-C34-C35-C58-C36-C37-C42-C43-C38-C46-C39-C45-C48-C49-C51-C50-C55-C54-C53-C59-C60-C61-C62-C47-C63-C40-C64-C41-C67-C66-C65-C90-C91-C92-C93-C94-C95-C68-C69-C70 | AJ72: INSTALLMENT
B73: FOR INCENTIVE % | C73: =B31-C34-C35-C58-C42-C43-C46-C45-C48-C44-C49-C50-C47-C63-C40-C64-C41-C65-C93-C95-C94-C66-C92-C90 | AJ73: DEDUCTIONS
B74: PERCENT | C74: =VLOOKUP(C73,'% RATES INCENTIVES'!C:D,2,TRUE)
A75: INCOME LESS GST | B75: =B31-C35 | C75: =C72/B75*100 | D75: % | R75: TOTAL | S75: =#REF!-S34-S35-S59-S58-S60-S61-S62-S63-S64-S65-S66+S67-S68-S69-S70-S71-S72-S73 | AJ75: TOTAL | AK75: =#REF!-AK34-AK35-AK58-AK59-AK60-AK61-AK62-AK63-AK64-AK65-AK66+AK67-AK68-AK69-AK70-AK71-AK72-AK73
R76: DOCTORS PAY | S76: =(S75*50%)+S77 | AJ76: DOCTORS PAY | AK76: =(AK75*50%)+AK77
B77: MEDISAVE ADMIN | C77: =G61+K61+O61+S83+W61+AA61+AF61+AK83 | D77: =C77/20 | F77: TOTAL PAYMENT | G77: =G57-G70-G74-G75-G71-G72-G73 | J77: TOTAL PAYMENT | K77: =K57-K70-K74-K75-K71-K72-K73 | N77: TOTAL PAYMENT | O77: =O57-O70-O74-O75-O71-O72-O73 | R77: ADJUSTMENTS (+) | V77: TOTAL PAYMENT | W77: =W57-W70-W74-W75-W71-W72-W73 | Z77: TOTAL PAYMENT | AA77: =AA57-AA70-AA74-AA75-AA71-AA72-AA73 | AE77: TOTAL PAYMENT | AF77: =AF57-AF70-AF74-AF75-AF71-AF72-AF73 | AJ77: ADJUSTMENTS (+) | AO77: TOTAL PAYMENT | AP77: =AP57-AP70-AP74-AP75-AP71-AP72-AP73 | AT77: TOTAL PAYMENT | AU77: =AU57-AU70-AU74-AU75-AU71-AU72-AU73 | AY77: TOTAL PAYMENT | AZ77: =AZ57-AZ70-AZ74-AZ75-AZ71-AZ72-AZ73
B78: ADDITIONAL MARKETING | C78: =G65+K65+O65+S87+W65+AA65+AF65+AP65+AU65+AZ65 | R78: ADJUSTMENTS (-) | S78: =S83+S87 | AJ78: ADJUSTMENTS (-) | AK78: =AK83+AK87 | AL78: MARKETING FEE & MEDISAVE ADMIN
B79: DOCTORS PERSONAL DEDUCTION | C79: =G70+G74+G75+K70+K74+K75+O70+O74+O75+S92+S96+S97+W70+W74+W75+AA70+AA74+AA75+AF70+AF74+AF75+G71+G72+G73+K71+K72+K73+O71+O72+O73+S93+S94+S95+W71+W72+W73+AA71+AA72+AA73+AF71+AF72+AF73+AP70+AP71+AP72+AP73+AP74+AP75+AU70+AU71+AU72+AU73+AU74+AU75+AZ70+AZ71+AZ72+AZ73+AZ74+AZ75 | R79: NET PAY | S79: =S76-S78 | AJ79: NET PAY | AK79: =AK76-AK78
B80: TOTAL | C80: =SUM(C77:C79)
B81: TOTAL ICC-5 | C81: =G36+K36+O36+S58+AA36+W36+AF36+AP36+AU36+AZ36 | R81: MEDISAVE ADMIN FEE CALCULATION: | AJ81: MEDISAVE ADMIN FEE CALCULATION:
R82: Medisave Claim | S82: Admin Fee | T82: REMARKS | AJ82: Medisave Claim | AK82: Admin Fee | AL82: REMARKS
B83: NURSES FEE-REVENUE | C83: =(C60+C61+C62)/B31 | S83: =R83*20 | AK83: =AJ83*20
B84: CONSUMABLE EXCL OFFICE RENT - REVENUE | C84: =(C49+C46+C48)/B31
B85: OFFICE RENT & ADMIN STAFF - REVENUE | C85: =(C45/B31) | R85: ADDITIONAL MARKETING: | AJ85: ADDITIONAL MARKETING:
B86: MARKETING - REVENUE | C86: =C50/B31 | R86: MONTH | S86: AMOUNT | T86: REMARKS | AJ86: MONTH | AK86: AMOUNT | AL86: REMARKS
R87: =R3 | AJ87: =AJ3
R89: OTHERS: (CPF,PERSONAL REFUND, COURSEFEE) | AJ89: OTHERS: (CPF,PERSONAL REFUND, COURSEFEE)
R91: DETAILS | S91: AMOUNT | AJ91: DETAILS | AK91: AMOUNT
AH92: feb 2191
R99: TOTAL CHEQUE AMOUNT | S99: =S79-S92-S96-S97-S93-S94-S95 | AJ99: TOTAL CHEQUE AMOUNT | AK99: =AK79-AK92-AK96-AK97-AK93-AK94-AK95

Sheet TENGAH SETTLEMENT CAL NEW
A3: MONTH/YEAR: | B3: 46023 | E3: MONTH/YEAR: | F3: =B3 | I3: MONTH/YEAR: | J3: =B3 | M3: MONTH/YEAR: | N3: =B3 | Q3: MONTH/YEAR: | R3: =B3 | U3: MONTH/YEAR: | V3: =B3 | Y3: MONTH/YEAR: | Z3: =B3 | AD3: MONTH/YEAR: | AE3: =B3 | AI3: MONTH/YEAR: | AJ3: =AE3
A4: BRANCH: | B4: CASA DENTAL TENGAH PTE LTD | E4: BRANCH: | F4: =B4 | I4: BRANCH: | J4: =F4 | M4: BRANCH: | N4: =J4 | Q4: BRANCH: | R4: CASA DENTAL AMK PTE LTD | U4: BRANCH: | V4: =N4 | Y4: BRANCH: | Z4: =V4 | AD4: BRANCH: | AE4: =Z4 | AI4: BRANCH: | AJ4: =AE4
A5: ALL PROVIDERS SETTLEMENT | E5: DR ANGELA TRAN | I5: DR ANG LI EN | M5: DR AMIT PATEL | Q5: DR KALIE | U5: DR PETER KEITH | Y5: DR JENNIFER HOANG | AD5: DR KALIE CHIA | AI5: DR YVETTE CHOW
C6: ADMIN CHARGES | G6: ADMIN CHARGES | J6: TOTALS | K6: ADMIN CHARGES | O6: ADMIN CHARGES | S6: ADMIN CHARGES | W6: ADMIN CHARGES | AA6: ADMIN CHARGES | AF6: ADMIN CHARGES | AK6: ADMIN CHARGES
A7: AIA | C7: =B7*0.05*1.09 | E7: AIA | G7: =F7*0.05*1.09 | I7: AIA | K7: =J7*0.05*1.09 | M7: AIA | O7: =N7*0.05*1.09 | Q7: AIA | S7: =R7*0.05*1.09 | U7: AIA | W7: =V7*0.05*1.09 | Y7: AIA | AA7: =Z7*0.05*1.09 | AD7: AIA | AF7: =AE7*0.05*1.09 | AI7: AIA | AK7: =AJ7*0.05*1.09
A8: ALLIANCE | C8: =B8*0.05*1.09 | E8: ALLIANCE | G8: =F8*0.05*1.09 | I8: ALLIANCE | K8: =J8*0.05*1.09 | M8: ALLIANCE | O8: =N8*0.05*1.09 | U8: ALLIANCE | W8: =V8*0.05*1.09 | Y8: ALLIANCE | AA8: =Z8*0.05*1.09 | AD8: ALLIANCE | AF8: =AE8*0.05*1.09 | AI8: ALLIANCE | AK8: =AJ8*0.05*1.09
A9: AMEX | C9: =B9*0.0195 | E9: AMEX | G9: =F9*0.0195 | I9: AMEX | K9: =J9*0.0195 | M9: AMEX | O9: =N9*0.0195 | Q9: AMEX | S9: =R9*0.0195 | U9: AMEX | W9: =V9*0.0195 | Y9: AMEX | AA9: =Z9*0.0195 | AD9: AMEX | AF9: =AE9*0.0195 | AI9: AMEX | AK9: =AJ9*0.0195
A10: BABYBONUS | C10: =B10*0.008 | E10: BABYBONUS | G10: =F10*0.008 | I10: BABYBONUS | K10: =J10*0.008 | M10: BABYBONUS | O10: =N10*0.008 | U10: BABYBONUS | W10: =V10*0.008 | Y10: BABYBONUS | AA10: =Z10*0.008 | AD10: BABYBONUS | AF10: =AE10*0.008 | AI10: BABYBONUS | AK10: =AJ10*0.008
A11: CASH | E11: CASH | I11: CASH | M11: CASH | Q11: ALLIANCE | S11: =R11*0.05*1.09 | U11: CASH | Y11: CASH | AD11: CASH | AI11: CASH
A12: CASA VOUCHER | E12: CASA VOUCHER | I12: CASA VOUCHER | M12: CASA VOUCHER | Q12: CASH | U12: CASA VOUCHER | Y12: CASA VOUCHER | AD12: CASA VOUCHER | AI12: CASA VOUCHER
A13: CDC VOUCHER | E13: CDC VOUCHER | I13: CDC VOUCHER | M13: CDC VOUCHER | Q13: CASA VOUCHER | U13: CDC VOUCHER | Y13: CDC VOUCHER | AD13: CDC VOUCHER | AI13: CDC VOUCHER
A14: CHAS | E14: CHAS | I14: CHAS | M14: CHAS | U14: CHAS | Y14: CHAS | AD14: CHAS | AI14: CHAS
A15: CYNERGY | E15: CYNERGY | I15: CYNERGY | M15: CYNERGY | U15: CYNERGY | Y15: CYNERGY | AD15: CYNERGY | AI15: CYNERGY
A16: DA ADEPT HEALTH | C16: =B16*8% | E16: DA ADEPT HEALTH | G16: =F16*8% | I16: DA ADEPT HEALTH | K16: =J16*8% | M16: DA ADEPT HEALTH | O16: =N16*8% | U16: DA ADEPT HEALTH | W16: =V16*8% | Y16: DA ADEPT HEALTH | AA16: =Z16*8% | AD16: DA ADEPT HEALTH | AF16: =AE16*8% | AI16: DA ADEPT HEALTH | AK16: =AJ16*8%
A17: DEPOSIT | C17: =G17+K17+O17+O17+S17+W17+AA17+AF17 | E17: DEPOSIT | I17: DEPOSIT | M17: DEPOSIT | Q17: DEPOSIT | S17: 0 | U17: DEPOSIT | Y17: DEPOSIT | AD17: DEPOSIT | AI17: DEPOSIT
A18: IHP | C18: =B18*0.051*1.09 | E18: IHP | G18: =F18*0.051*1.09 | I18: IHP | K18: =J18*0.051*1.09 | M18: IHP | O18: =N18*0.051*1.09 | U18: IHP | W18: =V18*0.051*1.09 | Y18: IHP | AA18: =Z18*0.051*1.09 | AD18: IHP | AF18: =AE18*0.051*1.09 | AI18: IHP | AK18: =AJ18*0.051*1.09
A19: JCB | C19: =B19*0.15*1.09 | E19: JCB | G19: =F19*0.15*1.09 | I19: JCB | K19: =J19*0.15*1.09 | M19: JCB | O19: =N19*0.15*1.09 | U19: JCB | W19: =V19*0.15*1.09 | Y19: JCB | AA19: =Z19*0.15*1.09 | AD19: JCB | AF19: =AE19*0.15*1.09 | AI19: JCB | AK19: =AJ19*0.15*1.09
A20: MASTER | C20: =B20*0.0225 | E20: MASTER | G20: =F20*0.0225 | I20: MASTER | K20: =J20*0.0225 | M20: MASTER | O20: =N20*0.0225 | U20: MASTER | W20: =V20*0.0225 | Y20: MASTER | AA20: =Z20*0.0225 | AD20: MASTER | AF20: =AE20*0.0225 | AI20: MASTER | AK20: =AJ20*0.0225
A21: MEDISAVE | E21: MEDISAVE | I21: MEDISAVE | M21: MEDISAVE | U21: MEDISAVE | Y21: MEDISAVE | AD21: MEDISAVE | AI21: MEDISAVE
A22: mednefits | C22: =B22*20% | E22: mednefits | G22: =F22*20% | I22: mednefits | K22: =J22*20% | M22: mednefits | O22: =N22*20% | U22: mednefits | W22: =V22*20% | Y22: mednefits | AA22: =Z22*20% | AD22: mednefits | AF22: =AE22*20% | AI22: mednefits | AK22: =AJ22*20%
A23: MHC | C23: =B23*0.15*1.09 | E23: MHC | G23: =F23*0.15*1.09 | I23: MHC | K23: =J23*0.15*1.09 | M23: MHC | O23: =N23*0.15*1.09 | U23: MHC | W23: =V23*0.15*1.09 | Y23: MHC | AA23: =Z23*0.15*1.09 | AD23: MHC | AF23: =AE23*0.15*1.09 | AI23: MHC | AK23: =AJ23*0.15*1.09
A24: NETS | C24: =B24*0.008 | E24: NETS | G24: =F24*0.008 | I24: NETS | K24: =J24*0.008 | M24: NETS | O24: =N24*0.008 | U24: NETS | W24: =V24*0.008 | Y24: NETS | AA24: =Z24*0.008 | AD24: NETS | AF24: =AE24*0.008 | AI24: NETS | AK24: =AJ24*0.008
A25: PARKWAY | C25: =B25*10% | E25: PARKWAY | G25: =F25*10% | I25: PARKWAY | K25: =J25*10% | M25: PARKWAY | O25: =N25*10% | U25: PARKWAY | W25: =V25*10% | Y25: PARKWAY | AA25: =Z25*10% | AD25: PARKWAY | AF25: =AE25*10% | AI25: PARKWAY | AK25: =AJ25*10%
A26: PAYNOW | E26: PAYNOW | I26: PAYNOW | M26: PAYNOW | U26: PAYNOW | Y26: PAYNOW | AD26: PAYNOW | AI26: PAYNOW
A27: RHI | E27: RHI | I27: RHI | M27: RHI | U27: RHI | Y27: RHI | AD27: RHI | AI27: RHI
A28: SAH | C28: =B28*8% | E28: SAH | G28: =F28*8% | I28: SAH | K28: =J28*8% | M28: SAH | O28: =N28*8% | U28: SAH | W28: =V28*8% | Y28: SAH | AA28: =Z28*8% | AD28: SAH | AF28: =AE28*8% | AI28: SAH | AK28: =AJ28*8%
A29: UNION PAY | C29: =B29*2.5% | E29: UNION PAY | G29: =F29*2.5% | I29: UNION PAY | K29: =J29*2.5% | M29: UNION PAY | O29: =N29*2.5% | U29: UNION PAY | W29: =V29*2.5% | Y29: UNION PAY | AA29: =Z29*2.5% | AD29: UNION PAY | AF29: =AE29*2.5% | AI29: UNION PAY | AK29: =AJ29*2.5%
A30: VISA | C30: =B30*0.0225 | E30: VISA | G30: =F30*0.0225 | I30: VISA | K30: =J30*0.0225 | M30: VISA | O30: =N30*0.0225 | U30: VISA | W30: =V30*0.0225 | Y30: VISA | AA30: =Z30*0.0225 | AD30: VISA | AF30: =AE30*0.0225 | AI30: VISA | AK30: =AJ30*0.0225
A31: TOTAL INCOME | B31: =SUM(B7:B30) | C31: =SUM(C7:C30) | E31: DR TOTAL INCOME | F31: =SUM(F7:F30) | G31: =SUM(G7:G30) | I31: DR TOTAL INCOME | J31: =SUM(J7:J30) | K31: =SUM(K7:K30) | M31: DR TOTAL INCOME | N31: =SUM(N7:N30) | O31: =SUM(O7:O30) | U31: DR TOTAL INCOME | V31: =SUM(V7:V30) | W31: =SUM(W7:W30) | Y31: DR TOTAL INCOME | Z31: =SUM(Z7:Z30) | AA31: =SUM(AA7:AA30) | AD31: DR TOTAL INCOME | AE31: =SUM(AE7:AE30) | AF31: =SUM(AF7:AF30) | AI31: DR TOTAL INCOME | AJ31: =SUM(AJ7:AJ30) | AK31: =SUM(AK7:AK30)
B33: EXPENSES | F33: DEDUCTIONS | H33: REMARKS | J33: DEDUCTIONS | L33: REMARKS | N33: DEDUCTIONS | P33: REMARKS | R33: DEDUCTIONS | T33: REMARKS | V33: DEDUCTIONS | X33: REMARKS | Z33: DEDUCTIONS | AB33: REMARKS | AE33: DEDUCTIONS | AG33: REMARKS | AJ33: DEDUCTIONS | AL33: REMARKS
B34: ADMIN FEE | C34: =SUM(C7:C30) | F34: ADMIN CHARGES | G34: =G31 | J34: ADMIN CHARGES | K34: =K31 | N34: ADMIN CHARGES | O34: =O31 | R34: ADMIN CHARGES | S34: =#REF! | V34: ADMIN CHARGES | W34: =W31 | Z34: ADMIN CHARGES | AA34: =AA31 | AE34: ADMIN CHARGES | AF34: =AF31 | AJ34: ADMIN CHARGES | AK34: =AK31
B35: GST | C35: =G35+K35+O35+S35+W35+AA35+AF35+AK35 | F35: GST | G35: 0 | J35: GST | N35: GST | R35: GST | V35: GST | Z35: GST | AE35: GST | AJ35: GST
B36: RENTAL | F36: ICC-5 | G36: 0 | J36: ICC-5 | N36: ICC-5 | V36: ICC-5 | Z36: ICC-5 | AE36: ICC-5 | AJ36: ICC-5
B37: LOAN INTEREST | F37: PRODUCTS | J37: PRODUCTS | N37: PRODUCTS | V37: PRODUCTS | Z37: PRODUCTS | AE37: PRODUCTS | AJ37: PRODUCTS
B38: IRAS TAX | F38: ORTHO (B+B) | J38: ORTHO (B+B) | N38: ORTHO (B+B) | V38: ORTHO (B+B) | Z38: ORTHO (B+B) | AE38: ORTHO (B+B) | AJ38: ORTHO (B+B)
B39: CK SECRETARIAL / ACCOUNTS SERVICES | F39: ABUTMENTS | J39: ABUTMENTS | N39: ABUTMENTS | V39: ABUTMENTS | Z39: ABUTMENTS | AE39: ABUTMENTS | AJ39: ABUTMENTS
B40: TOWN COUNCIL | C40: 131.89 | F40: IMPLANT | J40: IMPLANT | N40: IMPLANT | V40: IMPLANT | Z40: IMPLANT | AE40: IMPLANT | AJ40: IMPLANT
B41: SERVICE & CONSERVANCY CHARGES | F41: SKY LAB | J41: SKY LAB | N41: SKY LAB | V41: SKY LAB | Z41: SKY LAB | AE41: SKY LAB | AJ41: SKY LAB
B42: SP | F42: DIGICADCAM | J42: DIGICADCAM | N42: DIGICADCAM | V42: DIGICADCAM | Z42: DIGICADCAM | AE42: DIGICADCAM | AJ42: DIGICADCAM
B43: SINGTEL | F43: OTHER LAB | J43: OTHER LAB | N43: OTHER LAB | V43: OTHER LAB | Z43: OTHER LAB | AE43: OTHER LAB | AJ43: OTHER LAB
B44: PRODUCTS | C44: =G37+K37+O37+S59+W37+AA37+AF37+AK37 | F44: INVISALIGN | J44: INVISALIGN | N44: INVISALIGN | V44: INVISALIGN | Z44: INVISALIGN | AE44: INVISALIGN | AJ44: INVISALIGN
B45: ADMIN STAFF & OFFICE RENTAL | F45: TRANSFER (+) | J45: TRANSFER (+) | N45: TRANSFER (+) | V45: TRANSFER (+) | Z45: TRANSFER (+) | AE45: TRANSFER (+) | AJ45: TRANSFER (+)
B46: SUPPLIERS | F46: TRANSFER (-) | J46: TRANSFER (-) | N46: TRANSFER (-) | V46: TRANSFER (-) | Z46: TRANSFER (-) | AE46: TRANSFER (-) | AJ46: TRANSFER (-)
B47: VOUCHER | C47: =B12 | F47: REFUND/REFERRAL | J47: REFUND/REFERRAL | N47: REFUND/REFERRAL | V47: REFUND | Z47: REFUND | AE47: REFUND | AJ47: REFUND
B48: PETTY CASH | F48: VOUCHER | G48: =F12 | J48: VOUCHER | N48: VOUCHER | V48: VOUCHER | Z48: VOUCHER | AE48: SEDATION | AJ48: SEDATION
B49: STOCKS / CONSUMABLES FEES | F49: RETAINERS/BT/SPLINT | J49: RETAINERS/BT/SPLINT | N49: RETAINERS/BT/SPLINT | V49: RETAINERS/BT/SPLINT | Z49: RETAINERS/BT/SPLINT | AE49: RETAINERS/BT/SPLINT | AJ49: RETAINERS/BT/SPLINT
B50: MARKETING FEE | F50: INSTALLMENT | J50: INSTALLMENT | N50: INSTALLMENT | V50: INSTALLMENT | Z50: INSTALLMENT | AE50: INSTALLMENT | AJ50: INSTALLMENT
B51: INVISALIGN | C51: =G44+K44+O44+S66+W44+AA44+AF44+AK44 | F51: DEDUCTIONS | J51: DEDUCTIONS | N51: DEDUCTIONS | V51: DEDUCTIONS | Z51: DEDUCTIONS | AE51: DEDUCTIONS | AJ51: DEDUCTIONS
B52: IMPLANT | C52: =G40+O40+S62+W40+AA40+AF40+K40+AK40
B53: SKYLAB | C53: =G41+O41+W41+S63+K41+AA41+AF41+AK41 | F53: TOTAL | G53: =F31-G34-G35-G37-G36-G38-G39-G40-G41-G42-G43-G44+G45-G46-G47-G48-G49-G50-G51 | J53: TOTAL | K53: =J31-K34-K35-K36-K37-K38-K39-K40-K41-K42-K43-K44+K45-K46-K47-K48-K49-K50-K51 | N53: TOTAL | O53: =N31-O34-O35-O36-O37-O38-O39-O40-O41-O42-O43-O44+O45-O46-O47-O48-O49-O50-O51 | V53: TOTAL | W53: =V31-W34-W35-W36-W37-W38-W39-W40-W41-W42-W43-W44+W45-W46-W47-W48-W49-W50-W51 | Z53: TOTAL | AA53: =Z31-AA34-AA35-AA36-AA37-AA38-AA39-AA40-AA41-AA42-AA43-AA44+AA45-AA46-AA47-AA48-AA49-AA50-AA51 | AE53: TOTAL | AF53: =AE31-AF34-AF35-AF36-AF37-AF38-AF39-AF40-AF41-AF42-AF43-AF44+AF45-AF46-AF47-AF48-AF49-AF50-AF51 | AJ53: TOTAL | AK53: =AJ31-AK34-AK35-AK36-AK37-AK38-AK39-AK40-AK41-AK42-AK43-AK44+AK45-AK46-AK47-AK48-AK49-AK50-AK51
B54: DIGICADCAM | C54: =G42+O42+W42+AA42+AF42+S64+K42+AK42 | F54: DOCTORS FEE BEFORE DEDUCTION | G54: =G53/2+G55 | J54: DOCTORS FEE BEFORE DEDUCTION | K54: =K53/2+K55 | N54: DOCTORS PAY | O54: =(O53*50%)+O55 | V54: DOCTORS PAY | W54: =(W53*50%)+W55 | Z54: DOCTORS PAY | AA54: =(AA53*50%)+AA55 | AE54: DOCTORS PAY | AF54: =(AF53*50%)+AF55 | AJ54: DOCTORS PAY | AK54: =(AK53*45%)+AK55
B55: OTHER LAB | C55: =G43+O43+K43+S65+W43+AA43+AF43+AK43 | F55: ADJUSTMENTS (+) | J55: ADJUSTMENTS (+) | N55: ADJUSTMENTS (+) | V55: ADJUSTMENTS (+) | Z55: ADJUSTMENTS (+) | AE55: ADJUSTMENTS (+) | AJ55: ADJUSTMENTS (+)
B56: ORTHO (B+B) | C56: =G38+K38+O38+S60+W38+AA38+AF38+AK38 | F56: ADJUSTMENTS (-) | G56: =G61+G65 | H56: ADDN MARKETING& MEDISAVE ADMIN | J56: ADJUSTMENTS (-) | K56: =K61+K65 | L56: ADDN MARKETING | N56: ADJUSTMENTS (-) | O56: =O61+O65 | P56: ADDN MARKETING & MEDISAVE ADMIN | V56: ADJUSTMENTS (-) | W56: =W61+W65 | X56: ADDN MKTRG & MEDISAVE ADMIN | Z56: ADJUSTMENTS (-) | AA56: =AA61+AA65 | AB56: MEDISAVE ADMIN | AE56: ADJUSTMENTS (-) | AF56: =AF61+AF65 | AG56: MARKETING FEE & MEDISAVE ADMIN | AJ56: ADJUSTMENTS (-) | AK56: =AK61+AK65 | AL56: MARKETING FEE & MEDISAVE ADMIN
B57: ABUTMENT | C57: =O39+G39+K39+S61+AA39+W39+AF39+AK39 | F57: NET PAY | G57: =G54-G56 | J57: NET PAY | K57: =K54-K56 | N57: NET PAY | O57: =O54-O56 | V57: NET PAY | W57: =W54-W56 | Z57: NET PAY | AA57: =AA54-AA56 | AE57: NET PAY | AF57: =AF54-AF56 | AJ57: NET PAY | AK57: =AK54-AK56
B58: REFUND / REFERRAL | C58: =G47+K47+O47+S69+W47+AA47+AF47+AK47 | R58: ICC-5
B59: DOCTORS PAY | C59: =G54+K54+O54+W54+AA54+AF54+AK54 | F59: MEDISAVE ADMIN FEE CALCULATION: | J59: MEDISAVE ADMIN FEE CALCULATION: | N59: MEDISAVE ADMIN FEE CALCULATION: | R59: PRODUCTS | V59: MEDISAVE ADMIN FEE CALCULATION: | Z59: MEDISAVE ADMIN FEE CALCULATION: | AE59: MEDISAVE ADMIN FEE CALCULATION: | AJ59: MEDISAVE ADMIN FEE CALCULATION:
B60: NURSE PAY (BASIC PAY) | F60: Medisave Claim | G60: Admin Fee | H60: REMARKS | J60: Medisave Claim | K60: Admin Fee | L60: REMARKS | N60: Medisave Claim | O60: Admin Fee | P60: REMARKS | R60: ORTHO (B+B) | V60: Medisave Claim | W60: Admin Fee | X60: REMARKS | Z60: Medisave Claim | AA60: Admin Fee | AB60: REMARKS | AE60: Medisave Claim | AF60: Admin Fee | AG60: REMARKS | AJ60: Medisave Claim | AK60: Admin Fee | AL60: REMARKS
B61: NURSE PAY (INCENTIVE) | G61: =F61*20 | K61: =J61*20 | O61: =N61*20 | R61: ABUTMENTS | W61: =V61*20 | AA61: =Z61*20 | AF61: =AE61*20 | AK61: =AJ61*20
B62: NURSE TRANSFER FEE | R62: IMPLANT
B63: TANK CULTURE | F63: ADDITIONAL MARKETING: | J63: ADDITIONAL MARKETING: | N63: ADDITIONAL MARKETING: | R63: SKY LAB | V63: ADDITIONAL MARKETING: | Z63: ADDITIONAL MARKETING: | AE63: ADDITIONAL MARKETING: | AJ63: ADDITIONAL MARKETING:
B64: SHARP BIN | F64: MONTH | G64: AMOUNT | H64: REMARKS | J64: MONTH | K64: AMOUNT | L64: REMARKS | N64: MONTH | O64: AMOUNT | P64: REMARKS | R64: DIGICADCAM | V64: MONTH | W64: AMOUNT | X64: REMARKS | Z64: MONTH | AA64: AMOUNT | AB64: REMARKS | AE64: MONTH | AF64: AMOUNT | AG64: REMARKS | AJ64: MONTH | AK64: AMOUNT | AL64: REMARKS
B65: COURIER | C65: 0 | F65: =B3 | G65: 240 | J65: =F65 | K65: 180 | N65: =F65 | O65: 60 | R65: OTHER LAB | V65: =V3 | Z65: =V65 | AE65: =AE3 | AJ65: =AJ3
B66: REPAIR & MAINTENANCE | R66: INVISALIGN
B67: MOM LEVY | C67: 400 | F67: OTHERS: (CPF,PERSONAL REFUND, COURSEFEE) | J67: OTHERS: (CPF,PERSONAL REFUND, COURSEFEE) | N67: OTHERS: (CPF,PERSONAL REFUND, COURSEFEE) | R67: TRANSFER (+) | V67: OTHERS: (CPF,PERSONAL REFUND, COURSEFEE) | Z67: OTHERS: (CPF,PERSONAL REFUND, COURSEFEE) | AE67: OTHERS: (CPF,PERSONAL REFUND, COURSEFEE) | AJ67: OTHERS: (CPF,PERSONAL REFUND, COURSEFEE)
R68: TRANSFER (-)
F69: DETAILS | G69: AMOUNT | J69: DETAILS | K69: AMOUNT | N69: DETAILS | O69: AMOUNT | R69: REFUND | V69: DETAILS | W69: AMOUNT | Z69: DETAILS | AA69: AMOUNT | AE69: DETAILS | AF69: AMOUNT | AJ69: DETAILS | AK69: AMOUNT
R70: VOUCHER
R71: RETAINERS/BT/SPLINT
B72: TOTAL | C72: =B31-C34-C35-C58-C36-C37-C42-C43-C38-C46-C39-C45-C48-C49-C51-C50-C55-C54-C53-C59-C60-C61-C62-C47-C63-C40-C64-C41-C67-C66-C65-C90-C91-C92-C93-C94-C95-C68-C69-C70 | R72: INSTALLMENT
B73: FOR INCENTIVE % | C73: =B31-C34-C35-C58-C42-C43-C46-C45-C48-C44-C49-C50-C47-C63-C40-C64-C41-C65-C93-C95-C94-C66-C92-C90-C68-C69-C70 | R73: DEDUCTIONS
B74: PERCENT | C74: =VLOOKUP(C73,'% RATES INCENTIVES TENGAH'!C:D,2,TRUE)
A75: INCOME LESS GST | B75: =B31-C35 | C75: =C72/B75*100 | D75: % | R75: TOTAL | S75: =#REF!-S34-S35-S59-S58-S60-S61-S62-S63-S64-S65-S66+S67-S68-S69-S70-S71-S72-S73
R76: DOCTORS PAY | S76: =(S75*50%)+S77
B77: MEDISAVE ADMIN | C77: =G61+K61+O61+S83+W61+AA61+AF61+AK61 | D77: =C77/20 | F77: TOTAL PAYMENT | G77: =G57-G70-G74-G75-G71-G72-G73 | J77: TOTAL PAYMENT | K77: =K57-K70-K74-K75-K71-K72-K73 | N77: TOTAL PAYMENT | O77: =O57-O70-O74-O75-O71-O72-O73 | R77: ADJUSTMENTS (+) | V77: TOTAL PAYMENT | W77: =W57-W70-W74-W75-W71-W72-W73 | Z77: TOTAL PAYMENT | AA77: =AA57-AA70-AA74-AA75-AA71-AA72-AA73 | AE77: TOTAL PAYMENT | AF77: =AF57-AF70-AF74-AF75-AF71-AF72-AF73 | AJ77: TOTAL PAYMENT | AK77: =AK57-AK70-AK74-AK75-AK71-AK72-AK73
B78: ADDITIONAL MARKETING | C78: =G65+K65+O65+S87+W65+AA65+AF65 | R78: ADJUSTMENTS (-) | S78: =S83+S87
B79: DOCTORS PERSONAL DEDUCTION | C79: =G70+G74+G75+K70+K74+K75+O70+O74+O75+S92+S96+S97+W70+W74+W75+AA70+AA74+AA75+AF70+AF74+AF75+G71+G72+G73+K71+K72+K73+O71+O72+O73+S93+S94+S95+W71+W72+W73+AA71+AA72+AA73+AF71+AF72+AF73 | R79: NET PAY | S79: =S76-S78
B80: TOTAL | C80: =SUM(C77:C79)
B81: TOTAL ICC-5 | C81: =G36+K36+O36+S58+AA36+W36+AF36+AK36 | R81: MEDISAVE ADMIN FEE CALCULATION:
R82: Medisave Claim | S82: Admin Fee | T82: REMARKS
B83: NURSES FEE-REVENUE | C83: =(C60+C61+C62)/B31 | S83: =R83*20
B84: CONSUMABLE EXCL OFFICE RENT - REVENUE | C84: =(C49+C46+C48)/B31
B85: OFFICE RENT & ADMIN STAFF - REVENUE | C85: =(C45/B31) | R85: ADDITIONAL MARKETING:
B86: MARKETING - REVENUE | C86: =C50/B31 | R86: MONTH | S86: AMOUNT | T86: REMARKS
R87: =R3
R89: OTHERS: (CPF,PERSONAL REFUND, COURSEFEE)
R91: DETAILS | S91: AMOUNT
AH92: feb 2191
R99: TOTAL CHEQUE AMOUNT | S99: =S79-S92-S96-S97-S93-S94-S95

Sheet BOONKENG SETTLEMENT CAL NEW
A3: MONTH/YEAR: | B3: 46023 | E3: MONTH/YEAR: | F3: =B3 | I3: MONTH/YEAR: | J3: =B3 | M3: MONTH/YEAR: | N3: =B3 | Q3: MONTH/YEAR: | R3: =B3 | U3: MONTH/YEAR: | V3: =B3 | Y3: MONTH/YEAR: | Z3: =B3 | AD3: MONTH/YEAR: | AE3: =B3 | AI3: MONTH/YEAR: | AJ3: =AE3 | AN3: MONTH/YEAR: | AO3: =AE3 | AS3: MONTH/YEAR: | AT3: =AO3 | AX3: MONTH/YEAR: | AY3: =V3
A4: BRANCH: | B4: CASA DENTAL BOON KENG PTE LTD | E4: BRANCH: | F4: =B4 | I4: BRANCH: | J4: =B4 | M4: BRANCH: | N4: =B4 | Q4: BRANCH: | R4: CASA DENTAL AMK PTE LTD | U4: BRANCH: | V4: =B4 | Y4: BRANCH: | Z4: =B4 | AD4: BRANCH: | AE4: =B4 | AI4: BRANCH: | AJ4: CASA DENTAL AMK PTE LTD | AN4: BRANCH: | AO4: =AE4 | AS4: BRANCH: | AT4: =AO4 | AX4: BRANCH: | AY4: =V4
A5: ALL PROVIDERS SETTLEMENT | E5: DR CHAN KC | I5: DR AMIT PATEL | M5: DR ESTHER HOH | Q5: DR KALIE | AI5: DR ANDREW YIN | AN5: DR YVETTE CHOW | AS5: DR PETER KEITH | AX5: DR ROLAND FOO
C6: ADMIN CHARGES | G6: ADMIN CHARGES | J6: TOTALS | K6: ADMIN CHARGES | O6: ADMIN CHARGES | S6: ADMIN CHARGES | W6: ADMIN CHARGES | AA6: ADMIN CHARGES | AF6: ADMIN CHARGES | AK6: ADMIN CHARGES | AP6: ADMIN CHARGES | AU6: ADMIN CHARGES | AZ6: ADMIN CHARGES
A7: AIA | C7: =B7*0.05*1.09 | E7: AIA | G7: =F7*0.05*1.09 | I7: AIA | K7: =J7*0.05*1.09 | M7: AIA | O7: =N7*0.05*1.09 | Q7: AIA | S7: =R7*0.05*1.09 | U7: AIA | W7: =V7*0.05*1.09 | Y7: AIA | AA7: =Z7*0.05*1.09 | AD7: AIA | AF7: =AE7*0.05*1.09 | AI7: AIA | AK7: =AJ7*0.05*1.09 | AN7: AIA | AP7: =AO7*0.05*1.09 | AS7: AIA | AU7: =AT7*0.05*1.09 | AX7: AIA | AZ7: =AY7*0.05*1.09
A8: ALLIANCE | C8: =B8*0.05*1.09 | E8: ALLIANCE | G8: =F8*0.05*1.09 | I8: ALLIANCE | K8: =J8*0.05*1.09 | M8: ALLIANCE | O8: =N8*0.05*1.09 | U8: ALLIANCE | W8: =V8*0.05*1.09 | Y8: ALLIANCE | AA8: =Z8*0.05*1.09 | AD8: ALLIANCE | AF8: =AE8*0.05*1.09 | AN8: ALLIANCE | AP8: =AO8*0.05*1.09 | AS8: ALLIANCE | AU8: =AT8*0.05*1.09 | AX8: ALLIANCE | AZ8: =AY8*0.05*1.09
A9: AMEX | C9: =B9*0.0195 | E9: AMEX | G9: =F9*0.0195 | I9: AMEX | K9: =J9*0.0195 | M9: AMEX | O9: =N9*0.0195 | Q9: AMEX | S9: =R9*0.0195 | U9: AMEX | W9: =V9*0.0195 | Y9: AMEX | AA9: =Z9*0.0195 | AD9: AMEX | AF9: =AE9*0.0195 | AI9: AMEX | AK9: =AJ9*0.0195 | AN9: AMEX | AP9: =AO9*0.0195 | AS9: AMEX | AU9: =AT9*0.0195 | AX9: AMEX | AZ9: =AY9*0.0195
A10: BABYBONUS | C10: =B10*0.008 | E10: BABYBONUS | G10: =F10*0.008 | I10: BABYBONUS | K10: =J10*0.008 | M10: BABYBONUS | O10: =N10*0.008 | U10: BABYBONUS | W10: =V10*0.008 | Y10: BABYBONUS | AA10: =Z10*0.008 | AD10: BABYBONUS | AF10: =AE10*0.008 | AN10: BABYBONUS | AP10: =AO10*0.008 | AS10: BABYBONUS | AU10: =AT10*0.008 | AX10: BABYBONUS | AZ10: =AY10*0.008
A11: CASH | E11: CASH | I11: CASH | M11: CASH | Q11: ALLIANCE | S11: =R11*0.05*1.09 | U11: CASH | Y11: CASH | AD11: CASH | AI11: ALLIANCE | AK11: =AJ11*0.05*1.09 | AN11: CASH | AS11: CASH | AX11: CASH
A12: CASA VOUCHER | E12: CASA VOUCHER | I12: CASA VOUCHER | M12: CASA VOUCHER | Q12: CASH | U12: CASA VOUCHER | Y12: CASA VOUCHER | AD12: CASA VOUCHER | AI12: CASH | AN12: CASA VOUCHER | AS12: CASA VOUCHER | AX12: CASA VOUCHER
A13: CDC VOUCHER | E13: CDC VOUCHER | I13: CDC VOUCHER | M13: CDC VOUCHER | Q13: CASA VOUCHER | U13: CDC VOUCHER | Y13: CDC VOUCHER | AD13: CDC VOUCHER | AI13: CASA VOUCHER | AN13: CDC VOUCHER | AS13: CDC VOUCHER | AX13: CDC VOUCHER
A14: CHAS | E14: CHAS | I14: CHAS | M14: CHAS | U14: CHAS | Y14: CHAS | AD14: CHAS | AN14: CHAS | AS14: CHAS | AX14: CHAS
A15: CYNERGY | E15: CYNERGY | I15: CYNERGY | M15: CYNERGY | U15: CYNERGY | Y15: CYNERGY | AD15: CYNERGY | AN15: CYNERGY | AS15: CYNERGY | AX15: CYNERGY
A16: DA ADEPT HEALTH | C16: =B16*8% | E16: DA ADEPT HEALTH | G16: =F16*8% | I16: DA ADEPT HEALTH | K16: =J16*8% | M16: DA ADEPT HEALTH | O16: =N16*8% | U16: DA ADEPT HEALTH | W16: =V16*8% | Y16: DA ADEPT HEALTH | AA16: =Z16*8% | AD16: DA ADEPT HEALTH | AF16: =AE16*8% | AN16: DA ADEPT HEALTH | AP16: =AO16*8% | AS16: DA ADEPT HEALTH | AU16: =AT16*8% | AX16: DA ADEPT HEALTH | AZ16: =AY16*8%
A17: DEPOSIT | C17: =K17+O17 | E17: DEPOSIT | I17: DEPOSIT | M17: DEPOSIT | Q17: DEPOSIT | S17: 0 | U17: DEPOSIT | Y17: DEPOSIT | AD17: DEPOSIT | AI17: DEPOSIT | AN17: DEPOSIT | AS17: DEPOSIT | AX17: DEPOSIT
A18: IHP | C18: =B18*0.051*1.09 | E18: IHP | G18: =F18*0.051*1.09 | I18: IHP | K18: =J18*0.051*1.09 | M18: IHP | O18: =N18*0.051*1.09 | U18: IHP | W18: =V18*0.051*1.09 | Y18: IHP | AA18: =Z18*0.051*1.09 | AD18: IHP | AF18: =AE18*0.051*1.09 | AN18: IHP | AP18: =AO18*0.051*1.09 | AS18: IHP | AU18: =AT18*0.051*1.09 | AX18: IHP | AZ18: =AY18*0.051*1.09
A19: JCB | C19: =B19*0.15*1.09 | E19: JCB | G19: =F19*0.15*1.09 | I19: JCB | K19: =J19*0.15*1.09 | M19: JCB | O19: =N19*0.15*1.09 | U19: JCB | W19: =V19*0.15*1.09 | Y19: JCB | AA19: =Z19*0.15*1.09 | AD19: JCB | AF19: =AE19*0.15*1.09 | AN19: JCB | AP19: =AO19*0.15*1.09 | AS19: JCB | AU19: =AT19*0.15*1.09 | AX19: JCB | AZ19: =AY19*0.15*1.09
A20: MASTER | C20: =B20*0.0225 | E20: MASTER | G20: =F20*0.021 | I20: MASTER | K20: =J20*0.0225 | M20: MASTER | O20: =N20*0.0225 | U20: MASTER | W20: =V20*0.0225 | Y20: MASTER | AA20: =Z20*0.0225 | AD20: MASTER | AF20: =AE20*0.0225 | AN20: MASTER | AP20: =AO20*0.0225 | AS20: MASTER | AU20: =AT20*0.0225 | AX20: MASTER | AZ20: =AY20*0.021
A21: MEDISAVE | E21: MEDISAVE | I21: MEDISAVE | M21: MEDISAVE | U21: MEDISAVE | Y21: MEDISAVE | AD21: MEDISAVE | AN21: MEDISAVE | AS21: MEDISAVE | AX21: MEDISAVE
A22: mednefits | C22: =B22*20% | E22: mednefits | G22: =F22*20% | I22: mednefits | K22: =J22*20% | M22: mednefits | O22: =N22*20% | U22: mednefits | W22: =V22*20% | Y22: mednefits | AA22: =Z22*20% | AD22: mednefits | AF22: =AE22*20% | AN22: mednefits | AP22: =AO22*20% | AS22: mednefits | AU22: =AT22*20% | AX22: mednefits | AZ22: =AY22*20%
A23: MHC | C23: =B23*0.15*1.09 | E23: MHC | G23: =F23*0.15*1.09 | I23: MHC | K23: =J23*0.15*1.09 | M23: MHC | O23: =N23*0.15*1.09 | U23: MHC | W23: =V23*0.15*1.09 | Y23: MHC | AA23: =Z23*0.15*1.09 | AD23: MHC | AF23: =AE23*0.15*1.09 | AN23: MHC | AP23: =AO23*0.15*1.09 | AS23: MHC | AU23: =AT23*0.15*1.09 | AX23: MHC | AZ23: =AY23*0.15*1.09
A24: NETS | C24: =B24*0.008 | E24: NETS | G24: =F24*0.008 | I24: NETS | K24: =J24*0.008 | M24: NETS | O24: =N24*0.008 | U24: NETS | W24: =V24*0.008 | Y24: NETS | AA24: =Z24*0.008 | AD24: NETS | AF24: =AE24*0.008 | AN24: NETS | AP24: =AO24*0.008 | AS24: NETS | AU24: =AT24*0.008 | AX24: NETS | AZ24: =AY24*0.008
A25: PARKWAY | C25: =B25*10% | E25: PARKWAY | G25: =F25*10% | I25: PARKWAY | K25: =J25*10% | M25: PARKWAY | O25: =N25*10% | U25: PARKWAY | W25: =V25*10% | Y25: PARKWAY | AA25: =Z25*10% | AD25: PARKWAY | AF25: =AE25*10% | AN25: PARKWAY | AP25: =AO25*10% | AS25: PARKWAY | AU25: =AT25*10% | AX25: PARKWAY | AZ25: =AY25*10%
A26: PAYNOW | E26: PAYNOW | I26: PAYNOW | M26: PAYNOW | U26: PAYNOW | Y26: PAYNOW | AD26: PAYNOW | AN26: PAYNOW | AS26: PAYNOW | AX26: PAYNOW
A27: RHI | E27: RHI | I27: RHI | M27: RHI | U27: RHI | Y27: RHI | AD27: RHI | AN27: RHI | AS27: RHI | AX27: RHI
A28: SAH | C28: =B28*8% | E28: SAH | G28: =F28*8% | I28: SAH | K28: =J28*8% | M28: SAH | O28: =N28*8% | U28: SAH | W28: =V28*8% | Y28: SAH | AA28: =Z28*8% | AD28: SAH | AF28: =AE28*8% | AN28: SAH | AP28: =AO28*8% | AS28: SAH | AU28: =AT28*8% | AX28: SAH | AZ28: =AY28*8%
A29: UNION PAY | C29: =B29*2.5% | E29: UNION PAY | G29: =F29*2.5% | I29: UNION PAY | K29: =J29*2.5% | M29: UNION PAY | O29: =N29*2.5% | U29: UNION PAY | W29: =V29*2.5% | Y29: UNION PAY | AA29: =Z29*2.5% | AD29: UNION PAY | AF29: =AE29*2.5% | AN29: UNION PAY | AP29: =AO29*2.5% | AS29: UNION PAY | AU29: =AT29*2.5% | AX29: UNION PAY | AZ29: =AY29*2.5%
A30: VISA | C30: =B30*0.0225 | E30: VISA | G30: =F30*0.021 | I30: VISA | K30: =J30*0.0225 | M30: VISA | O30: =N30*0.0225 | U30: VISA | W30: =V30*0.0225 | Y30: VISA | AA30: =Z30*0.0225 | AD30: VISA | AF30: =AE30*0.0225 | AN30: VISA | AP30: =AO30*0.0225 | AS30: VISA | AU30: =AT30*0.0225 | AX30: VISA | AZ30: =AY30*0.021
A31: TOTAL INCOME | B31: =SUM(B7:B30) | C31: =SUM(C7:C30) | E31: DR TOTAL INCOME | F31: =SUM(F7:F30) | G31: =SUM(G7:G30) | I31: DR TOTAL INCOME | J31: =SUM(J7:J30) | K31: =SUM(K7:K30) | M31: DR TOTAL INCOME | N31: =SUM(N7:N30) | O31: =SUM(O7:O30) | U31: DR TOTAL INCOME | V31: =SUM(V7:V30) | W31: =SUM(W7:W30) | Y31: DR TOTAL INCOME | Z31: =SUM(Z7:Z30) | AA31: =SUM(AA7:AA30) | AD31: DR TOTAL INCOME | AE31: =SUM(AE7:AE30) | AF31: =SUM(AF7:AF30) | AN31: DR TOTAL INCOME | AO31: =SUM(AO7:AO30) | AP31: =SUM(AP7:AP30) | AS31: DR TOTAL INCOME | AT31: =SUM(AT7:AT30) | AU31: =SUM(AU7:AU30) | AX31: DR TOTAL INCOME | AY31: =SUM(AY7:AY30) | AZ31: =SUM(AZ7:AZ30)
B33: EXPENSES | F33: DEDUCTIONS | H33: REMARKS | J33: DEDUCTIONS | L33: REMARKS | N33: DEDUCTIONS | P33: REMARKS | R33: DEDUCTIONS | T33: REMARKS | V33: DEDUCTIONS | X33: REMARKS | Z33: DEDUCTIONS | AB33: REMARKS | AE33: DEDUCTIONS | AG33: REMARKS | AJ33: DEDUCTIONS | AL33: REMARKS | AO33: DEDUCTIONS | AQ33: REMARKS | AT33: DEDUCTIONS | AV33: REMARKS | AY33: DEDUCTIONS | BA33: REMARKS
B34: ADMIN FEE | C34: =SUM(C7:C30) | F34: ADMIN CHARGES | G34: =G31 | J34: ADMIN CHARGES | K34: =K31 | N34: ADMIN CHARGES | O34: =O31 | R34: ADMIN CHARGES | S34: =#REF! | V34: ADMIN CHARGES | W34: =W31 | Z34: ADMIN CHARGES | AA34: =AA31 | AE34: ADMIN CHARGES | AF34: =AF31 | AJ34: ADMIN CHARGES | AK34: =#REF! | AO34: ADMIN CHARGES | AP34: =AP31 | AT34: ADMIN CHARGES | AU34: =AU31 | AY34: ADMIN CHARGES | AZ34: =AZ31
B35: GST | C35: =K35+O35+AA35+AF35+AM35+AP35+T35+W35+AU35+AZ35 | F35: GST | J35: GST | N35: GST | R35: GST | V35: GST | Z35: GST | AE35: GST | AJ35: GST | AO35: GST | AT35: GST | AY35: GST
B36: RENTAL | F36: ICC-5 | J36: ICC-5 | N36: ICC-5 | V36: ICC-5 | Z36: ICC-5 | AE36: ICC-5 | AF36: 0 | AO36: ICC-5 | AT36: ICC-5 | AY36: ICC-5
B37: LOAN INTEREST | F37: PRODUCTS | J37: PRODUCTS | N37: PRODUCTS | V37: PRODUCTS | Z37: PRODUCTS | AE37: PRODUCTS | AO37: PRODUCTS | AT37: PRODUCTS | AY37: PRODUCTS
B38: IRAS TAX | F38: ORTHO (B+B) | J38: ORTHO (B+B) | N38: ORTHO (B+B) | V38: ORTHO (B+B) | Z38: ORTHO (B+B) | AE38: ORTHO (B+B) | AO38: ORTHO (B+B) | AT38: ORTHO (B+B) | AY38: ORTHO (B+B)
B39: CK SECRETARIAL / ACCOUNTS SERVICES | F39: ABUTMENTS | J39: ABUTMENTS | N39: ABUTMENTS | V39: ABUTMENTS | Z39: ABUTMENTS | AE39: ABUTMENTS | AO39: ABUTMENTS | AT39: ABUTMENTS | AY39: ABUTMENTS
B40: TOWN COUNCIL | F40: IMPLANT | J40: IMPLANT | N40: IMPLANT | V40: IMPLANT | Z40: IMPLANT | AE40: IMPLANT | AO40: IMPLANT | AT40: IMPLANT | AY40: IMPLANT
B41: SERVICE & CONSERVANCY CHARGES | F41: SKY LAB | J41: SKY LAB | N41: SKY LAB | V41: SKY LAB | Z41: SKY LAB | AE41: SKY LAB | AO41: SKY LAB | AT41: SKY LAB | AY41: SKY LAB
B42: SP | F42: DIGICADCAM | J42: DIGICADCAM | N42: DIGICADCAM | V42: DIGICADCAM | Z42: DIGICADCAM | AE42: DIGICADCAM | AO42: DIGICADCAM | AT42: DIGICADCAM | AY42: DIGICADCAM
B43: SINGTEL | F43: OTHER LAB | J43: OTHER LAB | N43: OTHER LAB | V43: OTHER LAB | Z43: OTHER LAB | AE43: OTHER LAB | AO43: OTHER LAB | AT43: OTHER LAB | AY43: OTHER LAB
B44: PRODUCTS | C44: =G37+K37+O37+S59+W37+AA37+AF37+AK59+AP37+AU37+AZ37 | F44: INVISALIGN | J44: INVISALIGN | N44: INVISALIGN | V44: INVISALIGN | Z44: INVISALIGN | AE44: INVISALIGN | AO44: INVISALIGN | AT44: INVISALIGN | AY44: INVISALIGN
B45: ADMIN STAFF & OFFICE RENTAL | C45: 0 | D45: NOT UNTIL APRIL 2026 | F45: TRANSFER (+) | J45: TRANSFER (+) | N45: TRANSFER (+) | V45: TRANSFER (+) | Z45: TRANSFER (+) | AE45: TRANSFER (+) | AO45: TRANSFER (+) | AT45: TRANSFER (+) | AY45: TRANSFER (+)
B46: SUPPLIERS | F46: TRANSFER (-) | J46: TRANSFER (-) | N46: TRANSFER (-) | V46: TRANSFER (-) | Z46: TRANSFER (-) | AE46: TRANSFER (-) | AO46: TRANSFER (-) | AT46: TRANSFER (-) | AY46: TRANSFER (-)
B47: VOUCHER | C47: =B12 | F47: REFUND/REFERRAL | J47: REFUND/REFERRAL | N47: REFUND/REFERRAL | V47: REFUND | Z47: REFUND | AE47: REFUND | AO47: REFUND | AT47: REFUND | AY47: REFUND
B48: PETTY CASH | F48: VOUCHER | G48: =F12 | J48: VOUCHER | N48: VOUCHER | V48: VOUCHER | Z48: VOUCHER | AE48: SEDATION | AO48: SEDATION | AT48: SEDATION | AY48: SEDATION
B49: STOCKS / CONSUMABLES FEES | F49: RETAINERS/BT/SPLINT | J49: RETAINERS/BT/SPLINT | N49: RETAINERS/BT/SPLINT | V49: RETAINERS/BT/SPLINT | Z49: RETAINERS/BT/SPLINT | AE49: RETAINERS/BT/SPLINT | AO49: RETAINERS/BT/SPLINT | AT49: RETAINERS/BT/SPLINT | AY49: RETAINERS/BT/SPLINT
B50: MARKETING FEE | F50: INSTALLMENT | J50: INSTALLMENT | N50: INSTALLMENT | V50: INSTALLMENT | Z50: INSTALLMENT | AE50: INSTALLMENT | AO50: INSTALLMENT | AT50: INSTALLMENT | AY50: INSTALLMENT
B51: INVISALIGN | C51: =G44+K44+O44+S66+W44+AA44+AF44+AK66+AP44+AU44 | F51: DEDUCTIONS | J51: DEDUCTIONS | N51: DEDUCTIONS | V51: DEDUCTIONS | Z51: DEDUCTIONS | AE51: DEDUCTIONS | AO51: DEDUCTIONS | AT51: DEDUCTIONS | AY51: DEDUCTIONS
B52: IMPLANT | C52: =G40+O40+S62+W40+AA40+AF40+K40+AK62
B53: SKYLAB | C53: =G41+O41+W41+S63+K41+AA41+AF41+AK63 | F53: TOTAL | G53: =F31-G34-G35-G37-G36-G38-G39-G40-G41-G42-G43-G44+G45-G46-G47-G48-G49-G50-G51 | J53: TOTAL | K53: =J31-K34-K35-K36-K37-K38-K39-K40-K41-K42-K43-K44+K45-K46-K47-K48-K49-K50-K51 | N53: TOTAL | O53: =N31-O34-O35-O36-O37-O38-O39-O40-O41-O42-O43-O44+O45-O46-O47-O48-O49-O50-O51 | V53: TOTAL | W53: =V31-W34-W35-W36-W37-W38-W39-W40-W41-W42-W43-W44+W45-W46-W47-W48-W49-W50-W51 | Z53: TOTAL | AA53: =Z31-AA34-AA35-AA36-AA37-AA38-AA39-AA40-AA41-AA42-AA43-AA44+AA45-AA46-AA47-AA48-AA49-AA50-AA51 | AE53: TOTAL | AF53: =AE31-AF34-AF35-AF36-AF37-AF38-AF39-AF40-AF41-AF42-AF43-AF44+AF45-AF46-AF47-AF48-AF49-AF50-AF51 | AO53: TOTAL | AP53: =AO31-AP34-AP35-AP36-AP37-AP38-AP39-AP40-AP41-AP42-AP43-AP44+AP45-AP46-AP47-AP48-AP49-AP50-AP51 | AT53: TOTAL | AU53: =AT31-AU34-AU35-AU36-AU37-AU38-AU39-AU40-AU41-AU42-AU43-AU44+AU45-AU46-AU47-AU48-AU49-AU50-AU51 | AY53: TOTAL | AZ53: =AY31-AZ34-AZ35-AZ36-AZ37-AZ38-AZ39-AZ40-AZ41-AZ42-AZ43-AZ44+AZ45-AZ46-AZ47-AZ48-AZ49-AZ50-AZ51
B54: DIGICADCAM | C54: =G42+O42+W42+AA42+AF42+S64+K42+AK64 | F54: DOCTORS FEE BEFORE DEDUCTION | G54: =G53/2+G55 | J54: DOCTORS FEE BEFORE DEDUCTION | K54: =K53/2+K55 | N54: DOCTORS PAY | O54: =(O53*50%)+O55 | V54: DOCTORS PAY | W54: =(W53*45%)+W55 | Z54: DOCTORS PAY | AA54: =(AA53*45%)+AA55 | AE54: DOCTORS PAY | AF54: =(AF53*50%)+AF55 | AO54: DOCTORS PAY | AP54: =(AP53*45%)+AP55 | AT54: DOCTORS PAY | AU54: =(AU53*50%)+AU55 | AY54: DOCTORS PAY | AZ54: =(AZ53*50%)+AZ55
B55: OTHER LAB | C55: =G43+O43+K43+S65+W43+AA43+AF43+AK65 | F55: ADJUSTMENTS (+) | J55: ADJUSTMENTS (+) | N55: ADJUSTMENTS (+) | V55: ADJUSTMENTS (+) | Z55: ADJUSTMENTS (+) | AE55: ADJUSTMENTS (+) | AO55: ADJUSTMENTS (+) | AT55: ADJUSTMENTS (+) | AY55: ADJUSTMENTS (+)
B56: ORTHO (B+B) | C56: =G38+K38+O38+S60+W38+AA38+AF38+AK60 | F56: ADJUSTMENTS (-) | G56: =G61+G65 | H56: ADDN MARKETING& MEDISAVE ADMIN | J56: ADJUSTMENTS (-) | K56: =K61+K65 | L56: ADDN MARKETING | N56: ADJUSTMENTS (-) | O56: =O61+O65 | P56: ADDN MARKETING & MEDISAVE ADMIN | V56: ADJUSTMENTS (-) | W56: =W61+W65 | X56: ADDN MKTRG & MEDISAVE ADMIN | Z56: ADJUSTMENTS (-) | AA56: =AA61+AA65 | AB56: MARKETING FEE & MEDISAVE ADMIN | AE56: ADJUSTMENTS (-) | AF56: =AF61+AF65 | AG56: MARKETING FEE & MEDISAVE ADMIN | AO56: ADJUSTMENTS (-) | AP56: =AP61+AP65 | AQ56: MARKETING FEE & MEDISAVE ADMIN | AT56: ADJUSTMENTS (-) | AU56: =AU61+AU65 | AV56: MARKETING FEE & MEDISAVE ADMIN | AY56: ADJUSTMENTS (-) | AZ56: =AZ61+AZ65 | BA56: MARKETING FEE & MEDISAVE ADMIN
B57: ABUTMENT | C57: =O39+G39+K39+S61+AA39+W39+AF39+AK61 | F57: NET PAY | G57: =G54-G56 | J57: NET PAY | K57: =K54-K56 | N57: NET PAY | O57: =O54-O56 | V57: NET PAY | W57: =W54-W56 | Z57: NET PAY | AA57: =AA54-AA56 | AE57: NET PAY | AF57: =AF54-AF56 | AO57: NET PAY | AP57: =AP54-AP56 | AT57: NET PAY | AU57: =AU54-AU56 | AY57: NET PAY | AZ57: =AZ54-AZ56
B58: REFUND / REFERRAL | C58: =G47+K47+O47+S69+W47+AA47+AF47+AK69 | R58: ICC-5 | AJ58: ICC-5
B59: DOCTORS PAY | C59: =G54+K54+O54+W54+AA54+AF54+AP54+AU54+AZ54 | F59: MEDISAVE ADMIN FEE CALCULATION: | J59: MEDISAVE ADMIN FEE CALCULATION: | N59: MEDISAVE ADMIN FEE CALCULATION: | R59: PRODUCTS | V59: MEDISAVE ADMIN FEE CALCULATION: | Z59: MEDISAVE ADMIN FEE CALCULATION: | AE59: MEDISAVE ADMIN FEE CALCULATION: | AJ59: PRODUCTS | AO59: MEDISAVE ADMIN FEE CALCULATION: | AT59: MEDISAVE ADMIN FEE CALCULATION: | AY59: MEDISAVE ADMIN FEE CALCULATION:
B60: NURSE PAY (BASIC PAY) | F60: Medisave Claim | G60: Admin Fee | H60: REMARKS | J60: Medisave Claim | K60: Admin Fee | L60: REMARKS | N60: Medisave Claim | O60: Admin Fee | P60: REMARKS | R60: ORTHO (B+B) | V60: Medisave Claim | W60: Admin Fee | X60: REMARKS | Z60: Medisave Claim | AA60: Admin Fee | AB60: REMARKS | AE60: Medisave Claim | AF60: Admin Fee | AG60: REMARKS | AJ60: ORTHO (B+B) | AO60: Medisave Claim | AP60: Admin Fee | AQ60: REMARKS | AT60: Medisave Claim | AU60: Admin Fee | AV60: REMARKS | AY60: Medisave Claim | AZ60: Admin Fee | BA60: REMARKS
B61: NURSE PAY (INCENTIVE) | G61: =F61*20 | K61: =J61*20 | O61: =N61*20 | R61: ABUTMENTS | W61: =V61*20 | AA61: =Z61*20 | AF61: =AE61*20 | AJ61: ABUTMENTS | AP61: =AO61*20 | AU61: =AT61*20 | AZ61: =AY61*20
B62: NURSE TRANSFER FEE | R62: IMPLANT | AJ62: IMPLANT
B63: TANK CULTURE | F63: ADDITIONAL MARKETING: | J63: ADDITIONAL MARKETING: | N63: ADDITIONAL MARKETING: | R63: SKY LAB | V63: ADDITIONAL MARKETING: | Z63: ADDITIONAL MARKETING: | AE63: ADDITIONAL MARKETING: | AJ63: SKY LAB | AO63: ADDITIONAL MARKETING: | AT63: ADDITIONAL MARKETING: | AY63: ADDITIONAL MARKETING:
B64: SHARP BIN | F64: MONTH | G64: AMOUNT | H64: REMARKS | J64: MONTH | K64: AMOUNT | L64: REMARKS | N64: MONTH | O64: AMOUNT | P64: REMARKS | R64: DIGICADCAM | V64: MONTH | W64: AMOUNT | X64: REMARKS | Z64: MONTH | AA64: AMOUNT | AB64: REMARKS | AE64: MONTH | AF64: AMOUNT | AG64: REMARKS | AJ64: DIGICADCAM | AO64: MONTH | AP64: AMOUNT | AQ64: REMARKS | AT64: MONTH | AU64: AMOUNT | AV64: REMARKS | AY64: MONTH | AZ64: AMOUNT | BA64: REMARKS
B65: COURIER | F65: =B3 | J65: =F65 | K65: 240 | N65: =F65 | O65: 240 | R65: OTHER LAB | V65: =V3 | Z65: =V65 | AE65: =AE3 | AJ65: OTHER LAB | AO65: =AO3 | AT65: =AT3 | AY65: =AY3
B66: REPAIR & MAINTENANCE | R66: INVISALIGN | AJ66: INVISALIGN
B67: MOM LEVY | C67: 600 | F67: OTHERS: (CPF,PERSONAL REFUND, COURSEFEE) | J67: OTHERS: (CPF,PERSONAL REFUND, COURSEFEE) | N67: OTHERS: (CPF,PERSONAL REFUND, COURSEFEE) | R67: TRANSFER (+) | V67: OTHERS: (CPF,PERSONAL REFUND, COURSEFEE) | Z67: OTHERS: (CPF,PERSONAL REFUND, COURSEFEE) | AE67: OTHERS: (CPF,PERSONAL REFUND, COURSEFEE) | AJ67: TRANSFER (+) | AO67: OTHERS: (CPF,PERSONAL REFUND, COURSEFEE) | AT67: OTHERS: (CPF,PERSONAL REFUND, COURSEFEE) | AY67: OTHERS: (CPF,PERSONAL REFUND, COURSEFEE)
R68: TRANSFER (-) | AJ68: TRANSFER (-)
F69: DETAILS | G69: AMOUNT | J69: DETAILS | K69: AMOUNT | N69: DETAILS | O69: AMOUNT | R69: REFUND | V69: DETAILS | W69: AMOUNT | Z69: DETAILS | AA69: AMOUNT | AE69: DETAILS | AF69: AMOUNT | AJ69: REFUND | AO69: DETAILS | AP69: AMOUNT | AT69: DETAILS | AU69: AMOUNT | AY69: DETAILS | AZ69: AMOUNT
F70: CPF CONT SALARY | R70: VOUCHER | AJ70: SEDATION
AJ71: RETAINERS/BT/SPLINT
B72: TOTAL | C72: =B31-C34-C35-C58-C36-C37-C42-C43-C38-C46-C39-C45-C48-C49-C51-C50-C55-C54-C53-C59-C60-C61-C62-C47-C63-C40-C64-C41-C67-C66-C65-C90-C91-C92-C93-C94-C95-C68-C69-C70 | AJ72: INSTALLMENT
B73: FOR INCENTIVE % | C73: =B31-C34-C35-C58-C42-C43-C46-C45-C48-C44-C49-C50-C47-C63-C40-C64-C41-C65-C93-C95-C94-C66-C92-C90 | AJ73: DEDUCTIONS
B74: PERCENT | C74: =VLOOKUP(C73,'% RATES INCENTIVES TENGAH'!C:D,2,TRUE)
A75: INCOME LESS GST | B75: =B31-C35 | C75: =C72/B75*100 | D75: % | R75: TOTAL | S75: =#REF!-S34-S35-S59-S58-S60-S61-S62-S63-S64-S65-S66+S67-S68-S69-S70-S71-S72-S73 | AJ75: TOTAL | AK75: =#REF!-AK34-AK35-AK58-AK59-AK60-AK61-AK62-AK63-AK64-AK65-AK66+AK67-AK68-AK69-AK70-AK71-AK72-AK73
R76: DOCTORS PAY | S76: =(S75*50%)+S77 | AJ76: DOCTORS PAY | AK76: =(AK75*50%)+AK77
B77: MEDISAVE ADMIN | C77: =G61+K61+O61+S83+W61+AA61+AF61+AK83 | D77: =C77/20 | F77: TOTAL PAYMENT | G77: =G57-G70-G74-G75-G71-G72-G73 | J77: TOTAL PAYMENT | K77: =K57-K70-K74-K75-K71-K72-K73 | N77: TOTAL PAYMENT | O77: =O57-O70-O74-O75-O71-O72-O73 | R77: ADJUSTMENTS (+) | V77: TOTAL PAYMENT | W77: =W57-W70-W74-W75-W71-W72-W73 | Z77: TOTAL PAYMENT | AA77: =AA57-AA70-AA74-AA75-AA71-AA72-AA73 | AE77: TOTAL PAYMENT | AF77: =AF57-AF70-AF74-AF75-AF71-AF72-AF73 | AJ77: ADJUSTMENTS (+) | AO77: TOTAL PAYMENT | AP77: =AP57-AP70-AP74-AP75-AP71-AP72-AP73 | AT77: TOTAL PAYMENT | AU77: =AU57-AU70-AU74-AU75-AU71-AU72-AU73 | AY77: TOTAL PAYMENT | AZ77: =AZ57-AZ70-AZ74-AZ75-AZ71-AZ72-AZ73
B78: ADDITIONAL MARKETING | C78: =G65+K65+O65+S87+W65+AA65+AF65+AP65+AU65+AZ65 | R78: ADJUSTMENTS (-) | S78: =S83+S87 | AJ78: ADJUSTMENTS (-) | AK78: =AK83+AK87 | AL78: MARKETING FEE & MEDISAVE ADMIN
B79: DOCTORS PERSONAL DEDUCTION | C79: =G70+G74+G75+K70+K74+K75+O70+O74+O75+S92+S96+S97+W70+W74+W75+AA70+AA74+AA75+AF70+AF74+AF75+G71+G72+G73+K71+K72+K73+O71+O72+O73+S93+S94+S95+W71+W72+W73+AA71+AA72+AA73+AF71+AF72+AF73+AP70+AP71+AP72+AP73+AP74+AP75+AU70+AU71+AU72+AU73+AU74+AU75+AZ70+AZ71+AZ72+AZ73+AZ74+AZ75 | R79: NET PAY | S79: =S76-S78 | AJ79: NET PAY | AK79: =AK76-AK78
B80: TOTAL | C80: =SUM(C77:C79)
B81: TOTAL ICC-5 | C81: =G36+K36+O36+S58+AA36+W36+AF36+AP36+AU36+AZ36 | R81: MEDISAVE ADMIN FEE CALCULATION: | AJ81: MEDISAVE ADMIN FEE CALCULATION:
R82: Medisave Claim | S82: Admin Fee | T82: REMARKS | AJ82: Medisave Claim | AK82: Admin Fee | AL82: REMARKS
B83: NURSES FEE-REVENUE | C83: =(C60+C61+C62)/B31 | S83: =R83*20 | AK83: =AJ83*20
B84: CONSUMABLE EXCL OFFICE RENT - REVENUE | C84: =(C49+C46+C48)/B31
B85: OFFICE RENT & ADMIN STAFF - REVENUE | C85: =(C45/B31) | R85: ADDITIONAL MARKETING: | AJ85: ADDITIONAL MARKETING:
B86: MARKETING - REVENUE | C86: =C50/B31 | R86: MONTH | S86: AMOUNT | T86: REMARKS | AJ86: MONTH | AK86: AMOUNT | AL86: REMARKS
R87: =R3 | AJ87: =AJ3
R89: OTHERS: (CPF,PERSONAL REFUND, COURSEFEE) | AJ89: OTHERS: (CPF,PERSONAL REFUND, COURSEFEE)
R91: DETAILS | S91: AMOUNT | AJ91: DETAILS | AK91: AMOUNT
R99: TOTAL CHEQUE AMOUNT | S99: =S79-S92-S96-S97-S93-S94-S95 | AJ99: TOTAL CHEQUE AMOUNT | AK99: =AK79-AK92-AK96-AK97-AK93-AK94-AK95

Sheet % RATES INCENTIVES
B1: Range | C1: Tier | D1: Comm
B2: $110,000 - $119,999 | C2: 110000 | D2: 0.05
B3: $120,000 - $129,999 | C3: 120000 | D3: 0.1
B4: $130,000 - $139,999 | C4: 130000 | D4: 0.15
B5: $140,000 - $149,999 | C5: 140000 | D5: 0.2
B6: $150,000 - $159,999 | C6: 150000 | D6: 0.25
B7: $160,000 - $169,999 | C7: 160000 | D7: 0.3
B8: $170,000 - $179,999 | C8: 170000 | D8: 0.35
B9: $180,000 - $189,999 | C9: 180000 | D9: 0.4
B10: $190,000 - $199,999 | C10: 190000 | D10: 0.45
B11: $200,000 - $209,999 | C11: 200000 | D11: 0.5
B12: $210,000 - $219,999 | C12: 210000 | D12: 0.55
B13: $220,000 - $229,999 | C13: 220000 | D13: 0.6
... B36: $450,000 - $459,999 | C36: 450000 | D36: 1.75
C37: 460000 | D37: 1.8
C38: 470000 | D38: 1.85
C39: 480000 | D39: 1.9
C40: 490000 | D40: 1.95
C41: 500000 | D41: 2
C42: 510000 | D42: 2.05
C43: 520000 | D43: 2.1
C44: 530000 | D44: 2.15
C45: 540000 | D45: 2.2
C46: 550000 | D46: 2.25
C47: 560000 | D47: 2.3
C48: 570000 | D48: 2.35

Sheet % RATES INCENTIVES AMK
B1: Range | C1: Tier | D1: Comm
B2: $130,000 - $139,999 | C2: 130000 | D2: 0.05
B3: $140,000 - $149,999 | C3: 140000 | D3: 0.1
B4: $150,000 - $159,999 | C4: 150000 | D4: 0.15
B5: $160,000 - $169,999 | C5: 160000 | D5: 0.2
B6: $170,000 - $179,999 | C6: 170000 | D6: 0.25
B7: $180,000 - $189,999 | C7: 180000 | D7: 0.3
B8: $190,000 - $199,999 | C8: 190000 | D8: 0.35
B9: $200,000 - $209,999 | C9: 200000 | D9: 0.4
B10: $210,000 - $219,999 | C10: 210000 | D10: 0.45
B11: $220,000 - $229,999 | C11: 220000 | D11: 0.5
B12: $230,000 - $239,999 | C12: 230000 | D12: 0.55
B13: $240,000 - $249,999 | C13: 240000 | D13: 0.6
... B34: $450,000 - $459,999 | C34: 450000 | D34: 1.65
C35: 460000 | D35: 1.7
C36: 470000 | D36: 1.75
C37: 480000 | D37: 1.8
C38: 490000 | D38: 1.85
C39: 500000 | D39: 1.9
C40: 510000 | D40: 1.95
C41: 520000 | D41: 2
C42: 530000 | D42: 2.05
C43: 540000 | D43: 2.1
C44: 550000 | D44: 2.15
C45: 560000 | D45: 2.2
C46: 570000 | D46: 2.25
D47: 2.3
D48: 2.35

Sheet % RATES INCENTIVES HOLLAND
B1: Range | C1: Tier | D1: Comm
B2: $140,000 - $149,999 | C2: 140000 | D2: 0.05
B3: $150,000 - $159,999 | C3: 150000 | D3: 0.1
B4: $160,000 - $169,999 | C4: 160000 | D4: 0.15
B5: $170,000 - $179,999 | C5: 170000 | D5: 0.2
B6: $180,000 - $189,999 | C6: 180000 | D6: 0.25
B7: $190,000 - $199,999 | C7: 190000 | D7: 0.3
B8: $200,000 - $209,999 | C8: 200000 | D8: 0.35
B9: $210,000 - $219,999 | C9: 210000 | D9: 0.4
B10: $220,000 - $229,999 | C10: 220000 | D10: 0.45
B11: $230,000 - $239,999 | C11: 230000 | D11: 0.5
B12: $240,000 - $249,999 | C12: 240000 | D12: 0.55
B13: $250,000 - $259,999 | C13: 250000 | D13: 0.6
... B33: $450,000 - $459,999 | C33: 450000 | D33: 1.6
C34: 460000 | D34: 1.65
C35: 470000 | D35: 1.7
C36: 480000 | D36: 1.75
C37: 490000 | D37: 1.8
C38: 500000 | D38: 1.85
C39: 510000 | D39: 1.9
C40: 520000 | D40: 1.95
C41: 530000 | D41: 2
C42: 540000 | D42: 2.05
C43: 550000 | D43: 2.1
C44: 560000 | D44: 2.15
C45: 570000 | D45: 2.2
D46: 2.25
D47: 2.3
D48: 2.35

Sheet % RATES INCENTIVES TENGAH
B1: Range | C1: Tier | D1: Comm
B2: $80,000 - $89,999 | C2: 80000 | D2: 0.05
B3: $90,000 - $99,999 | C3: 90000 | D3: 0.1
B4: $100,000 - $109,999 | C4: 100000 | D4: 0.15
B5: $110,000 - $119,999 | C5: 110000 | D5: 0.2
B6: $120,000 - $129,999 | C6: 120000 | D6: 0.25
B7: $130,000 - $139,999 | C7: 130000 | D7: 0.3
B8: $140,000 - $149,999 | C8: 140000 | D8: 0.35
B9: $150,000 - $159,999 | C9: 150000 | D9: 0.4
B10: $160,000 - $169,999 | C10: 160000 | D10: 0.45
B11: $170,000 - $179,999 | C11: 170000 | D11: 0.5
B12: $180,000 - $189,999 | C12: 180000 | D12: 0.55
B13: $190,000 - $199,999 | C13: 190000 | D13: 0.6
... B29: $350,000 - $359,999 | C29: 350000 | D29: 1.4
D30: 1.45

Sheet % RATES INCENTIVES WDLS
B1: Range | C1: Tier | D1: Comm
B2: $150,000 - $159,999 | C2: 150000 | D2: 0.025
B3: $160,000 - $169,999 | C3: 160000 | D3: 0.05
B4: $170,000 - $179,999 | C4: 170000 | D4: 0.075
B5: $180,000 - $189,999 | C5: 180000 | D5: 0.1
B6: $190,000 - $199,999 | C6: 190000 | D6: 0.125
B7: $200,000 - $209,999 | C7: 200000 | D7: 0.15
B8: $210,000 - $219,999 | C8: 210000 | D8: 0.15
B9: $220,000 - $229,999 | C9: 220000 | D9: 0.15
B10: $230,000 - $239,999 | C10: 230000 | D10: 0.15
B11: $240,000 - $249,999 | C11: 240000 | D11: 0.15
B12: $250,000 - $259,999 | C12: 250000 | D12: 0.15
B13: $260,000 - $269,999 | C13: 260000 | D13: 0.15
... B22: $350,000 - $359,999 | C22: 350000 | D22: 0.15
D23: 0.15
D24: 0.15
D25: 0.15
D26: 0.15

Sheet % RATES INCENTIVES CLEMENTI
B1: Range | C1: Tier | D1: Comm
B2: $120,000 - $129,999 | C2: 120000 | D2: 0.025
B3: $130,000 - $139,999 | C3: 130000 | D3: 0.05
B4: $140,000 - $149,999 | C4: 140000 | D4: 0.075
B5: $150,000 - $159,999 | C5: 150000 | D5: 0.1
B6: $160,000 - $169,999 | C6: 160000 | D6: 0.125
B7: $170,000 - $179,999 | C7: 170000 | D7: 0.15
B8: $180,000 - $189,999 | C8: 180000 | D8: 0.175
B9: $190,000 - $199,999 | C9: 190000 | D9: 0.2
B10: $200,000 - $209,999 | C10: 200000 | D10: 0.225
B11: $210,000 - $219,999 | C11: 210000 | D11: 0.25
B12: $220,000 - $229,999 | C12: 220000 | D12: 0.275
B13: $230,000 - $239,999 | C13: 230000 | D13: 0.3
... B25: $350,000 - $359,999 | C25: 350000 | D25: 0.6
